Workbook

Sheet Start Here
A1: Thunderdome ZT Production OTA – PWS Requirements & Deliverable Matrix
A2: Built from the PWS "as of 02 SEP 2026" (Agreement Order HC1084-26-9-2023). Replace the yellow cells; everything else calculates.
A4: Key facts (from PWS)
A5: Agreement Number | B5: HC1084-23-9-2000
A6: Agreement Order | B6: HC1084-26-9-2023
A7: Vendor | B7: Booz Allen Hamilton (BAH)
A8: Primary AOR | B8: Brian Abrigo, U.S. Pacific Command (N00038)
A9: Alternate AOR / Property Administrator | B9: Blank in the PWS contact tables – fill in when named
A10: Period of performance | B10: Base 4 May 2026–3 May 2027 · OY1 to 3 May 2028 · OY2 to 3 May 2029 · OY3 to 29 Sep 2029
A12: Settings (drive every date and metric in the workbook)
A13: Award / kickoff date | B13: 46146 | C13: ASSUMED = base period start (4 May 2026). The PWS says "after award" without a date. Enter the real award or kickoff date.
A14: End of period of performance | B14: 47390 | C14: From PWS Period of Performance (OY3 end).
A15: Gov inspection window (business days) | B15: 5 | C15: PWS Deliverables: Government has up to 5 business days; silence = deemed acceptance.
A16: Vendor resubmission window (business days) | B16: 10 | C16: PWS Deliverables: resubmit within 10 business days of a rejection notice.
A17: CAR response (business days) | B17: 5 | C17: PWS Incentives: written reply to a Corrective Action Report within 5 business days.
A18: Monthly/quarterly due offset (business days after period end) | B18: 5 | C18: ASSUMED. The PWS says "as determined by the Government" / "ICW MSR". Change when the COR sets a date.
A19: Target: on-time submissions | B19: 0.95 | C19: PWS Performance Standards, example: 95% of submissions on time.
A20: Target: max deliverables needing rework | B20: 0.05 | C20: PWS Performance Standards, example: fewer than 5% require rework.
A21: AQL: per-task quality level | B21: 0.9 | C21: PWS AQL table for 6.1, 6.2 and 6.3: 90%.
A22: Today (auto) | B22: =TODAY() -> 46306 | C22: Updates when the file opens. Overwrite with a fixed date to freeze a status snapshot.
A24: How the tabs fit together
A25: Deliverables | B25: Master list of A001–A044 straight from the PWS deliverables table. Rollups count what you log.
A26: Submission Log | B26: One row per due date. Pre-filled for the base year (weekly, monthly, quarterly, one-time). Enter submitted date and Government decision; timeliness and deadlines calculate.
A27: PWS Requirements | B27: One row per PWS paragraph: what the Vendor shall do, which deliverables the PWS names, and a gap flag. Owner and status are yours to fill.
A28: Timed Obligations | B28: Every day-count the PWS imposes (1 week, 30/120 days, 5/10 business days, 2 hours, and so on).
A29: Traceability Check | B29: Deliverables table vs. deliverable lists inside the PWS body, paragraph by paragraph.
A30: PWS Issues | B30: Conflicts, gaps and undefined terms found in the PWS that need a Government ruling.
A31: Performance | B31: On-time and rework rates against the PWS targets, plus open-item counts.
A32: Lists | B32: Dropdown sources.
A34: Color key
A35: Blue text on yellow = you enter it
A36: Black on gray = formula, do not overwrite
A38: Read this first
A39: The file ships with no actuals. Every pre-filled due date earlier than Today shows "Overdue" until you enter its submitted date, so the Performance tab reads poorly on day one. Back-fill the Submission Log, or set the award date to the real one, before trusting any rate.
A41: Example row (Submission Log)
A42: WAR wk 1: due Fri 8 May 2026, submitted 8 May, Gov decision "Accepted" → Timeliness = On time.

Sheet Deliverables
A1: Deliverables (PWS A001–A044)
A2: Columns A–J copy the PWS deliverables table. Yellow = yours. Rollups (P–U) read the Submission Log.
A4: ID | B4: Deliverable | C4: PWS ref (per PWS table) | D4: Task group | E4: Data rights | F4: Format | G4: Due (PWS wording) | H4: Distribution | I4: Frequency (PWS wording) | J4: Cadence | K4: Base / Optional | L4: Primary owner | M4: Alternate owner | N4: Gov reviewer (COR/AOR) | O4: Status | P4: Scheduled in log | Q4: Submitted | R4: Accepted | S4: Returned | T4: Overdue | U4: Next open due date | V4: Flags from PWS review
A5: A001 | B5: Implementation Approach and Architecture | C5: 6.1 | D5: 6.1 | E5: OTA Technical Data | F5: Government format | G5: Due Date IAW IMS | H5: Standard Distribution | I5: One-Time, update as needed | J5: One-time + updates | K5: Base | O5: Not Started | P5: =COUNTIF('Submission Log'!$B$5:$B$400,A5) -> 1 | Q5: =COUNTIFS('Submission Log'!$B$5:$B$400,A5,'Submission Log'!$G$5:$G$400,"<>") -> 0 | R5: =COUNTIFS('Submission Log'!$B$5:$B$400,A5,'Submission Log'!$H$5:$H$400,"Accepted")+COUNTIFS('Submission Log'!$B$5:$B$400,A5,'Submission Log'!$H$5:$H$400,"Deemed Accepted") -> 0 | S5: =COUNTIFS('Submission Log'!$B$5:$B$400,A5,'Submission Log'!$H$5:$H$400,"Returned") -> 0 | T5: =COUNTIFS('Submission Log'!$B$5:$B$400,A5,'Submission Log'!$M$5:$M$400,"Overdue") -> 0 | U5: =IFERROR(IF(_xlfn.MINIFS('Submission Log'!$F$5:$F$400,'Submission Log'!$B$5:$B$400,A5,'Submission Log'!$G$5:$G$400,"=",'Submission Log'!$F$5:$F$400,">="&Today)=0,"",_xlfn.MINIFS('Submission Log'!$F$5:$F$400,'Submission Log'!$B$5:$B$400,A5,'Submission Log'!$G$5:$G$400,"=",'Submission Log'!$F$5:$F$400,">="&Today)),"") | V5: Due "IAW IMS" – A017 must exist first (Issue 8).
A6: A002 | B6: ZT Governance Plan | C6: 6.1 | D6: 6.1 | E6: OTA Technical Data | F6: Government format | G6: Due Date IAW IMS | H6: Standard Distribution | I6: One-Time, update as needed | J6: One-time + updates | K6: Base | O6: Not Started | P6: =COUNTIF('Submission Log'!$B$5:$B$400,A6) -> 1 | Q6: =COUNTIFS('Submission Log'!$B$5:$B$400,A6,'Submission Log'!$G$5:$G$400,"<>") -> 0 | R6: =COUNTIFS('Submission Log'!$B$5:$B$400,A6,'Submission Log'!$H$5:$H$400,"Accepted")+COUNTIFS('Submission Log'!$B$5:$B$400,A6,'Submission Log'!$H$5:$H$400,"Deemed Accepted") -> 0 | S6: =COUNTIFS('Submission Log'!$B$5:$B$400,A6,'Submission Log'!$H$5:$H$400,"Returned") -> 0 | T6: =COUNTIFS('Submission Log'!$B$5:$B$400,A6,'Submission Log'!$M$5:$M$400,"Overdue") -> 0 | U6: =IFERROR(IF(_xlfn.MINIFS('Submission Log'!$F$5:$F$400,'Submission Log'!$B$5:$B$400,A6,'Submission Log'!$G$5:$G$400,"=",'Submission Log'!$F$5:$F$400,">="&Today)=0,"",_xlfn.MINIFS('Submission Log'!$F$5:$F$400,'Submission Log'!$B$5:$B$400,A6,'Submission Log'!$G$5:$G$400,"=",'Submission Log'!$F$5:$F$400,">="&Today)),"") | V6: Due "IAW IMS" (Issue 8).
A7: A003 | B7: eMASS Data Entry | C7: 6.2.1 | D7: 6.2 | E7: OTA Technical Data | F7: Government format | G7: Due Date IAW IMS | H7: Standard Distribution | I7: As Needed | J7: As needed | K7: Base | O7: Not Started | P7: =COUNTIF('Submission Log'!$B$5:$B$400,A7) -> 0 | Q7: =COUNTIFS('Submission Log'!$B$5:$B$400,A7,'Submission Log'!$G$5:$G$400,"<>") -> 0 | R7: =COUNTIFS('Submission Log'!$B$5:$B$400,A7,'Submission Log'!$H$5:$H$400,"Accepted")+COUNTIFS('Submission Log'!$B$5:$B$400,A7,'Submission Log'!$H$5:$H$400,"Deemed Accepted") -> 0 | S7: =COUNTIFS('Submission Log'!$B$5:$B$400,A7,'Submission Log'!$H$5:$H$400,"Returned") -> 0 | T7: =COUNTIFS('Submission Log'!$B$5:$B$400,A7,'Submission Log'!$M$5:$M$400,"Overdue") -> 0 | U7: =IFERROR(IF(_xlfn.MINIFS('Submission Log'!$F$5:$F$400,'Submission Log'!$B$5:$B$400,A7,'Submission Log'!$G$5:$G$400,"=",'Submission Log'!$F$5:$F$400,">="&Today)=0,"",_xlfn.MINIFS('Submission Log'!$F$5:$F$400,'Submission Log'!$B$5:$B$400,A7,'Submission Log'!$G$5:$G$400,"=",'Submission Log'!$F$5:$F$400,">="&Today)),"")
A8: A004 | B8: ATO Documentation/ Artifacts | C8: 6.1, 6.2.1 | D8: 6.1 | E8: OTA Technical Data | F8: Government format | G8: Due Date IAW IMS | H8: Standard Distribution | I8: One-Time, update as needed | J8: One-time + updates | K8: Base | O8: Not Started | P8: =COUNTIF('Submission Log'!$B$5:$B$400,A8) -> 1 | Q8: =COUNTIFS('Submission Log'!$B$5:$B$400,A8,'Submission Log'!$G$5:$G$400,"<>") -> 0 | R8: =COUNTIFS('Submission Log'!$B$5:$B$400,A8,'Submission Log'!$H$5:$H$400,"Accepted")+COUNTIFS('Submission Log'!$B$5:$B$400,A8,'Submission Log'!$H$5:$H$400,"Deemed Accepted") -> 0 | S8: =COUNTIFS('Submission Log'!$B$5:$B$400,A8,'Submission Log'!$H$5:$H$400,"Returned") -> 0 | T8: =COUNTIFS('Submission Log'!$B$5:$B$400,A8,'Submission Log'!$M$5:$M$400,"Overdue") -> 0 | U8: =IFERROR(IF(_xlfn.MINIFS('Submission Log'!$F$5:$F$400,'Submission Log'!$B$5:$B$400,A8,'Submission Log'!$G$5:$G$400,"=",'Submission Log'!$F$5:$F$400,">="&Today)=0,"",_xlfn.MINIFS('Submission Log'!$F$5:$F$400,'Submission Log'!$B$5:$B$400,A8,'Submission Log'!$G$5:$G$400,"=",'Submission Log'!$F$5:$F$400,">="&Today)),"") | V8: Due "IAW IMS" (Issue 8).
A9: A005 | B9: POA&Ms including risk acceptance POA&Ms for vulnerabilities that cannot be mitigated and STIGs that cannot be applied. | C9: 6.1, 6.2.1 | D9: 6.1 | E9: OTA Technical Data | F9: Government format | G9: 30 days post vulnerability identification (if vulnerability cannot be mitigated). To be reviewed every 30 days from initial finding. | H9: Standard Distribution | I9: As Needed | J9: As needed | K9: Base | O9: Not Started | P9: =COUNTIF('Submission Log'!$B$5:$B$400,A9) -> 0 | Q9: =COUNTIFS('Submission Log'!$B$5:$B$400,A9,'Submission Log'!$G$5:$G$400,"<>") -> 0 | R9: =COUNTIFS('Submission Log'!$B$5:$B$400,A9,'Submission Log'!$H$5:$H$400,"Accepted")+COUNTIFS('Submission Log'!$B$5:$B$400,A9,'Submission Log'!$H$5:$H$400,"Deemed Accepted") -> 0 | S9: =COUNTIFS('Submission Log'!$B$5:$B$400,A9,'Submission Log'!$H$5:$H$400,"Returned") -> 0 | T9: =COUNTIFS('Submission Log'!$B$5:$B$400,A9,'Submission Log'!$M$5:$M$400,"Overdue") -> 0 | U9: =IFERROR(IF(_xlfn.MINIFS('Submission Log'!$F$5:$F$400,'Submission Log'!$B$5:$B$400,A9,'Submission Log'!$G$5:$G$400,"=",'Submission Log'!$F$5:$F$400,">="&Today)=0,"",_xlfn.MINIFS('Submission Log'!$F$5:$F$400,'Submission Log'!$B$5:$B$400,A9,'Submission Log'!$G$5:$G$400,"=",'Submission Log'!$F$5:$F$400,">="&Today)),"") | V9: Body says CAT I POA&M if no fix in 1 week; table says 30 days (Issue 3).
A10: A006 | B10: STIG/SRG Checklists | C10: 6.1, 6.2.1 | D10: 6.1 | E10: OTA Technical Data | F10: Government format | G10: Routine Updates | H10: Standard Distribution | I10: Quarterly | J10: Quarterly | K10: Base | O10: Not Started | P10: =COUNTIF('Submission Log'!$B$5:$B$400,A10) -> 4 | Q10: =COUNTIFS('Submission Log'!$B$5:$B$400,A10,'Submission Log'!$G$5:$G$400,"<>") -> 0 | R10: =COUNTIFS('Submission Log'!$B$5:$B$400,A10,'Submission Log'!$H$5:$H$400,"Accepted")+COUNTIFS('Submission Log'!$B$5:$B$400,A10,'Submission Log'!$H$5:$H$400,"Deemed Accepted") -> 0 | S10: =COUNTIFS('Submission Log'!$B$5:$B$400,A10,'Submission Log'!$H$5:$H$400,"Returned") -> 0 | T10: =COUNTIFS('Submission Log'!$B$5:$B$400,A10,'Submission Log'!$M$5:$M$400,"Overdue") -> 1 | U10: =IFERROR(IF(_xlfn.MINIFS('Submission Log'!$F$5:$F$400,'Submission Log'!$B$5:$B$400,A10,'Submission Log'!$G$5:$G$400,"=",'Submission Log'!$F$5:$F$400,">="&Today)=0,"",_xlfn.MINIFS('Submission Log'!$F$5:$F$400,'Submission Log'!$B$5:$B$400,A10,'Submission Log'!$G$5:$G$400,"=",'Submission Log'!$F$5:$F$400,">="&Today)),"") -> 46332
A11: A007 | B11: ACAS Scans | C11: 6.1, 6.2.1 | D11: 6.1 | E11: OTA Technical Data | F11: Vendor format/ Government Approved | G11: As Needed | H11: Standard Distribution | I11: Weekly | J11: Weekly | K11: Base | O11: Not Started | P11: =COUNTIF('Submission Log'!$B$5:$B$400,A11) -> 52 | Q11: =COUNTIFS('Submission Log'!$B$5:$B$400,A11,'Submission Log'!$G$5:$G$400,"<>") -> 0 | R11: =COUNTIFS('Submission Log'!$B$5:$B$400,A11,'Submission Log'!$H$5:$H$400,"Accepted")+COUNTIFS('Submission Log'!$B$5:$B$400,A11,'Submission Log'!$H$5:$H$400,"Deemed Accepted") -> 0 | S11: =COUNTIFS('Submission Log'!$B$5:$B$400,A11,'Submission Log'!$H$5:$H$400,"Returned") -> 0 | T11: =COUNTIFS('Submission Log'!$B$5:$B$400,A11,'Submission Log'!$M$5:$M$400,"Overdue") -> 23 | U11: =IFERROR(IF(_xlfn.MINIFS('Submission Log'!$F$5:$F$400,'Submission Log'!$B$5:$B$400,A11,'Submission Log'!$G$5:$G$400,"=",'Submission Log'!$F$5:$F$400,">="&Today)=0,"",_xlfn.MINIFS('Submission Log'!$F$5:$F$400,'Submission Log'!$B$5:$B$400,A11,'Submission Log'!$G$5:$G$400,"=",'Submission Log'!$F$5:$F$400,">="&Today)),"") -> 46311
A12: A008 | B12: System Change Requests Form/ Configuration Change Request | C12: 6.2.1 | D12: 6.2 | E12: OTA Technical Data | F12: Government Format | G12: As needed | H12: Standard Distribution | I12: As required | J12: As needed | K12: Base | O12: Not Started | P12: =COUNTIF('Submission Log'!$B$5:$B$400,A12) -> 0 | Q12: =COUNTIFS('Submission Log'!$B$5:$B$400,A12,'Submission Log'!$G$5:$G$400,"<>") -> 0 | R12: =COUNTIFS('Submission Log'!$B$5:$B$400,A12,'Submission Log'!$H$5:$H$400,"Accepted")+COUNTIFS('Submission Log'!$B$5:$B$400,A12,'Submission Log'!$H$5:$H$400,"Deemed Accepted") -> 0 | S12: =COUNTIFS('Submission Log'!$B$5:$B$400,A12,'Submission Log'!$H$5:$H$400,"Returned") -> 0 | T12: =COUNTIFS('Submission Log'!$B$5:$B$400,A12,'Submission Log'!$M$5:$M$400,"Overdue") -> 0 | U12: =IFERROR(IF(_xlfn.MINIFS('Submission Log'!$F$5:$F$400,'Submission Log'!$B$5:$B$400,A12,'Submission Log'!$G$5:$G$400,"=",'Submission Log'!$F$5:$F$400,">="&Today)=0,"",_xlfn.MINIFS('Submission Log'!$F$5:$F$400,'Submission Log'!$B$5:$B$400,A12,'Submission Log'!$G$5:$G$400,"=",'Submission Log'!$F$5:$F$400,">="&Today)),"")
A13: A009 | B13: eMASS Package | C13: 6.2.1 | D13: 6.2 | E13: OTA Technical Data | F13: Government Format | G13: As needed | H13: Standard Distribution | I13: One-Time per package, update as needed | J13: One-time + updates | K13: Base | O13: Not Started | P13: =COUNTIF('Submission Log'!$B$5:$B$400,A13) -> 0 | Q13: =COUNTIFS('Submission Log'!$B$5:$B$400,A13,'Submission Log'!$G$5:$G$400,"<>") -> 0 | R13: =COUNTIFS('Submission Log'!$B$5:$B$400,A13,'Submission Log'!$H$5:$H$400,"Accepted")+COUNTIFS('Submission Log'!$B$5:$B$400,A13,'Submission Log'!$H$5:$H$400,"Deemed Accepted") -> 0 | S13: =COUNTIFS('Submission Log'!$B$5:$B$400,A13,'Submission Log'!$H$5:$H$400,"Returned") -> 0 | T13: =COUNTIFS('Submission Log'!$B$5:$B$400,A13,'Submission Log'!$M$5:$M$400,"Overdue") -> 0 | U13: =IFERROR(IF(_xlfn.MINIFS('Submission Log'!$F$5:$F$400,'Submission Log'!$B$5:$B$400,A13,'Submission Log'!$G$5:$G$400,"=",'Submission Log'!$F$5:$F$400,">="&Today)=0,"",_xlfn.MINIFS('Submission Log'!$F$5:$F$400,'Submission Log'!$B$5:$B$400,A13,'Submission Log'!$G$5:$G$400,"=",'Submission Log'!$F$5:$F$400,">="&Today)),"")
A14: A010 | B14: Status updates on Security patches/hot fixes, OPORD, TASK ORDER, FISMA, PPSM, IAVM and STIGs | C14: 6.2.1 | D14: 6.2 | E14: OTA Technical Data | F14: Vendor format/ Government Approved | G14: As needed | H14: Standard Distribution | I14: As required | J14: As needed | K14: Base | O14: Not Started | P14: =COUNTIF('Submission Log'!$B$5:$B$400,A14) -> 0 | Q14: =COUNTIFS('Submission Log'!$B$5:$B$400,A14,'Submission Log'!$G$5:$G$400,"<>") -> 0 | R14: =COUNTIFS('Submission Log'!$B$5:$B$400,A14,'Submission Log'!$H$5:$H$400,"Accepted")+COUNTIFS('Submission Log'!$B$5:$B$400,A14,'Submission Log'!$H$5:$H$400,"Deemed Accepted") -> 0 | S14: =COUNTIFS('Submission Log'!$B$5:$B$400,A14,'Submission Log'!$H$5:$H$400,"Returned") -> 0 | T14: =COUNTIFS('Submission Log'!$B$5:$B$400,A14,'Submission Log'!$M$5:$M$400,"Overdue") -> 0 | U14: =IFERROR(IF(_xlfn.MINIFS('Submission Log'!$F$5:$F$400,'Submission Log'!$B$5:$B$400,A14,'Submission Log'!$G$5:$G$400,"=",'Submission Log'!$F$5:$F$400,">="&Today)=0,"",_xlfn.MINIFS('Submission Log'!$F$5:$F$400,'Submission Log'!$B$5:$B$400,A14,'Submission Log'!$G$5:$G$400,"=",'Submission Log'!$F$5:$F$400,">="&Today)),"")
A15: A011 | B15: Incident Response Plan | C15: 6.2.1 | D15: 6.2 | E15: OTA Technical Data | F15: Government format | G15: Due Date IAW IMS | H15: Standard Distribution | I15: One-Time, update as needed | J15: One-time + updates | K15: Base | O15: Not Started | P15: =COUNTIF('Submission Log'!$B$5:$B$400,A15) -> 1 | Q15: =COUNTIFS('Submission Log'!$B$5:$B$400,A15,'Submission Log'!$G$5:$G$400,"<>") -> 0 | R15: =COUNTIFS('Submission Log'!$B$5:$B$400,A15,'Submission Log'!$H$5:$H$400,"Accepted")+COUNTIFS('Submission Log'!$B$5:$B$400,A15,'Submission Log'!$H$5:$H$400,"Deemed Accepted") -> 0 | S15: =COUNTIFS('Submission Log'!$B$5:$B$400,A15,'Submission Log'!$H$5:$H$400,"Returned") -> 0 | T15: =COUNTIFS('Submission Log'!$B$5:$B$400,A15,'Submission Log'!$M$5:$M$400,"Overdue") -> 0 | U15: =IFERROR(IF(_xlfn.MINIFS('Submission Log'!$F$5:$F$400,'Submission Log'!$B$5:$B$400,A15,'Submission Log'!$G$5:$G$400,"=",'Submission Log'!$F$5:$F$400,">="&Today)=0,"",_xlfn.MINIFS('Submission Log'!$F$5:$F$400,'Submission Log'!$B$5:$B$400,A15,'Submission Log'!$G$5:$G$400,"=",'Submission Log'!$F$5:$F$400,">="&Today)),"") | V15: Due "IAW IMS" (Issue 8).
A16: A012 | B16: Security Monitoring Reports | C16: 6.2.1 | D16: 6.2 | E16: OTA Technical Data | F16: Government format | G16: Routine Updates | H16: Standard Distribution | I16: Quarterly | J16: Quarterly | K16: Base | O16: Not Started | P16: =COUNTIF('Submission Log'!$B$5:$B$400,A16) -> 4 | Q16: =COUNTIFS('Submission Log'!$B$5:$B$400,A16,'Submission Log'!$G$5:$G$400,"<>") -> 0 | R16: =COUNTIFS('Submission Log'!$B$5:$B$400,A16,'Submission Log'!$H$5:$H$400,"Accepted")+COUNTIFS('Submission Log'!$B$5:$B$400,A16,'Submission Log'!$H$5:$H$400,"Deemed Accepted") -> 0 | S16: =COUNTIFS('Submission Log'!$B$5:$B$400,A16,'Submission Log'!$H$5:$H$400,"Returned") -> 0 | T16: =COUNTIFS('Submission Log'!$B$5:$B$400,A16,'Submission Log'!$M$5:$M$400,"Overdue") -> 1 | U16: =IFERROR(IF(_xlfn.MINIFS('Submission Log'!$F$5:$F$400,'Submission Log'!$B$5:$B$400,A16,'Submission Log'!$G$5:$G$400,"=",'Submission Log'!$F$5:$F$400,">="&Today)=0,"",_xlfn.MINIFS('Submission Log'!$F$5:$F$400,'Submission Log'!$B$5:$B$400,A16,'Submission Log'!$G$5:$G$400,"=",'Submission Log'!$F$5:$F$400,">="&Today)),"") -> 46332 | V16: Same title as A040 (Issue 20).
A17: A013 | B17: Vulnerability Scan Reports | C17: 6.2.1 | D17: 6.2 | E17: OTA Technical Data | F17: Government format | G17: Routine Updates | H17: Standard Distribution | I17: Quarterly | J17: Quarterly | K17: Base | O17: Not Started | P17: =COUNTIF('Submission Log'!$B$5:$B$400,A17) -> 4 | Q17: =COUNTIFS('Submission Log'!$B$5:$B$400,A17,'Submission Log'!$G$5:$G$400,"<>") -> 0 | R17: =COUNTIFS('Submission Log'!$B$5:$B$400,A17,'Submission Log'!$H$5:$H$400,"Accepted")+COUNTIFS('Submission Log'!$B$5:$B$400,A17,'Submission Log'!$H$5:$H$400,"Deemed Accepted") -> 0 | S17: =COUNTIFS('Submission Log'!$B$5:$B$400,A17,'Submission Log'!$H$5:$H$400,"Returned") -> 0 | T17: =COUNTIFS('Submission Log'!$B$5:$B$400,A17,'Submission Log'!$M$5:$M$400,"Overdue") -> 1 | U17: =IFERROR(IF(_xlfn.MINIFS('Submission Log'!$F$5:$F$400,'Submission Log'!$B$5:$B$400,A17,'Submission Log'!$G$5:$G$400,"=",'Submission Log'!$F$5:$F$400,">="&Today)=0,"",_xlfn.MINIFS('Submission Log'!$F$5:$F$400,'Submission Log'!$B$5:$B$400,A17,'Submission Log'!$G$5:$G$400,"=",'Submission Log'!$F$5:$F$400,">="&Today)),"") -> 46332
A18: A014 | B18: Compliance Documentation | C18: 6.2.1 | D18: 6.2 | E18: OTA Work | F18: Vendor Determined Format | G18: 90 Days after award | H18: Standard Distribution | I18: One per accreditation package | J18: Per package | K18: Base | O18: Not Started | P18: =COUNTIF('Submission Log'!$B$5:$B$400,A18) -> 1 | Q18: =COUNTIFS('Submission Log'!$B$5:$B$400,A18,'Submission Log'!$G$5:$G$400,"<>") -> 0 | R18: =COUNTIFS('Submission Log'!$B$5:$B$400,A18,'Submission Log'!$H$5:$H$400,"Accepted")+COUNTIFS('Submission Log'!$B$5:$B$400,A18,'Submission Log'!$H$5:$H$400,"Deemed Accepted") -> 0 | S18: =COUNTIFS('Submission Log'!$B$5:$B$400,A18,'Submission Log'!$H$5:$H$400,"Returned") -> 0 | T18: =COUNTIFS('Submission Log'!$B$5:$B$400,A18,'Submission Log'!$M$5:$M$400,"Overdue") -> 1 | U18: =IFERROR(IF(_xlfn.MINIFS('Submission Log'!$F$5:$F$400,'Submission Log'!$B$5:$B$400,A18,'Submission Log'!$G$5:$G$400,"=",'Submission Log'!$F$5:$F$400,">="&Today)=0,"",_xlfn.MINIFS('Submission Log'!$F$5:$F$400,'Submission Log'!$B$5:$B$400,A18,'Submission Log'!$G$5:$G$400,"=",'Submission Log'!$F$5:$F$400,">="&Today)),"")
A19: A015 | B19: Security Assessment Report | C19: 6.2.1 | D19: 6.2 | E19: OTA Work | F19: Vendor Determined Format | G19: ICW Accreditation | H19: Standard Distribution | I19: One per accreditation package | J19: Per package | K19: Base | O19: Not Started | P19: =COUNTIF('Submission Log'!$B$5:$B$400,A19) -> 1 | Q19: =COUNTIFS('Submission Log'!$B$5:$B$400,A19,'Submission Log'!$G$5:$G$400,"<>") -> 0 | R19: =COUNTIFS('Submission Log'!$B$5:$B$400,A19,'Submission Log'!$H$5:$H$400,"Accepted")+COUNTIFS('Submission Log'!$B$5:$B$400,A19,'Submission Log'!$H$5:$H$400,"Deemed Accepted") -> 0 | S19: =COUNTIFS('Submission Log'!$B$5:$B$400,A19,'Submission Log'!$H$5:$H$400,"Returned") -> 0 | T19: =COUNTIFS('Submission Log'!$B$5:$B$400,A19,'Submission Log'!$M$5:$M$400,"Overdue") -> 0 | U19: =IFERROR(IF(_xlfn.MINIFS('Submission Log'!$F$5:$F$400,'Submission Log'!$B$5:$B$400,A19,'Submission Log'!$G$5:$G$400,"=",'Submission Log'!$F$5:$F$400,">="&Today)=0,"",_xlfn.MINIFS('Submission Log'!$F$5:$F$400,'Submission Log'!$B$5:$B$400,A19,'Submission Log'!$G$5:$G$400,"=",'Submission Log'!$F$5:$F$400,">="&Today)),"")
A20: A016 | B20: Briefings Slides | C20: 6.1, 6.2.2, 6.3.2.1, 6.3.2.4, 6.3.3.1 | D20: 6.1 | E20: OTA Technical Data | F20: Vendor Determined Format | G20: As determined by the Government | H20: Standard Distribution | I20: As required | J20: As needed | K20: Base | O20: Not Started | P20: =COUNTIF('Submission Log'!$B$5:$B$400,A20) -> 0 | Q20: =COUNTIFS('Submission Log'!$B$5:$B$400,A20,'Submission Log'!$G$5:$G$400,"<>") -> 0 | R20: =COUNTIFS('Submission Log'!$B$5:$B$400,A20,'Submission Log'!$H$5:$H$400,"Accepted")+COUNTIFS('Submission Log'!$B$5:$B$400,A20,'Submission Log'!$H$5:$H$400,"Deemed Accepted") -> 0 | S20: =COUNTIFS('Submission Log'!$B$5:$B$400,A20,'Submission Log'!$H$5:$H$400,"Returned") -> 0 | T20: =COUNTIFS('Submission Log'!$B$5:$B$400,A20,'Submission Log'!$M$5:$M$400,"Overdue") -> 0 | U20: =IFERROR(IF(_xlfn.MINIFS('Submission Log'!$F$5:$F$400,'Submission Log'!$B$5:$B$400,A20,'Submission Log'!$G$5:$G$400,"=",'Submission Log'!$F$5:$F$400,">="&Today)=0,"",_xlfn.MINIFS('Submission Log'!$F$5:$F$400,'Submission Log'!$B$5:$B$400,A20,'Submission Log'!$G$5:$G$400,"=",'Submission Log'!$F$5:$F$400,">="&Today)),"")
A21: A017 | B21: Integrated Master Schedule | C21: 6.3.1 | D21: 6.3 | E21: OTA Work | F21: Vendor Determined Format | G21: As determined by the Government | H21: Standard Distribution | I21: One per month | J21: Monthly | K21: Base | O21: Not Started | P21: =COUNTIF('Submission Log'!$B$5:$B$400,A21) -> 12 | Q21: =COUNTIFS('Submission Log'!$B$5:$B$400,A21,'Submission Log'!$G$5:$G$400,"<>") -> 0 | R21: =COUNTIFS('Submission Log'!$B$5:$B$400,A21,'Submission Log'!$H$5:$H$400,"Accepted")+COUNTIFS('Submission Log'!$B$5:$B$400,A21,'Submission Log'!$H$5:$H$400,"Deemed Accepted") -> 0 | S21: =COUNTIFS('Submission Log'!$B$5:$B$400,A21,'Submission Log'!$H$5:$H$400,"Returned") -> 0 | T21: =COUNTIFS('Submission Log'!$B$5:$B$400,A21,'Submission Log'!$M$5:$M$400,"Overdue") -> 5 | U21: =IFERROR(IF(_xlfn.MINIFS('Submission Log'!$F$5:$F$400,'Submission Log'!$B$5:$B$400,A21,'Submission Log'!$G$5:$G$400,"=",'Submission Log'!$F$5:$F$400,">="&Today)=0,"",_xlfn.MINIFS('Submission Log'!$F$5:$F$400,'Submission Log'!$B$5:$B$400,A21,'Submission Log'!$G$5:$G$400,"=",'Submission Log'!$F$5:$F$400,">="&Today)),"") -> 46332
A22: A018 | B22: Monthly Progress Report (MPR) (including Invoice Data, ODC Data, Travel Data) | C22: 6.3.1.1 | D22: 6.3 | E22: OTA Work | F22: Vendor Determined Format | G22: As determined by the Government | H22: Standard Distribution | I22: One per month | J22: Monthly | K22: Base | O22: Not Started | P22: =COUNTIF('Submission Log'!$B$5:$B$400,A22) -> 12 | Q22: =COUNTIFS('Submission Log'!$B$5:$B$400,A22,'Submission Log'!$G$5:$G$400,"<>") -> 0 | R22: =COUNTIFS('Submission Log'!$B$5:$B$400,A22,'Submission Log'!$H$5:$H$400,"Accepted")+COUNTIFS('Submission Log'!$B$5:$B$400,A22,'Submission Log'!$H$5:$H$400,"Deemed Accepted") -> 0 | S22: =COUNTIFS('Submission Log'!$B$5:$B$400,A22,'Submission Log'!$H$5:$H$400,"Returned") -> 0 | T22: =COUNTIFS('Submission Log'!$B$5:$B$400,A22,'Submission Log'!$M$5:$M$400,"Overdue") -> 5 | U22: =IFERROR(IF(_xlfn.MINIFS('Submission Log'!$F$5:$F$400,'Submission Log'!$B$5:$B$400,A22,'Submission Log'!$G$5:$G$400,"=",'Submission Log'!$F$5:$F$400,">="&Today)=0,"",_xlfn.MINIFS('Submission Log'!$F$5:$F$400,'Submission Log'!$B$5:$B$400,A22,'Submission Log'!$G$5:$G$400,"=",'Submission Log'!$F$5:$F$400,">="&Today)),"") -> 46332
A23: A019 | B23: Weekly Activity Report (WAR) | C23: 6.3.1.2, 6.3.1.4 | D23: 6.3 | E23: OTA Work | F23: Vendor Determined Format | G23: Every Friday | H23: Standard Distribution | I23: Weekly | J23: Weekly | K23: Base | O23: Not Started | P23: =COUNTIF('Submission Log'!$B$5:$B$400,A23) -> 52 | Q23: =COUNTIFS('Submission Log'!$B$5:$B$400,A23,'Submission Log'!$G$5:$G$400,"<>") -> 0 | R23: =COUNTIFS('Submission Log'!$B$5:$B$400,A23,'Submission Log'!$H$5:$H$400,"Accepted")+COUNTIFS('Submission Log'!$B$5:$B$400,A23,'Submission Log'!$H$5:$H$400,"Deemed Accepted") -> 0 | S23: =COUNTIFS('Submission Log'!$B$5:$B$400,A23,'Submission Log'!$H$5:$H$400,"Returned") -> 0 | T23: =COUNTIFS('Submission Log'!$B$5:$B$400,A23,'Submission Log'!$M$5:$M$400,"Overdue") -> 23 | U23: =IFERROR(IF(_xlfn.MINIFS('Submission Log'!$F$5:$F$400,'Submission Log'!$B$5:$B$400,A23,'Submission Log'!$G$5:$G$400,"=",'Submission Log'!$F$5:$F$400,">="&Today)=0,"",_xlfn.MINIFS('Submission Log'!$F$5:$F$400,'Submission Log'!$B$5:$B$400,A23,'Submission Log'!$G$5:$G$400,"=",'Submission Log'!$F$5:$F$400,">="&Today)),"") -> 46311
A24: A020 | B24: Technical Library Documentation Report | C24: 6.3.1.7 | D24: 6.3 | E24: OTA Work | F24: Vendor Determined Format | G24: ICW MSR | H24: Standard Distribution | I24: Once per month | J24: Monthly | K24: Base | O24: Not Started | P24: =COUNTIF('Submission Log'!$B$5:$B$400,A24) -> 12 | Q24: =COUNTIFS('Submission Log'!$B$5:$B$400,A24,'Submission Log'!$G$5:$G$400,"<>") -> 0 | R24: =COUNTIFS('Submission Log'!$B$5:$B$400,A24,'Submission Log'!$H$5:$H$400,"Accepted")+COUNTIFS('Submission Log'!$B$5:$B$400,A24,'Submission Log'!$H$5:$H$400,"Deemed Accepted") -> 0 | S24: =COUNTIFS('Submission Log'!$B$5:$B$400,A24,'Submission Log'!$H$5:$H$400,"Returned") -> 0 | T24: =COUNTIFS('Submission Log'!$B$5:$B$400,A24,'Submission Log'!$M$5:$M$400,"Overdue") -> 5 | U24: =IFERROR(IF(_xlfn.MINIFS('Submission Log'!$F$5:$F$400,'Submission Log'!$B$5:$B$400,A24,'Submission Log'!$G$5:$G$400,"=",'Submission Log'!$F$5:$F$400,">="&Today)=0,"",_xlfn.MINIFS('Submission Log'!$F$5:$F$400,'Submission Log'!$B$5:$B$400,A24,'Submission Log'!$G$5:$G$400,"=",'Submission Log'!$F$5:$F$400,">="&Today)),"") -> 46332 | V24: "ICW MSR" is undefined (Issue 7).
A25: A021 | B25: Technical Briefing/ Presentation | C25: 6.3.1.7 | D25: 6.3 | E25: OTA Work | F25: Vendor Determined Format | G25: ICW MSR | H25: Standard Distribution | I25: One per month | J25: Monthly | K25: Base | O25: Not Started | P25: =COUNTIF('Submission Log'!$B$5:$B$400,A25) -> 12 | Q25: =COUNTIFS('Submission Log'!$B$5:$B$400,A25,'Submission Log'!$G$5:$G$400,"<>") -> 0 | R25: =COUNTIFS('Submission Log'!$B$5:$B$400,A25,'Submission Log'!$H$5:$H$400,"Accepted")+COUNTIFS('Submission Log'!$B$5:$B$400,A25,'Submission Log'!$H$5:$H$400,"Deemed Accepted") -> 0 | S25: =COUNTIFS('Submission Log'!$B$5:$B$400,A25,'Submission Log'!$H$5:$H$400,"Returned") -> 0 | T25: =COUNTIFS('Submission Log'!$B$5:$B$400,A25,'Submission Log'!$M$5:$M$400,"Overdue") -> 5 | U25: =IFERROR(IF(_xlfn.MINIFS('Submission Log'!$F$5:$F$400,'Submission Log'!$B$5:$B$400,A25,'Submission Log'!$G$5:$G$400,"=",'Submission Log'!$F$5:$F$400,">="&Today)=0,"",_xlfn.MINIFS('Submission Log'!$F$5:$F$400,'Submission Log'!$B$5:$B$400,A25,'Submission Log'!$G$5:$G$400,"=",'Submission Log'!$F$5:$F$400,">="&Today)),"") -> 46332 | V25: "ICW MSR" is undefined (Issue 7).
A26: A022 | B26: Knowledge Management Site | C26: 6.3.1.7 | D26: 6.3 | E26: OTA Work | F26: Vendor Determined Format | G26: ICW MSR | H26: Standard Distribution | I26: Updated, as needed | J26: As needed | K26: Base | O26: Not Started | P26: =COUNTIF('Submission Log'!$B$5:$B$400,A26) -> 0 | Q26: =COUNTIFS('Submission Log'!$B$5:$B$400,A26,'Submission Log'!$G$5:$G$400,"<>") -> 0 | R26: =COUNTIFS('Submission Log'!$B$5:$B$400,A26,'Submission Log'!$H$5:$H$400,"Accepted")+COUNTIFS('Submission Log'!$B$5:$B$400,A26,'Submission Log'!$H$5:$H$400,"Deemed Accepted") -> 0 | S26: =COUNTIFS('Submission Log'!$B$5:$B$400,A26,'Submission Log'!$H$5:$H$400,"Returned") -> 0 | T26: =COUNTIFS('Submission Log'!$B$5:$B$400,A26,'Submission Log'!$M$5:$M$400,"Overdue") -> 0 | U26: =IFERROR(IF(_xlfn.MINIFS('Submission Log'!$F$5:$F$400,'Submission Log'!$B$5:$B$400,A26,'Submission Log'!$G$5:$G$400,"=",'Submission Log'!$F$5:$F$400,">="&Today)=0,"",_xlfn.MINIFS('Submission Log'!$F$5:$F$400,'Submission Log'!$B$5:$B$400,A26,'Submission Log'!$G$5:$G$400,"=",'Submission Log'!$F$5:$F$400,">="&Today)),"") | V26: "ICW MSR" is undefined (Issue 7).
A27: A023 | B27: Whitepapers | C27: 6.3.2.1, 6.3.2.3, 6.3.3.1 | D27: 6.3 | E27: OTA Work | F27: Vendor Determined Format | G27: ICW MSR | H27: Standard Distribution | I27: As needed | J27: As needed | K27: Base | O27: Not Started | P27: =COUNTIF('Submission Log'!$B$5:$B$400,A27) -> 0 | Q27: =COUNTIFS('Submission Log'!$B$5:$B$400,A27,'Submission Log'!$G$5:$G$400,"<>") -> 0 | R27: =COUNTIFS('Submission Log'!$B$5:$B$400,A27,'Submission Log'!$H$5:$H$400,"Accepted")+COUNTIFS('Submission Log'!$B$5:$B$400,A27,'Submission Log'!$H$5:$H$400,"Deemed Accepted") -> 0 | S27: =COUNTIFS('Submission Log'!$B$5:$B$400,A27,'Submission Log'!$H$5:$H$400,"Returned") -> 0 | T27: =COUNTIFS('Submission Log'!$B$5:$B$400,A27,'Submission Log'!$M$5:$M$400,"Overdue") -> 0 | U27: =IFERROR(IF(_xlfn.MINIFS('Submission Log'!$F$5:$F$400,'Submission Log'!$B$5:$B$400,A27,'Submission Log'!$G$5:$G$400,"=",'Submission Log'!$F$5:$F$400,">="&Today)=0,"",_xlfn.MINIFS('Submission Log'!$F$5:$F$400,'Submission Log'!$B$5:$B$400,A27,'Submission Log'!$G$5:$G$400,"=",'Submission Log'!$F$5:$F$400,">="&Today)),"") | V27: Table omits 6.3.2.4, where the body lists it (Issue 5).
A28: A024 | B28: DoDAF Artifacts/Diagrams (e.g., OV, SV) | C28: 6.1, 6.3.2.4, 6.3.3.1 | D28: 6.1 | E28: OTA Technical Data | F28: Vendor Determined Format | G28: As determined by the Government | H28: Standard Distribution | I28: As needed | J28: As needed | K28: Base | O28: Not Started | P28: =COUNTIF('Submission Log'!$B$5:$B$400,A28) -> 0 | Q28: =COUNTIFS('Submission Log'!$B$5:$B$400,A28,'Submission Log'!$G$5:$G$400,"<>") -> 0 | R28: =COUNTIFS('Submission Log'!$B$5:$B$400,A28,'Submission Log'!$H$5:$H$400,"Accepted")+COUNTIFS('Submission Log'!$B$5:$B$400,A28,'Submission Log'!$H$5:$H$400,"Deemed Accepted") -> 0 | S28: =COUNTIFS('Submission Log'!$B$5:$B$400,A28,'Submission Log'!$H$5:$H$400,"Returned") -> 0 | T28: =COUNTIFS('Submission Log'!$B$5:$B$400,A28,'Submission Log'!$M$5:$M$400,"Overdue") -> 0 | U28: =IFERROR(IF(_xlfn.MINIFS('Submission Log'!$F$5:$F$400,'Submission Log'!$B$5:$B$400,A28,'Submission Log'!$G$5:$G$400,"=",'Submission Log'!$F$5:$F$400,">="&Today)=0,"",_xlfn.MINIFS('Submission Log'!$F$5:$F$400,'Submission Log'!$B$5:$B$400,A28,'Submission Log'!$G$5:$G$400,"=",'Submission Log'!$F$5:$F$400,">="&Today)),"")
A29: A025 | B29: Engineering Artifacts (e.g., Network/System Diagrams) | C29: 6.1, 6.3.2.4, 6.3.4.1.3, 6.3.4.1.4, 6.3.4.1.5 | D29: 6.1 | E29: OTA Technical Data | F29: Government format | G29: Within 10 business days after assignment | H29: Standard Distribution | I29: As needed | J29: As needed | K29: Base | O29: Not Started | P29: =COUNTIF('Submission Log'!$B$5:$B$400,A29) -> 0 | Q29: =COUNTIFS('Submission Log'!$B$5:$B$400,A29,'Submission Log'!$G$5:$G$400,"<>") -> 0 | R29: =COUNTIFS('Submission Log'!$B$5:$B$400,A29,'Submission Log'!$H$5:$H$400,"Accepted")+COUNTIFS('Submission Log'!$B$5:$B$400,A29,'Submission Log'!$H$5:$H$400,"Deemed Accepted") -> 0 | S29: =COUNTIFS('Submission Log'!$B$5:$B$400,A29,'Submission Log'!$H$5:$H$400,"Returned") -> 0 | T29: =COUNTIFS('Submission Log'!$B$5:$B$400,A29,'Submission Log'!$M$5:$M$400,"Overdue") -> 0 | U29: =IFERROR(IF(_xlfn.MINIFS('Submission Log'!$F$5:$F$400,'Submission Log'!$B$5:$B$400,A29,'Submission Log'!$G$5:$G$400,"=",'Submission Log'!$F$5:$F$400,">="&Today)=0,"",_xlfn.MINIFS('Submission Log'!$F$5:$F$400,'Submission Log'!$B$5:$B$400,A29,'Submission Log'!$G$5:$G$400,"=",'Submission Log'!$F$5:$F$400,">="&Today)),"") | V29: Near-duplicate of A032 (Issue 20).
A30: A026 | B30: Concept of Operations (CONOPS) | C30: 6.1 | D30: 6.1 | E30: OTA Technical Data | F30: Vendor Determined/ Govt Approved Format | G30: 60 days post deployment | H30: Standard Distribution | I30: Once, updated yearly or with major change | J30: One-time + updates | K30: Base | O30: Not Started | P30: =COUNTIF('Submission Log'!$B$5:$B$400,A30) -> 1 | Q30: =COUNTIFS('Submission Log'!$B$5:$B$400,A30,'Submission Log'!$G$5:$G$400,"<>") -> 0 | R30: =COUNTIFS('Submission Log'!$B$5:$B$400,A30,'Submission Log'!$H$5:$H$400,"Accepted")+COUNTIFS('Submission Log'!$B$5:$B$400,A30,'Submission Log'!$H$5:$H$400,"Deemed Accepted") -> 0 | S30: =COUNTIFS('Submission Log'!$B$5:$B$400,A30,'Submission Log'!$H$5:$H$400,"Returned") -> 0 | T30: =COUNTIFS('Submission Log'!$B$5:$B$400,A30,'Submission Log'!$M$5:$M$400,"Overdue") -> 0 | U30: =IFERROR(IF(_xlfn.MINIFS('Submission Log'!$F$5:$F$400,'Submission Log'!$B$5:$B$400,A30,'Submission Log'!$G$5:$G$400,"=",'Submission Log'!$F$5:$F$400,">="&Today)=0,"",_xlfn.MINIFS('Submission Log'!$F$5:$F$400,'Submission Log'!$B$5:$B$400,A30,'Submission Log'!$G$5:$G$400,"=",'Submission Log'!$F$5:$F$400,">="&Today)),"")
A31: A027 | B31: Network Modernization Plan | C31: 6.3.2.2 | D31: 6.3 | E31: OTA Technical Data | F31: Vendor Determined Format | G31: 90 Days after contract award | H31: Standard Distribution | I31: One-Time, updated yearly or with major change | J31: One-time + updates | K31: Base | O31: Not Started | P31: =COUNTIF('Submission Log'!$B$5:$B$400,A31) -> 1 | Q31: =COUNTIFS('Submission Log'!$B$5:$B$400,A31,'Submission Log'!$G$5:$G$400,"<>") -> 0 | R31: =COUNTIFS('Submission Log'!$B$5:$B$400,A31,'Submission Log'!$H$5:$H$400,"Accepted")+COUNTIFS('Submission Log'!$B$5:$B$400,A31,'Submission Log'!$H$5:$H$400,"Deemed Accepted") -> 0 | S31: =COUNTIFS('Submission Log'!$B$5:$B$400,A31,'Submission Log'!$H$5:$H$400,"Returned") -> 0 | T31: =COUNTIFS('Submission Log'!$B$5:$B$400,A31,'Submission Log'!$M$5:$M$400,"Overdue") -> 1 | U31: =IFERROR(IF(_xlfn.MINIFS('Submission Log'!$F$5:$F$400,'Submission Log'!$B$5:$B$400,A31,'Submission Log'!$G$5:$G$400,"=",'Submission Log'!$F$5:$F$400,">="&Today)=0,"",_xlfn.MINIFS('Submission Log'!$F$5:$F$400,'Submission Log'!$B$5:$B$400,A31,'Submission Log'!$G$5:$G$400,"=",'Submission Log'!$F$5:$F$400,">="&Today)),"")
A32: A028 | B32: ZT Traceability Matrix | C32: 6.3.2.3 | D32: 6.3 | E32: OTA Technical Data | F32: Vendor Determined Format | G32: ICW MSR | H32: Standard Distribution | I32: One-Time, updated yearly or with major change | J32: One-time + updates | K32: Base | O32: Not Started | P32: =COUNTIF('Submission Log'!$B$5:$B$400,A32) -> 1 | Q32: =COUNTIFS('Submission Log'!$B$5:$B$400,A32,'Submission Log'!$G$5:$G$400,"<>") -> 0 | R32: =COUNTIFS('Submission Log'!$B$5:$B$400,A32,'Submission Log'!$H$5:$H$400,"Accepted")+COUNTIFS('Submission Log'!$B$5:$B$400,A32,'Submission Log'!$H$5:$H$400,"Deemed Accepted") -> 0 | S32: =COUNTIFS('Submission Log'!$B$5:$B$400,A32,'Submission Log'!$H$5:$H$400,"Returned") -> 0 | T32: =COUNTIFS('Submission Log'!$B$5:$B$400,A32,'Submission Log'!$M$5:$M$400,"Overdue") -> 0 | U32: =IFERROR(IF(_xlfn.MINIFS('Submission Log'!$F$5:$F$400,'Submission Log'!$B$5:$B$400,A32,'Submission Log'!$G$5:$G$400,"=",'Submission Log'!$F$5:$F$400,">="&Today)=0,"",_xlfn.MINIFS('Submission Log'!$F$5:$F$400,'Submission Log'!$B$5:$B$400,A32,'Submission Log'!$G$5:$G$400,"=",'Submission Log'!$F$5:$F$400,">="&Today)),"") | V32: "ICW MSR" is undefined (Issue 7).
A33: A029 | B33: ZT Gap Analysis | C33: 6.3.2.3 | D33: 6.3 | E33: OTA Technical Data | F33: Vendor Determined Format | G33: As determined by the Government | H33: Standard Distribution | I33: One-Time, updated yearly or with major change | J33: One-time + updates | K33: Base | O33: Not Started | P33: =COUNTIF('Submission Log'!$B$5:$B$400,A33) -> 1 | Q33: =COUNTIFS('Submission Log'!$B$5:$B$400,A33,'Submission Log'!$G$5:$G$400,"<>") -> 0 | R33: =COUNTIFS('Submission Log'!$B$5:$B$400,A33,'Submission Log'!$H$5:$H$400,"Accepted")+COUNTIFS('Submission Log'!$B$5:$B$400,A33,'Submission Log'!$H$5:$H$400,"Deemed Accepted") -> 0 | S33: =COUNTIFS('Submission Log'!$B$5:$B$400,A33,'Submission Log'!$H$5:$H$400,"Returned") -> 0 | T33: =COUNTIFS('Submission Log'!$B$5:$B$400,A33,'Submission Log'!$M$5:$M$400,"Overdue") -> 0 | U33: =IFERROR(IF(_xlfn.MINIFS('Submission Log'!$F$5:$F$400,'Submission Log'!$B$5:$B$400,A33,'Submission Log'!$G$5:$G$400,"=",'Submission Log'!$F$5:$F$400,">="&Today)=0,"",_xlfn.MINIFS('Submission Log'!$F$5:$F$400,'Submission Log'!$B$5:$B$400,A33,'Submission Log'!$G$5:$G$400,"=",'Submission Log'!$F$5:$F$400,">="&Today)),"")
A34: A030 | B34: Zero Trust Architecture Design Document | C34: 6.3.2.3 | D34: 6.3 | E34: OTA Technical Data | F34: Vendor Determined Format | G34: As determined by the Government | H34: Standard Distribution | I34: One-Time, updated yearly or with major change | J34: One-time + updates | K34: Base | O34: Not Started | P34: =COUNTIF('Submission Log'!$B$5:$B$400,A34) -> 1 | Q34: =COUNTIFS('Submission Log'!$B$5:$B$400,A34,'Submission Log'!$G$5:$G$400,"<>") -> 0 | R34: =COUNTIFS('Submission Log'!$B$5:$B$400,A34,'Submission Log'!$H$5:$H$400,"Accepted")+COUNTIFS('Submission Log'!$B$5:$B$400,A34,'Submission Log'!$H$5:$H$400,"Deemed Accepted") -> 0 | S34: =COUNTIFS('Submission Log'!$B$5:$B$400,A34,'Submission Log'!$H$5:$H$400,"Returned") -> 0 | T34: =COUNTIFS('Submission Log'!$B$5:$B$400,A34,'Submission Log'!$M$5:$M$400,"Overdue") -> 0 | U34: =IFERROR(IF(_xlfn.MINIFS('Submission Log'!$F$5:$F$400,'Submission Log'!$B$5:$B$400,A34,'Submission Log'!$G$5:$G$400,"=",'Submission Log'!$F$5:$F$400,">="&Today)=0,"",_xlfn.MINIFS('Submission Log'!$F$5:$F$400,'Submission Log'!$B$5:$B$400,A34,'Submission Log'!$G$5:$G$400,"=",'Submission Log'!$F$5:$F$400,">="&Today)),"")
A35: A031 | B35: Implementation Plan | C35: 6.3.2.5, 6.3.3.2, 6.3.3.3 | D35: 6.3 | E35: OTA Technical Data | F35: Vendor format | G35: 30 days before Implementation | H35: Standard Distribution | I35: As needed | J35: As needed | K35: Base | O35: Not Started | P35: =COUNTIF('Submission Log'!$B$5:$B$400,A35) -> 0 | Q35: =COUNTIFS('Submission Log'!$B$5:$B$400,A35,'Submission Log'!$G$5:$G$400,"<>") -> 0 | R35: =COUNTIFS('Submission Log'!$B$5:$B$400,A35,'Submission Log'!$H$5:$H$400,"Accepted")+COUNTIFS('Submission Log'!$B$5:$B$400,A35,'Submission Log'!$H$5:$H$400,"Deemed Accepted") -> 0 | S35: =COUNTIFS('Submission Log'!$B$5:$B$400,A35,'Submission Log'!$H$5:$H$400,"Returned") -> 0 | T35: =COUNTIFS('Submission Log'!$B$5:$B$400,A35,'Submission Log'!$M$5:$M$400,"Overdue") -> 0 | U35: =IFERROR(IF(_xlfn.MINIFS('Submission Log'!$F$5:$F$400,'Submission Log'!$B$5:$B$400,A35,'Submission Log'!$G$5:$G$400,"=",'Submission Log'!$F$5:$F$400,">="&Today)=0,"",_xlfn.MINIFS('Submission Log'!$F$5:$F$400,'Submission Log'!$B$5:$B$400,A35,'Submission Log'!$G$5:$G$400,"=",'Submission Log'!$F$5:$F$400,">="&Today)),"")
A36: A032 | B36: Engineering Artifacts (e.g., Network/System Diagrams) | C36: 6.3.2.5, 6.3.3.1, 6.3.3.2, 6.3.3.3 | D36: 6.3 | E36: OTA Technical Data | F36: Government format | G36: Within 10 business days after assignment | H36: Standard Distribution | I36: As needed | J36: As needed | K36: Base | O36: Not Started | P36: =COUNTIF('Submission Log'!$B$5:$B$400,A36) -> 0 | Q36: =COUNTIFS('Submission Log'!$B$5:$B$400,A36,'Submission Log'!$G$5:$G$400,"<>") -> 0 | R36: =COUNTIFS('Submission Log'!$B$5:$B$400,A36,'Submission Log'!$H$5:$H$400,"Accepted")+COUNTIFS('Submission Log'!$B$5:$B$400,A36,'Submission Log'!$H$5:$H$400,"Deemed Accepted") -> 0 | S36: =COUNTIFS('Submission Log'!$B$5:$B$400,A36,'Submission Log'!$H$5:$H$400,"Returned") -> 0 | T36: =COUNTIFS('Submission Log'!$B$5:$B$400,A36,'Submission Log'!$M$5:$M$400,"Overdue") -> 0 | U36: =IFERROR(IF(_xlfn.MINIFS('Submission Log'!$F$5:$F$400,'Submission Log'!$B$5:$B$400,A36,'Submission Log'!$G$5:$G$400,"=",'Submission Log'!$F$5:$F$400,">="&Today)=0,"",_xlfn.MINIFS('Submission Log'!$F$5:$F$400,'Submission Log'!$B$5:$B$400,A36,'Submission Log'!$G$5:$G$400,"=",'Submission Log'!$F$5:$F$400,">="&Today)),"") | V36: Near-duplicate of A025 (Issue 20).
A37: A033 | B37: ASIs | C37: 6.3.2.5, 6.3.3.2, 6.3.3.3 | D37: 6.3 | E37: OTA Technical Data | F37: Government format | G37: 10 days upon expected outage unless otherwise noted by the Government (must receive Gov’t approval) | H37: Standard Distribution | I37: One-Time | J37: One-time | K37: Base | O37: Not Started | P37: =COUNTIF('Submission Log'!$B$5:$B$400,A37) -> 0 | Q37: =COUNTIFS('Submission Log'!$B$5:$B$400,A37,'Submission Log'!$G$5:$G$400,"<>") -> 0 | R37: =COUNTIFS('Submission Log'!$B$5:$B$400,A37,'Submission Log'!$H$5:$H$400,"Accepted")+COUNTIFS('Submission Log'!$B$5:$B$400,A37,'Submission Log'!$H$5:$H$400,"Deemed Accepted") -> 0 | S37: =COUNTIFS('Submission Log'!$B$5:$B$400,A37,'Submission Log'!$H$5:$H$400,"Returned") -> 0 | T37: =COUNTIFS('Submission Log'!$B$5:$B$400,A37,'Submission Log'!$M$5:$M$400,"Overdue") -> 0 | U37: =IFERROR(IF(_xlfn.MINIFS('Submission Log'!$F$5:$F$400,'Submission Log'!$B$5:$B$400,A37,'Submission Log'!$G$5:$G$400,"=",'Submission Log'!$F$5:$F$400,">="&Today)=0,"",_xlfn.MINIFS('Submission Log'!$F$5:$F$400,'Submission Log'!$B$5:$B$400,A37,'Submission Log'!$G$5:$G$400,"=",'Submission Log'!$F$5:$F$400,">="&Today)),"")
A38: A034 | B38: Site Survey Reports | C38: 6.3.2.6, 6.3.3.1 | D38: 6.3 | E38: OTA Technical Data | F38: Vendor format/ Government Approved | G38: IAW IMS | H38: Standard Distribution | I38: One-Time | J38: One-time | K38: Base | O38: Not Started | P38: =COUNTIF('Submission Log'!$B$5:$B$400,A38) -> 1 | Q38: =COUNTIFS('Submission Log'!$B$5:$B$400,A38,'Submission Log'!$G$5:$G$400,"<>") -> 0 | R38: =COUNTIFS('Submission Log'!$B$5:$B$400,A38,'Submission Log'!$H$5:$H$400,"Accepted")+COUNTIFS('Submission Log'!$B$5:$B$400,A38,'Submission Log'!$H$5:$H$400,"Deemed Accepted") -> 0 | S38: =COUNTIFS('Submission Log'!$B$5:$B$400,A38,'Submission Log'!$H$5:$H$400,"Returned") -> 0 | T38: =COUNTIFS('Submission Log'!$B$5:$B$400,A38,'Submission Log'!$M$5:$M$400,"Overdue") -> 0 | U38: =IFERROR(IF(_xlfn.MINIFS('Submission Log'!$F$5:$F$400,'Submission Log'!$B$5:$B$400,A38,'Submission Log'!$G$5:$G$400,"=",'Submission Log'!$F$5:$F$400,">="&Today)=0,"",_xlfn.MINIFS('Submission Log'!$F$5:$F$400,'Submission Log'!$B$5:$B$400,A38,'Submission Log'!$G$5:$G$400,"=",'Submission Log'!$F$5:$F$400,">="&Today)),"") | V38: Table cites 6.3.2.6, which names no deliverables (Issue 4).
A39: A035 | B39: ITSM/ Change Tickets | C39: 6.3.4.1.1, 6.3.4.1.2 | D39: 6.3 | E39: OTA Technical Data | F39: Government format | G39: 10 days prior to necessary change | H39: Standard Distribution | I39: One-Time, updated as needed | J39: One-time + updates | K39: Base + Optional | O39: Not Started | P39: =COUNTIF('Submission Log'!$B$5:$B$400,A39) -> 0 | Q39: =COUNTIFS('Submission Log'!$B$5:$B$400,A39,'Submission Log'!$G$5:$G$400,"<>") -> 0 | R39: =COUNTIFS('Submission Log'!$B$5:$B$400,A39,'Submission Log'!$H$5:$H$400,"Accepted")+COUNTIFS('Submission Log'!$B$5:$B$400,A39,'Submission Log'!$H$5:$H$400,"Deemed Accepted") -> 0 | S39: =COUNTIFS('Submission Log'!$B$5:$B$400,A39,'Submission Log'!$H$5:$H$400,"Returned") -> 0 | T39: =COUNTIFS('Submission Log'!$B$5:$B$400,A39,'Submission Log'!$M$5:$M$400,"Overdue") -> 0 | U39: =IFERROR(IF(_xlfn.MINIFS('Submission Log'!$F$5:$F$400,'Submission Log'!$B$5:$B$400,A39,'Submission Log'!$G$5:$G$400,"=",'Submission Log'!$F$5:$F$400,">="&Today)=0,"",_xlfn.MINIFS('Submission Log'!$F$5:$F$400,'Submission Log'!$B$5:$B$400,A39,'Submission Log'!$G$5:$G$400,"=",'Submission Log'!$F$5:$F$400,">="&Today)),"") | V39: Table omits the 24x7 paragraph (Issue 6).
A40: A036 | B40: Metrics Report | C40: 6.3.4.1.2 | D40: 6.3 | E40: OTA Technical Data | F40: Vendor Determined/ Govt Approved format | G40: 30 Days after Implementation | H40: Standard Distribution | I40: One-Time | J40: One-time | K40: Optional Priced | O40: Not Started | P40: =COUNTIF('Submission Log'!$B$5:$B$400,A40) -> 0 | Q40: =COUNTIFS('Submission Log'!$B$5:$B$400,A40,'Submission Log'!$G$5:$G$400,"<>") -> 0 | R40: =COUNTIFS('Submission Log'!$B$5:$B$400,A40,'Submission Log'!$H$5:$H$400,"Accepted")+COUNTIFS('Submission Log'!$B$5:$B$400,A40,'Submission Log'!$H$5:$H$400,"Deemed Accepted") -> 0 | S40: =COUNTIFS('Submission Log'!$B$5:$B$400,A40,'Submission Log'!$H$5:$H$400,"Returned") -> 0 | T40: =COUNTIFS('Submission Log'!$B$5:$B$400,A40,'Submission Log'!$M$5:$M$400,"Overdue") -> 0 | U40: =IFERROR(IF(_xlfn.MINIFS('Submission Log'!$F$5:$F$400,'Submission Log'!$B$5:$B$400,A40,'Submission Log'!$G$5:$G$400,"=",'Submission Log'!$F$5:$F$400,">="&Today)=0,"",_xlfn.MINIFS('Submission Log'!$F$5:$F$400,'Submission Log'!$B$5:$B$400,A40,'Submission Log'!$G$5:$G$400,"=",'Submission Log'!$F$5:$F$400,">="&Today)),"") | V40: Table omits the 24x7 paragraph (Issue 6).
A41: A037 | B41: Help Desk Report | C41: 6.3.4.1.2 | D41: 6.3 | E41: OTA Technical Data | F41: Vendor Determined/ Govt Approved format | G41: 24 hours upon request | H41: Standard Distribution | I41: One-Time, updated as needed | J41: One-time + updates | K41: Optional Priced | O41: Not Started | P41: =COUNTIF('Submission Log'!$B$5:$B$400,A41) -> 0 | Q41: =COUNTIFS('Submission Log'!$B$5:$B$400,A41,'Submission Log'!$G$5:$G$400,"<>") -> 0 | R41: =COUNTIFS('Submission Log'!$B$5:$B$400,A41,'Submission Log'!$H$5:$H$400,"Accepted")+COUNTIFS('Submission Log'!$B$5:$B$400,A41,'Submission Log'!$H$5:$H$400,"Deemed Accepted") -> 0 | S41: =COUNTIFS('Submission Log'!$B$5:$B$400,A41,'Submission Log'!$H$5:$H$400,"Returned") -> 0 | T41: =COUNTIFS('Submission Log'!$B$5:$B$400,A41,'Submission Log'!$M$5:$M$400,"Overdue") -> 0 | U41: =IFERROR(IF(_xlfn.MINIFS('Submission Log'!$F$5:$F$400,'Submission Log'!$B$5:$B$400,A41,'Submission Log'!$G$5:$G$400,"=",'Submission Log'!$F$5:$F$400,">="&Today)=0,"",_xlfn.MINIFS('Submission Log'!$F$5:$F$400,'Submission Log'!$B$5:$B$400,A41,'Submission Log'!$G$5:$G$400,"=",'Submission Log'!$F$5:$F$400,">="&Today)),"") | V41: Table omits the 24x7 paragraph (Issue 6).
A42: A038 | B42: Test Plans | C42: 6.3.4.1.3, 6.3.4.1.4 | D42: 6.3 | E42: OTA Technical Data | F42: Vendor Determined/ Govt Approved format | G42: 30 days after contract award | H42: Standard Distribution | I42: One-Time, updated as needed | J42: One-time + updates | K42: Base | O42: Not Started | P42: =COUNTIF('Submission Log'!$B$5:$B$400,A42) -> 1 | Q42: =COUNTIFS('Submission Log'!$B$5:$B$400,A42,'Submission Log'!$G$5:$G$400,"<>") -> 0 | R42: =COUNTIFS('Submission Log'!$B$5:$B$400,A42,'Submission Log'!$H$5:$H$400,"Accepted")+COUNTIFS('Submission Log'!$B$5:$B$400,A42,'Submission Log'!$H$5:$H$400,"Deemed Accepted") -> 0 | S42: =COUNTIFS('Submission Log'!$B$5:$B$400,A42,'Submission Log'!$H$5:$H$400,"Returned") -> 0 | T42: =COUNTIFS('Submission Log'!$B$5:$B$400,A42,'Submission Log'!$M$5:$M$400,"Overdue") -> 1 | U42: =IFERROR(IF(_xlfn.MINIFS('Submission Log'!$F$5:$F$400,'Submission Log'!$B$5:$B$400,A42,'Submission Log'!$G$5:$G$400,"=",'Submission Log'!$F$5:$F$400,">="&Today)=0,"",_xlfn.MINIFS('Submission Log'!$F$5:$F$400,'Submission Log'!$B$5:$B$400,A42,'Submission Log'!$G$5:$G$400,"=",'Submission Log'!$F$5:$F$400,">="&Today)),"") | V42: Due 30 days after award, before anything exists to test (Issue 9).
A43: A039 | B43: Test Reports | C43: 6.3.4.1.3, 6.3.4.1.4 | D43: 6.3 | E43: OTA Technical Data | F43: Vendor Determined/ Govt Approved format | G43: 30 days after contract award | H43: Standard Distribution | I43: One-Time, updated as needed | J43: One-time + updates | K43: Base | O43: Not Started | P43: =COUNTIF('Submission Log'!$B$5:$B$400,A43) -> 1 | Q43: =COUNTIFS('Submission Log'!$B$5:$B$400,A43,'Submission Log'!$G$5:$G$400,"<>") -> 0 | R43: =COUNTIFS('Submission Log'!$B$5:$B$400,A43,'Submission Log'!$H$5:$H$400,"Accepted")+COUNTIFS('Submission Log'!$B$5:$B$400,A43,'Submission Log'!$H$5:$H$400,"Deemed Accepted") -> 0 | S43: =COUNTIFS('Submission Log'!$B$5:$B$400,A43,'Submission Log'!$H$5:$H$400,"Returned") -> 0 | T43: =COUNTIFS('Submission Log'!$B$5:$B$400,A43,'Submission Log'!$M$5:$M$400,"Overdue") -> 1 | U43: =IFERROR(IF(_xlfn.MINIFS('Submission Log'!$F$5:$F$400,'Submission Log'!$B$5:$B$400,A43,'Submission Log'!$G$5:$G$400,"=",'Submission Log'!$F$5:$F$400,">="&Today)=0,"",_xlfn.MINIFS('Submission Log'!$F$5:$F$400,'Submission Log'!$B$5:$B$400,A43,'Submission Log'!$G$5:$G$400,"=",'Submission Log'!$F$5:$F$400,">="&Today)),"") | V43: Due 30 days after award, before anything exists to test (Issue 9).
A44: A040 | B44: Security Monitoring Reports | C44: 6.3.4.2 | D44: 6.3 | E44: OTA Technical Data | F44: Vendor Determined Format | G44: 90 Days after award | H44: Standard Distribution | I44: One-Time, updated yearly or with major change | J44: One-time + updates | K44: Optional Priced | O44: Not Started | P44: =COUNTIF('Submission Log'!$B$5:$B$400,A44) -> 1 | Q44: =COUNTIFS('Submission Log'!$B$5:$B$400,A44,'Submission Log'!$G$5:$G$400,"<>") -> 0 | R44: =COUNTIFS('Submission Log'!$B$5:$B$400,A44,'Submission Log'!$H$5:$H$400,"Accepted")+COUNTIFS('Submission Log'!$B$5:$B$400,A44,'Submission Log'!$H$5:$H$400,"Deemed Accepted") -> 0 | S44: =COUNTIFS('Submission Log'!$B$5:$B$400,A44,'Submission Log'!$H$5:$H$400,"Returned") -> 0 | T44: =COUNTIFS('Submission Log'!$B$5:$B$400,A44,'Submission Log'!$M$5:$M$400,"Overdue") -> 1 | U44: =IFERROR(IF(_xlfn.MINIFS('Submission Log'!$F$5:$F$400,'Submission Log'!$B$5:$B$400,A44,'Submission Log'!$G$5:$G$400,"=",'Submission Log'!$F$5:$F$400,">="&Today)=0,"",_xlfn.MINIFS('Submission Log'!$F$5:$F$400,'Submission Log'!$B$5:$B$400,A44,'Submission Log'!$G$5:$G$400,"=",'Submission Log'!$F$5:$F$400,">="&Today)),"") | V44: Same title as A012; one-time due date for an ongoing optional service (Issue 9).
A45: A041 | B45: Transition-In Plan | C45: 6.3.1.3 | D45: 6.3 | E45: OTA Technical Data | F45: Vendor Determined Format | G45: Initial Draft at Project Kickoff Meeting Final Draft 5 business days after contract award | H45: Standard Distribution | I45: One-Time | J45: One-time | K45: Base | O45: Not Started | P45: =COUNTIF('Submission Log'!$B$5:$B$400,A45) -> 2 | Q45: =COUNTIFS('Submission Log'!$B$5:$B$400,A45,'Submission Log'!$G$5:$G$400,"<>") -> 0 | R45: =COUNTIFS('Submission Log'!$B$5:$B$400,A45,'Submission Log'!$H$5:$H$400,"Accepted")+COUNTIFS('Submission Log'!$B$5:$B$400,A45,'Submission Log'!$H$5:$H$400,"Deemed Accepted") -> 0 | S45: =COUNTIFS('Submission Log'!$B$5:$B$400,A45,'Submission Log'!$H$5:$H$400,"Returned") -> 0 | T45: =COUNTIFS('Submission Log'!$B$5:$B$400,A45,'Submission Log'!$M$5:$M$400,"Overdue") -> 2 | U45: =IFERROR(IF(_xlfn.MINIFS('Submission Log'!$F$5:$F$400,'Submission Log'!$B$5:$B$400,A45,'Submission Log'!$G$5:$G$400,"=",'Submission Log'!$F$5:$F$400,">="&Today)=0,"",_xlfn.MINIFS('Submission Log'!$F$5:$F$400,'Submission Log'!$B$5:$B$400,A45,'Submission Log'!$G$5:$G$400,"=",'Submission Log'!$F$5:$F$400,">="&Today)),"") | V45: Body: 30 days after kickoff; table: draft at kickoff, final 5 business days after award (Issue 1).
A46: A042 | B46: Transition-Out Plan | C46: 6.3.1.3 | D46: 6.3 | E46: OTA Technical Data | F46: Vendor Determined Format | G46: T-30 Days (30 Days Prior to Contract End) | H46: Standard Distribution | I46: One-Time | J46: One-time | K46: Base | O46: Not Started | P46: =COUNTIF('Submission Log'!$B$5:$B$400,A46) -> 1 | Q46: =COUNTIFS('Submission Log'!$B$5:$B$400,A46,'Submission Log'!$G$5:$G$400,"<>") -> 0 | R46: =COUNTIFS('Submission Log'!$B$5:$B$400,A46,'Submission Log'!$H$5:$H$400,"Accepted")+COUNTIFS('Submission Log'!$B$5:$B$400,A46,'Submission Log'!$H$5:$H$400,"Deemed Accepted") -> 0 | S46: =COUNTIFS('Submission Log'!$B$5:$B$400,A46,'Submission Log'!$H$5:$H$400,"Returned") -> 0 | T46: =COUNTIFS('Submission Log'!$B$5:$B$400,A46,'Submission Log'!$M$5:$M$400,"Overdue") -> 0 | U46: =IFERROR(IF(_xlfn.MINIFS('Submission Log'!$F$5:$F$400,'Submission Log'!$B$5:$B$400,A46,'Submission Log'!$G$5:$G$400,"=",'Submission Log'!$F$5:$F$400,">="&Today)=0,"",_xlfn.MINIFS('Submission Log'!$F$5:$F$400,'Submission Log'!$B$5:$B$400,A46,'Submission Log'!$G$5:$G$400,"=",'Submission Log'!$F$5:$F$400,">="&Today)),"") -> 47270 | V46: Body: 120 calendar days before end; table: T-30 (Issue 2).
A47: A043 | B47: Task Order Closeout | C47: 6.3.1.3 | D47: 6.3 | E47: OTA Technical Data | F47: Vendor Determined Format | G47: End of Contract | H47: Standard Distribution | I47: One-Time | J47: One-time | K47: Base | O47: Not Started | P47: =COUNTIF('Submission Log'!$B$5:$B$400,A47) -> 1 | Q47: =COUNTIFS('Submission Log'!$B$5:$B$400,A47,'Submission Log'!$G$5:$G$400,"<>") -> 0 | R47: =COUNTIFS('Submission Log'!$B$5:$B$400,A47,'Submission Log'!$H$5:$H$400,"Accepted")+COUNTIFS('Submission Log'!$B$5:$B$400,A47,'Submission Log'!$H$5:$H$400,"Deemed Accepted") -> 0 | S47: =COUNTIFS('Submission Log'!$B$5:$B$400,A47,'Submission Log'!$H$5:$H$400,"Returned") -> 0 | T47: =COUNTIFS('Submission Log'!$B$5:$B$400,A47,'Submission Log'!$M$5:$M$400,"Overdue") -> 0 | U47: =IFERROR(IF(_xlfn.MINIFS('Submission Log'!$F$5:$F$400,'Submission Log'!$B$5:$B$400,A47,'Submission Log'!$G$5:$G$400,"=",'Submission Log'!$F$5:$F$400,">="&Today)=0,"",_xlfn.MINIFS('Submission Log'!$F$5:$F$400,'Submission Log'!$B$5:$B$400,A47,'Submission Log'!$G$5:$G$400,"=",'Submission Log'!$F$5:$F$400,">="&Today)),"") -> 47390
A48: A044 | B48: Logistics Deliverables | C48: 6.3.1.4 | D48: 6.3 | E48: OTA Technical Data | F48: Vendor Determined Format | G48: ICW MSR | H48: Standard Distribution | I48: Updated as needed | J48: As needed | K48: Base | O48: Not Started | P48: =COUNTIF('Submission Log'!$B$5:$B$400,A48) -> 0 | Q48: =COUNTIFS('Submission Log'!$B$5:$B$400,A48,'Submission Log'!$G$5:$G$400,"<>") -> 0 | R48: =COUNTIFS('Submission Log'!$B$5:$B$400,A48,'Submission Log'!$H$5:$H$400,"Accepted")+COUNTIFS('Submission Log'!$B$5:$B$400,A48,'Submission Log'!$H$5:$H$400,"Deemed Accepted") -> 0 | S48: =COUNTIFS('Submission Log'!$B$5:$B$400,A48,'Submission Log'!$H$5:$H$400,"Returned") -> 0 | T48: =COUNTIFS('Submission Log'!$B$5:$B$400,A48,'Submission Log'!$M$5:$M$400,"Overdue") -> 0 | U48: =IFERROR(IF(_xlfn.MINIFS('Submission Log'!$F$5:$F$400,'Submission Log'!$B$5:$B$400,A48,'Submission Log'!$G$5:$G$400,"=",'Submission Log'!$F$5:$F$400,">="&Today)=0,"",_xlfn.MINIFS('Submission Log'!$F$5:$F$400,'Submission Log'!$B$5:$B$400,A48,'Submission Log'!$G$5:$G$400,"=",'Submission Log'!$F$5:$F$400,">="&Today)),"") | V48: "ICW MSR" is undefined (Issue 7).

Sheet Submission Log
A1: Submission Log
A2: One row per due date. Enter the yellow cells; the gray cells calculate. Add rows for as-needed deliverables in the blank rows below.
A4: Log # | B4: Deliverable ID | C4: Deliverable | D4: Task group | E4: Period / event | F4: Due date | G4: Date submitted | H4: Gov decision | I4: Decision date | J4: Gov inspection deadline | K4: Deemed-acceptance flag | L4: Resubmission due | M4: Timeliness | N4: Days late | O4: Rework (1/0) | P4: Link / location | Q4: Notes
A5: 1 | B5: A001 | C5: =IF(B5="","",IFERROR(INDEX(Deliverables!$B$5:$B$48,MATCH(B5,Deliverables!$A$5:$A$48,0)),"ID not found")) -> Implementation Approach and Architecture | D5: =IF(B5="","",IFERROR(INDEX(Deliverables!$D$5:$D$48,MATCH(B5,Deliverables!$A$5:$A$48,0)),"")) -> 6.1 | E5: Initial delivery | J5: =IF(G5="","",WORKDAY(G5,ReviewDays)) | K5: =IF(AND(G5<>"",OR(H5="",H5="Pending"),Today>J5),"Past inspection window – deemed accepted","") | L5: =IF(AND(H5="Returned",I5<>""),WORKDAY(I5,ResubDays),"") | M5: =IF(OR(B5="",F5=""),"",IF(G5<>"",IF(G5<=F5,"On time","Late"),IF(Today>F5,"Overdue",IF(F5-Today<=7,"Due within 7 days","Not yet due")))) | N5: =IF(OR(M5="Late",M5="Overdue"),IF(G5<>"",G5-F5,Today-F5),"") | O5: =IF(H5="Returned",1,0) -> 0 | Q5: Due per the IMS (A017): enter the date.
A6: 2 | B6: A002 | C6: =IF(B6="","",IFERROR(INDEX(Deliverables!$B$5:$B$48,MATCH(B6,Deliverables!$A$5:$A$48,0)),"ID not found")) -> ZT Governance Plan | D6: =IF(B6="","",IFERROR(INDEX(Deliverables!$D$5:$D$48,MATCH(B6,Deliverables!$A$5:$A$48,0)),"")) -> 6.1 | E6: Initial delivery | J6: =IF(G6="","",WORKDAY(G6,ReviewDays)) | K6: =IF(AND(G6<>"",OR(H6="",H6="Pending"),Today>J6),"Past inspection window – deemed accepted","") | L6: =IF(AND(H6="Returned",I6<>""),WORKDAY(I6,ResubDays),"") | M6: =IF(OR(B6="",F6=""),"",IF(G6<>"",IF(G6<=F6,"On time","Late"),IF(Today>F6,"Overdue",IF(F6-Today<=7,"Due within 7 days","Not yet due")))) | N6: =IF(OR(M6="Late",M6="Overdue"),IF(G6<>"",G6-F6,Today-F6),"") | O6: =IF(H6="Returned",1,0) -> 0 | Q6: Due per the IMS (A017): enter the date.
A7: 3 | B7: A004 | C7: =IF(B7="","",IFERROR(INDEX(Deliverables!$B$5:$B$48,MATCH(B7,Deliverables!$A$5:$A$48,0)),"ID not found")) -> ATO Documentation/ Artifacts | D7: =IF(B7="","",IFERROR(INDEX(Deliverables!$D$5:$D$48,MATCH(B7,Deliverables!$A$5:$A$48,0)),"")) -> 6.1 | E7: Initial delivery | J7: =IF(G7="","",WORKDAY(G7,ReviewDays)) | K7: =IF(AND(G7<>"",OR(H7="",H7="Pending"),Today>J7),"Past inspection window – deemed accepted","") | L7: =IF(AND(H7="Returned",I7<>""),WORKDAY(I7,ResubDays),"") | M7: =IF(OR(B7="",F7=""),"",IF(G7<>"",IF(G7<=F7,"On time","Late"),IF(Today>F7,"Overdue",IF(F7-Today<=7,"Due within 7 days","Not yet due")))) | N7: =IF(OR(M7="Late",M7="Overdue"),IF(G7<>"",G7-F7,Today-F7),"") | O7: =IF(H7="Returned",1,0) -> 0 | Q7: Due per the IMS (A017): enter the date.
A8: 4 | B8: A006 | C8: =IF(B8="","",IFERROR(INDEX(Deliverables!$B$5:$B$48,MATCH(B8,Deliverables!$A$5:$A$48,0)),"ID not found")) -> STIG/SRG Checklists | D8: =IF(B8="","",IFERROR(INDEX(Deliverables!$D$5:$D$48,MATCH(B8,Deliverables!$A$5:$A$48,0)),"")) -> 6.1 | E8: ="Quarter 1 (months 1-3)" -> Quarter 1 (months 1-3) | F8: =WORKDAY(EOMONTH(Award,2),DueOffset) -> 46241 | J8: =IF(G8="","",WORKDAY(G8,ReviewDays)) | K8: =IF(AND(G8<>"",OR(H8="",H8="Pending"),Today>J8),"Past inspection window – deemed accepted","") | L8: =IF(AND(H8="Returned",I8<>""),WORKDAY(I8,ResubDays),"") | M8: =IF(OR(B8="",F8=""),"",IF(G8<>"",IF(G8<=F8,"On time","Late"),IF(Today>F8,"Overdue",IF(F8-Today<=7,"Due within 7 days","Not yet due")))) -> Overdue | N8: =IF(OR(M8="Late",M8="Overdue"),IF(G8<>"",G8-F8,Today-F8),"") -> 65 | O8: =IF(H8="Returned",1,0) -> 0 | Q8: Due date uses the DueOffset assumption.
A9: 5 | B9: A006 | C9: =IF(B9="","",IFERROR(INDEX(Deliverables!$B$5:$B$48,MATCH(B9,Deliverables!$A$5:$A$48,0)),"ID not found")) -> STIG/SRG Checklists | D9: =IF(B9="","",IFERROR(INDEX(Deliverables!$D$5:$D$48,MATCH(B9,Deliverables!$A$5:$A$48,0)),"")) -> 6.1 | E9: ="Quarter 2 (months 4-6)" -> Quarter 2 (months 4-6) | F9: =WORKDAY(EOMONTH(Award,5),DueOffset) -> 46332 | J9: =IF(G9="","",WORKDAY(G9,ReviewDays)) | K9: =IF(AND(G9<>"",OR(H9="",H9="Pending"),Today>J9),"Past inspection window – deemed accepted","") | L9: =IF(AND(H9="Returned",I9<>""),WORKDAY(I9,ResubDays),"") | M9: =IF(OR(B9="",F9=""),"",IF(G9<>"",IF(G9<=F9,"On time","Late"),IF(Today>F9,"Overdue",IF(F9-Today<=7,"Due within 7 days","Not yet due")))) -> Not yet due | N9: =IF(OR(M9="Late",M9="Overdue"),IF(G9<>"",G9-F9,Today-F9),"") | O9: =IF(H9="Returned",1,0) -> 0 | Q9: Due date uses the DueOffset assumption.
A10: 6 | B10: A006 | C10: =IF(B10="","",IFERROR(INDEX(Deliverables!$B$5:$B$48,MATCH(B10,Deliverables!$A$5:$A$48,0)),"ID not found")) -> STIG/SRG Checklists | D10: =IF(B10="","",IFERROR(INDEX(Deliverables!$D$5:$D$48,MATCH(B10,Deliverables!$A$5:$A$48,0)),"")) -> 6.1 | E10: ="Quarter 3 (months 7-9)" -> Quarter 3 (months 7-9) | F10: =WORKDAY(EOMONTH(Award,8),DueOffset) -> 46423 | J10: =IF(G10="","",WORKDAY(G10,ReviewDays)) | K10: =IF(AND(G10<>"",OR(H10="",H10="Pending"),Today>J10),"Past inspection window – deemed accepted","") | L10: =IF(AND(H10="Returned",I10<>""),WORKDAY(I10,ResubDays),"") | M10: =IF(OR(B10="",F10=""),"",IF(G10<>"",IF(G10<=F10,"On time","Late"),IF(Today>F10,"Overdue",IF(F10-Today<=7,"Due within 7 days","Not yet due")))) -> Not yet due | N10: =IF(OR(M10="Late",M10="Overdue"),IF(G10<>"",G10-F10,Today-F10),"") | O10: =IF(H10="Returned",1,0) -> 0 | Q10: Due date uses the DueOffset assumption.
A11: 7 | B11: A006 | C11: =IF(B11="","",IFERROR(INDEX(Deliverables!$B$5:$B$48,MATCH(B11,Deliverables!$A$5:$A$48,0)),"ID not found")) -> STIG/SRG Checklists | D11: =IF(B11="","",IFERROR(INDEX(Deliverables!$D$5:$D$48,MATCH(B11,Deliverables!$A$5:$A$48,0)),"")) -> 6.1 | E11: ="Quarter 4 (months 10-12)" -> Quarter 4 (months 10-12) | F11: =WORKDAY(EOMONTH(Award,11),DueOffset) -> 46514 | J11: =IF(G11="","",WORKDAY(G11,ReviewDays)) | K11: =IF(AND(G11<>"",OR(H11="",H11="Pending"),Today>J11),"Past inspection window – deemed accepted","") | L11: =IF(AND(H11="Returned",I11<>""),WORKDAY(I11,ResubDays),"") | M11: =IF(OR(B11="",F11=""),"",IF(G11<>"",IF(G11<=F11,"On time","Late"),IF(Today>F11,"Overdue",IF(F11-Today<=7,"Due within 7 days","Not yet due")))) -> Not yet due | N11: =IF(OR(M11="Late",M11="Overdue"),IF(G11<>"",G11-F11,Today-F11),"") | O11: =IF(H11="Returned",1,0) -> 0 | Q11: Due date uses the DueOffset assumption.
A12: 8 | B12: A007 | C12: =IF(B12="","",IFERROR(INDEX(Deliverables!$B$5:$B$48,MATCH(B12,Deliverables!$A$5:$A$48,0)),"ID not found")) -> ACAS Scans | D12: =IF(B12="","",IFERROR(INDEX(Deliverables!$D$5:$D$48,MATCH(B12,Deliverables!$A$5:$A$48,0)),"")) -> 6.1 | E12: ="ACAS scan wk 1" -> ACAS scan wk 1 | F12: =Award+MOD(6-WEEKDAY(Award),7)+0 -> 46150 | J12: =IF(G12="","",WORKDAY(G12,ReviewDays)) | K12: =IF(AND(G12<>"",OR(H12="",H12="Pending"),Today>J12),"Past inspection window – deemed accepted","") | L12: =IF(AND(H12="Returned",I12<>""),WORKDAY(I12,ResubDays),"") | M12: =IF(OR(B12="",F12=""),"",IF(G12<>"",IF(G12<=F12,"On time","Late"),IF(Today>F12,"Overdue",IF(F12-Today<=7,"Due within 7 days","Not yet due")))) -> Overdue | N12: =IF(OR(M12="Late",M12="Overdue"),IF(G12<>"",G12-F12,Today-F12),"") -> 156 | O12: =IF(H12="Returned",1,0) -> 0 | Q12: Friday assumed; PWS says weekly only.
A13: 9 | B13: A007 | C13: =IF(B13="","",IFERROR(INDEX(Deliverables!$B$5:$B$48,MATCH(B13,Deliverables!$A$5:$A$48,0)),"ID not found")) -> ACAS Scans | D13: =IF(B13="","",IFERROR(INDEX(Deliverables!$D$5:$D$48,MATCH(B13,Deliverables!$A$5:$A$48,0)),"")) -> 6.1 | E13: ="ACAS scan wk 2" -> ACAS scan wk 2 | F13: =Award+MOD(6-WEEKDAY(Award),7)+7 -> 46157 | J13: =IF(G13="","",WORKDAY(G13,ReviewDays)) | K13: =IF(AND(G13<>"",OR(H13="",H13="Pending"),Today>J13),"Past inspection window – deemed accepted","") | L13: =IF(AND(H13="Returned",I13<>""),WORKDAY(I13,ResubDays),"") | M13: =IF(OR(B13="",F13=""),"",IF(G13<>"",IF(G13<=F13,"On time","Late"),IF(Today>F13,"Overdue",IF(F13-Today<=7,"Due within 7 days","Not yet due")))) -> Overdue | N13: =IF(OR(M13="Late",M13="Overdue"),IF(G13<>"",G13-F13,Today-F13),"") -> 149 | O13: =IF(H13="Returned",1,0) -> 0 | Q13: Friday assumed; PWS says weekly only.
A14: 10 | B14: A007 | C14: =IF(B14="","",IFERROR(INDEX(Deliverables!$B$5:$B$48,MATCH(B14,Deliverables!$A$5:$A$48,0)),"ID not found")) -> ACAS Scans | D14: =IF(B14="","",IFERROR(INDEX(Deliverables!$D$5:$D$48,MATCH(B14,Deliverables!$A$5:$A$48,0)),"")) -> 6.1 | E14: ="ACAS scan wk 3" -> ACAS scan wk 3 | F14: =Award+MOD(6-WEEKDAY(Award),7)+14 -> 46164 | J14: =IF(G14="","",WORKDAY(G14,ReviewDays)) | K14: =IF(AND(G14<>"",OR(H14="",H14="Pending"),Today>J14),"Past inspection window – deemed accepted","") | L14: =IF(AND(H14="Returned",I14<>""),WORKDAY(I14,ResubDays),"") | M14: =IF(OR(B14="",F14=""),"",IF(G14<>"",IF(G14<=F14,"On time","Late"),IF(Today>F14,"Overdue",IF(F14-Today<=7,"Due within 7 days","Not yet due")))) -> Overdue | N14: =IF(OR(M14="Late",M14="Overdue"),IF(G14<>"",G14-F14,Today-F14),"") -> 142 | O14: =IF(H14="Returned",1,0) -> 0 | Q14: Friday assumed; PWS says weekly only.
A15: 11 | B15: A007 | C15: =IF(B15="","",IFERROR(INDEX(Deliverables!$B$5:$B$48,MATCH(B15,Deliverables!$A$5:$A$48,0)),"ID not found")) -> ACAS Scans | D15: =IF(B15="","",IFERROR(INDEX(Deliverables!$D$5:$D$48,MATCH(B15,Deliverables!$A$5:$A$48,0)),"")) -> 6.1 | E15: ="ACAS scan wk 4" -> ACAS scan wk 4 | F15: =Award+MOD(6-WEEKDAY(Award),7)+21 -> 46171 | J15: =IF(G15="","",WORKDAY(G15,ReviewDays)) | K15: =IF(AND(G15<>"",OR(H15="",H15="Pending"),Today>J15),"Past inspection window – deemed accepted","") | L15: =IF(AND(H15="Returned",I15<>""),WORKDAY(I15,ResubDays),"") | M15: =IF(OR(B15="",F15=""),"",IF(G15<>"",IF(G15<=F15,"On time","Late"),IF(Today>F15,"Overdue",IF(F15-Today<=7,"Due within 7 days","Not yet due")))) -> Overdue | N15: =IF(OR(M15="Late",M15="Overdue"),IF(G15<>"",G15-F15,Today-F15),"") -> 135 | O15: =IF(H15="Returned",1,0) -> 0 | Q15: Friday assumed; PWS says weekly only.
A16: 12 | B16: A007 | C16: =IF(B16="","",IFERROR(INDEX(Deliverables!$B$5:$B$48,MATCH(B16,Deliverables!$A$5:$A$48,0)),"ID not found")) -> ACAS Scans | D16: =IF(B16="","",IFERROR(INDEX(Deliverables!$D$5:$D$48,MATCH(B16,Deliverables!$A$5:$A$48,0)),"")) -> 6.1 | E16: ="ACAS scan wk 5" -> ACAS scan wk 5 | F16: =Award+MOD(6-WEEKDAY(Award),7)+28 -> 46178 | J16: =IF(G16="","",WORKDAY(G16,ReviewDays)) | K16: =IF(AND(G16<>"",OR(H16="",H16="Pending"),Today>J16),"Past inspection window – deemed accepted","") | L16: =IF(AND(H16="Returned",I16<>""),WORKDAY(I16,ResubDays),"") | M16: =IF(OR(B16="",F16=""),"",IF(G16<>"",IF(G16<=F16,"On time","Late"),IF(Today>F16,"Overdue",IF(F16-Today<=7,"Due within 7 days","Not yet due")))) -> Overdue | N16: =IF(OR(M16="Late",M16="Overdue"),IF(G16<>"",G16-F16,Today-F16),"") -> 128 | O16: =IF(H16="Returned",1,0) -> 0 | Q16: Friday assumed; PWS says weekly only.
A17: 13 | B17: A007 | C17: =IF(B17="","",IFERROR(INDEX(Deliverables!$B$5:$B$48,MATCH(B17,Deliverables!$A$5:$A$48,0)),"ID not found")) -> ACAS Scans | D17: =IF(B17="","",IFERROR(INDEX(Deliverables!$D$5:$D$48,MATCH(B17,Deliverables!$A$5:$A$48,0)),"")) -> 6.1 | E17: ="ACAS scan wk 6" -> ACAS scan wk 6 | F17: =Award+MOD(6-WEEKDAY(Award),7)+35 -> 46185 | J17: =IF(G17="","",WORKDAY(G17,ReviewDays)) | K17: =IF(AND(G17<>"",OR(H17="",H17="Pending"),Today>J17),"Past inspection window – deemed accepted","") | L17: =IF(AND(H17="Returned",I17<>""),WORKDAY(I17,ResubDays),"") | M17: =IF(OR(B17="",F17=""),"",IF(G17<>"",IF(G17<=F17,"On time","Late"),IF(Today>F17,"Overdue",IF(F17-Today<=7,"Due within 7 days","Not yet due")))) -> Overdue | N17: =IF(OR(M17="Late",M17="Overdue"),IF(G17<>"",G17-F17,Today-F17),"") -> 121 | O17: =IF(H17="Returned",1,0) -> 0 | Q17: Friday assumed; PWS says weekly only.
A18: 14 | B18: A007 | C18: =IF(B18="","",IFERROR(INDEX(Deliverables!$B$5:$B$48,MATCH(B18,Deliverables!$A$5:$A$48,0)),"ID not found")) -> ACAS Scans | D18: =IF(B18="","",IFERROR(INDEX(Deliverables!$D$5:$D$48,MATCH(B18,Deliverables!$A$5:$A$48,0)),"")) -> 6.1 | E18: ="ACAS scan wk 7" -> ACAS scan wk 7 | F18: =Award+MOD(6-WEEKDAY(Award),7)+42 -> 46192 | J18: =IF(G18="","",WORKDAY(G18,ReviewDays)) | K18: =IF(AND(G18<>"",OR(H18="",H18="Pending"),Today>J18),"Past inspection window – deemed accepted","") | L18: =IF(AND(H18="Returned",I18<>""),WORKDAY(I18,ResubDays),"") | M18: =IF(OR(B18="",F18=""),"",IF(G18<>"",IF(G18<=F18,"On time","Late"),IF(Today>F18,"Overdue",IF(F18-Today<=7,"Due within 7 days","Not yet due")))) -> Overdue | N18: =IF(OR(M18="Late",M18="Overdue"),IF(G18<>"",G18-F18,Today-F18),"") -> 114 | O18: =IF(H18="Returned",1,0) -> 0 | Q18: Friday assumed; PWS says weekly only.
A19: 15 | B19: A007 | C19: =IF(B19="","",IFERROR(INDEX(Deliverables!$B$5:$B$48,MATCH(B19,Deliverables!$A$5:$A$48,0)),"ID not found")) -> ACAS Scans | D19: =IF(B19="","",IFERROR(INDEX(Deliverables!$D$5:$D$48,MATCH(B19,Deliverables!$A$5:$A$48,0)),"")) -> 6.1 | E19: ="ACAS scan wk 8" -> ACAS scan wk 8 | F19: =Award+MOD(6-WEEKDAY(Award),7)+49 -> 46199 | J19: =IF(G19="","",WORKDAY(G19,ReviewDays)) | K19: =IF(AND(G19<>"",OR(H19="",H19="Pending"),Today>J19),"Past inspection window – deemed accepted","") | L19: =IF(AND(H19="Returned",I19<>""),WORKDAY(I19,ResubDays),"") | M19: =IF(OR(B19="",F19=""),"",IF(G19<>"",IF(G19<=F19,"On time","Late"),IF(Today>F19,"Overdue",IF(F19-Today<=7,"Due within 7 days","Not yet due")))) -> Overdue | N19: =IF(OR(M19="Late",M19="Overdue"),IF(G19<>"",G19-F19,Today-F19),"") -> 107 | O19: =IF(H19="Returned",1,0) -> 0 | Q19: Friday assumed; PWS says weekly only.
A20: 16 | B20: A007 | C20: =IF(B20="","",IFERROR(INDEX(Deliverables!$B$5:$B$48,MATCH(B20,Deliverables!$A$5:$A$48,0)),"ID not found")) -> ACAS Scans | D20: =IF(B20="","",IFERROR(INDEX(Deliverables!$D$5:$D$48,MATCH(B20,Deliverables!$A$5:$A$48,0)),"")) -> 6.1 | E20: ="ACAS scan wk 9" -> ACAS scan wk 9 | F20: =Award+MOD(6-WEEKDAY(Award),7)+56 -> 46206 | J20: =IF(G20="","",WORKDAY(G20,ReviewDays)) | K20: =IF(AND(G20<>"",OR(H20="",H20="Pending"),Today>J20),"Past inspection window – deemed accepted","") | L20: =IF(AND(H20="Returned",I20<>""),WORKDAY(I20,ResubDays),"") | M20: =IF(OR(B20="",F20=""),"",IF(G20<>"",IF(G20<=F20,"On time","Late"),IF(Today>F20,"Overdue",IF(F20-Today<=7,"Due within 7 days","Not yet due")))) -> Overdue | N20: =IF(OR(M20="Late",M20="Overdue"),IF(G20<>"",G20-F20,Today-F20),"") -> 100 | O20: =IF(H20="Returned",1,0) -> 0 | Q20: Friday assumed; PWS says weekly only.
A21: 17 | B21: A007 | C21: =IF(B21="","",IFERROR(INDEX(Deliverables!$B$5:$B$48,MATCH(B21,Deliverables!$A$5:$A$48,0)),"ID not found")) -> ACAS Scans | D21: =IF(B21="","",IFERROR(INDEX(Deliverables!$D$5:$D$48,MATCH(B21,Deliverables!$A$5:$A$48,0)),"")) -> 6.1 | E21: ="ACAS scan wk 10" -> ACAS scan wk 10 | F21: =Award+MOD(6-WEEKDAY(Award),7)+63 -> 46213 | J21: =IF(G21="","",WORKDAY(G21,ReviewDays)) | K21: =IF(AND(G21<>"",OR(H21="",H21="Pending"),Today>J21),"Past inspection window – deemed accepted","") | L21: =IF(AND(H21="Returned",I21<>""),WORKDAY(I21,ResubDays),"") | M21: =IF(OR(B21="",F21=""),"",IF(G21<>"",IF(G21<=F21,"On time","Late"),IF(Today>F21,"Overdue",IF(F21-Today<=7,"Due within 7 days","Not yet due")))) -> Overdue | N21: =IF(OR(M21="Late",M21="Overdue"),IF(G21<>"",G21-F21,Today-F21),"") -> 93 | O21: =IF(H21="Returned",1,0) -> 0 | Q21: Friday assumed; PWS says weekly only.
A22: 18 | B22: A007 | C22: =IF(B22="","",IFERROR(INDEX(Deliverables!$B$5:$B$48,MATCH(B22,Deliverables!$A$5:$A$48,0)),"ID not found")) -> ACAS Scans | D22: =IF(B22="","",IFERROR(INDEX(Deliverables!$D$5:$D$48,MATCH(B22,Deliverables!$A$5:$A$48,0)),"")) -> 6.1 | E22: ="ACAS scan wk 11" -> ACAS scan wk 11 | F22: =Award+MOD(6-WEEKDAY(Award),7)+70 -> 46220 | J22: =IF(G22="","",WORKDAY(G22,ReviewDays)) | K22: =IF(AND(G22<>"",OR(H22="",H22="Pending"),Today>J22),"Past inspection window – deemed accepted","") | L22: =IF(AND(H22="Returned",I22<>""),WORKDAY(I22,ResubDays),"") | M22: =IF(OR(B22="",F22=""),"",IF(G22<>"",IF(G22<=F22,"On time","Late"),IF(Today>F22,"Overdue",IF(F22-Today<=7,"Due within 7 days","Not yet due")))) -> Overdue | N22: =IF(OR(M22="Late",M22="Overdue"),IF(G22<>"",G22-F22,Today-F22),"") -> 86 | O22: =IF(H22="Returned",1,0) -> 0 | Q22: Friday assumed; PWS says weekly only.
A23: 19 | B23: A007 | C23: =IF(B23="","",IFERROR(INDEX(Deliverables!$B$5:$B$48,MATCH(B23,Deliverables!$A$5:$A$48,0)),"ID not found")) -> ACAS Scans | D23: =IF(B23="","",IFERROR(INDEX(Deliverables!$D$5:$D$48,MATCH(B23,Deliverables!$A$5:$A$48,0)),"")) -> 6.1 | E23: ="ACAS scan wk 12" -> ACAS scan wk 12 | F23: =Award+MOD(6-WEEKDAY(Award),7)+77 -> 46227 | J23: =IF(G23="","",WORKDAY(G23,ReviewDays)) | K23: =IF(AND(G23<>"",OR(H23="",H23="Pending"),Today>J23),"Past inspection window – deemed accepted","") | L23: =IF(AND(H23="Returned",I23<>""),WORKDAY(I23,ResubDays),"") | M23: =IF(OR(B23="",F23=""),"",IF(G23<>"",IF(G23<=F23,"On time","Late"),IF(Today>F23,"Overdue",IF(F23-Today<=7,"Due within 7 days","Not yet due")))) -> Overdue | N23: =IF(OR(M23="Late",M23="Overdue"),IF(G23<>"",G23-F23,Today-F23),"") -> 79 | O23: =IF(H23="Returned",1,0) -> 0 | Q23: Friday assumed; PWS says weekly only.
A24: 20 | B24: A007 | C24: =IF(B24="","",IFERROR(INDEX(Deliverables!$B$5:$B$48,MATCH(B24,Deliverables!$A$5:$A$48,0)),"ID not found")) -> ACAS Scans | D24: =IF(B24="","",IFERROR(INDEX(Deliverables!$D$5:$D$48,MATCH(B24,Deliverables!$A$5:$A$48,0)),"")) -> 6.1 | E24: ="ACAS scan wk 13" -> ACAS scan wk 13 | F24: =Award+MOD(6-WEEKDAY(Award),7)+84 -> 46234 | J24: =IF(G24="","",WORKDAY(G24,ReviewDays)) | K24: =IF(AND(G24<>"",OR(H24="",H24="Pending"),Today>J24),"Past inspection window – deemed accepted","") | L24: =IF(AND(H24="Returned",I24<>""),WORKDAY(I24,ResubDays),"") | M24: =IF(OR(B24="",F24=""),"",IF(G24<>"",IF(G24<=F24,"On time","Late"),IF(Today>F24,"Overdue",IF(F24-Today<=7,"Due within 7 days","Not yet due")))) -> Overdue | N24: =IF(OR(M24="Late",M24="Overdue"),IF(G24<>"",G24-F24,Today-F24),"") -> 72 | O24: =IF(H24="Returned",1,0) -> 0 | Q24: Friday assumed; PWS says weekly only.
A25: 21 | B25: A007 | C25: =IF(B25="","",IFERROR(INDEX(Deliverables!$B$5:$B$48,MATCH(B25,Deliverables!$A$5:$A$48,0)),"ID not found")) -> ACAS Scans | D25: =IF(B25="","",IFERROR(INDEX(Deliverables!$D$5:$D$48,MATCH(B25,Deliverables!$A$5:$A$48,0)),"")) -> 6.1 | E25: ="ACAS scan wk 14" -> ACAS scan wk 14 | F25: =Award+MOD(6-WEEKDAY(Award),7)+91 -> 46241 | J25: =IF(G25="","",WORKDAY(G25,ReviewDays)) | K25: =IF(AND(G25<>"",OR(H25="",H25="Pending"),Today>J25),"Past inspection window – deemed accepted","") | L25: =IF(AND(H25="Returned",I25<>""),WORKDAY(I25,ResubDays),"") | M25: =IF(OR(B25="",F25=""),"",IF(G25<>"",IF(G25<=F25,"On time","Late"),IF(Today>F25,"Overdue",IF(F25-Today<=7,"Due within 7 days","Not yet due")))) -> Overdue | N25: =IF(OR(M25="Late",M25="Overdue"),IF(G25<>"",G25-F25,Today-F25),"") -> 65 | O25: =IF(H25="Returned",1,0) -> 0 | Q25: Friday assumed; PWS says weekly only.
A26: 22 | B26: A007 | C26: =IF(B26="","",IFERROR(INDEX(Deliverables!$B$5:$B$48,MATCH(B26,Deliverables!$A$5:$A$48,0)),"ID not found")) -> ACAS Scans | D26: =IF(B26="","",IFERROR(INDEX(Deliverables!$D$5:$D$48,MATCH(B26,Deliverables!$A$5:$A$48,0)),"")) -> 6.1 | E26: ="ACAS scan wk 15" -> ACAS scan wk 15 | F26: =Award+MOD(6-WEEKDAY(Award),7)+98 -> 46248 | J26: =IF(G26="","",WORKDAY(G26,ReviewDays)) | K26: =IF(AND(G26<>"",OR(H26="",H26="Pending"),Today>J26),"Past inspection window – deemed accepted","") | L26: =IF(AND(H26="Returned",I26<>""),WORKDAY(I26,ResubDays),"") | M26: =IF(OR(B26="",F26=""),"",IF(G26<>"",IF(G26<=F26,"On time","Late"),IF(Today>F26,"Overdue",IF(F26-Today<=7,"Due within 7 days","Not yet due")))) -> Overdue | N26: =IF(OR(M26="Late",M26="Overdue"),IF(G26<>"",G26-F26,Today-F26),"") -> 58 | O26: =IF(H26="Returned",1,0) -> 0 | Q26: Friday assumed; PWS says weekly only.
A27: 23 | B27: A007 | C27: =IF(B27="","",IFERROR(INDEX(Deliverables!$B$5:$B$48,MATCH(B27,Deliverables!$A$5:$A$48,0)),"ID not found")) -> ACAS Scans | D27: =IF(B27="","",IFERROR(INDEX(Deliverables!$D$5:$D$48,MATCH(B27,Deliverables!$A$5:$A$48,0)),"")) -> 6.1 | E27: ="ACAS scan wk 16" -> ACAS scan wk 16 | F27: =Award+MOD(6-WEEKDAY(Award),7)+105 -> 46255 | J27: =IF(G27="","",WORKDAY(G27,ReviewDays)) | K27: =IF(AND(G27<>"",OR(H27="",H27="Pending"),Today>J27),"Past inspection window – deemed accepted","") | L27: =IF(AND(H27="Returned",I27<>""),WORKDAY(I27,ResubDays),"") | M27: =IF(OR(B27="",F27=""),"",IF(G27<>"",IF(G27<=F27,"On time","Late"),IF(Today>F27,"Overdue",IF(F27-Today<=7,"Due within 7 days","Not yet due")))) -> Overdue | N27: =IF(OR(M27="Late",M27="Overdue"),IF(G27<>"",G27-F27,Today-F27),"") -> 51 | O27: =IF(H27="Returned",1,0) -> 0 | Q27: Friday assumed; PWS says weekly only.
A28: 24 | B28: A007 | C28: =IF(B28="","",IFERROR(INDEX(Deliverables!$B$5:$B$48,MATCH(B28,Deliverables!$A$5:$A$48,0)),"ID not found")) -> ACAS Scans | D28: =IF(B28="","",IFERROR(INDEX(Deliverables!$D$5:$D$48,MATCH(B28,Deliverables!$A$5:$A$48,0)),"")) -> 6.1 | E28: ="ACAS scan wk 17" -> ACAS scan wk 17 | F28: =Award+MOD(6-WEEKDAY(Award),7)+112 -> 46262 | J28: =IF(G28="","",WORKDAY(G28,ReviewDays)) | K28: =IF(AND(G28<>"",OR(H28="",H28="Pending"),Today>J28),"Past inspection window – deemed accepted","") | L28: =IF(AND(H28="Returned",I28<>""),WORKDAY(I28,ResubDays),"") | M28: =IF(OR(B28="",F28=""),"",IF(G28<>"",IF(G28<=F28,"On time","Late"),IF(Today>F28,"Overdue",IF(F28-Today<=7,"Due within 7 days","Not yet due")))) -> Overdue | N28: =IF(OR(M28="Late",M28="Overdue"),IF(G28<>"",G28-F28,Today-F28),"") -> 44 | O28: =IF(H28="Returned",1,0) -> 0 | Q28: Friday assumed; PWS says weekly only.
A29: 25 | B29: A007 | C29: =IF(B29="","",IFERROR(INDEX(Deliverables!$B$5:$B$48,MATCH(B29,Deliverables!$A$5:$A$48,0)),"ID not found")) -> ACAS Scans | D29: =IF(B29="","",IFERROR(INDEX(Deliverables!$D$5:$D$48,MATCH(B29,Deliverables!$A$5:$A$48,0)),"")) -> 6.1 | E29: ="ACAS scan wk 18" -> ACAS scan wk 18 | F29: =Award+MOD(6-WEEKDAY(Award),7)+119 -> 46269 | J29: =IF(G29="","",WORKDAY(G29,ReviewDays)) | K29: =IF(AND(G29<>"",OR(H29="",H29="Pending"),Today>J29),"Past inspection window – deemed accepted","") | L29: =IF(AND(H29="Returned",I29<>""),WORKDAY(I29,ResubDays),"") | M29: =IF(OR(B29="",F29=""),"",IF(G29<>"",IF(G29<=F29,"On time","Late"),IF(Today>F29,"Overdue",IF(F29-Today<=7,"Due within 7 days","Not yet due")))) -> Overdue | N29: =IF(OR(M29="Late",M29="Overdue"),IF(G29<>"",G29-F29,Today-F29),"") -> 37 | O29: =IF(H29="Returned",1,0) -> 0 | Q29: Friday assumed; PWS says weekly only.
A30: 26 | B30: A007 | C30: =IF(B30="","",IFERROR(INDEX(Deliverables!$B$5:$B$48,MATCH(B30,Deliverables!$A$5:$A$48,0)),"ID not found")) -> ACAS Scans | D30: =IF(B30="","",IFERROR(INDEX(Deliverables!$D$5:$D$48,MATCH(B30,Deliverables!$A$5:$A$48,0)),"")) -> 6.1 | E30: ="ACAS scan wk 19" -> ACAS scan wk 19 | F30: =Award+MOD(6-WEEKDAY(Award),7)+126 -> 46276 | J30: =IF(G30="","",WORKDAY(G30,ReviewDays)) | K30: =IF(AND(G30<>"",OR(H30="",H30="Pending"),Today>J30),"Past inspection window – deemed accepted","") | L30: =IF(AND(H30="Returned",I30<>""),WORKDAY(I30,ResubDays),"") | M30: =IF(OR(B30="",F30=""),"",IF(G30<>"",IF(G30<=F30,"On time","Late"),IF(Today>F30,"Overdue",IF(F30-Today<=7,"Due within 7 days","Not yet due")))) -> Overdue | N30: =IF(OR(M30="Late",M30="Overdue"),IF(G30<>"",G30-F30,Today-F30),"") -> 30 | O30: =IF(H30="Returned",1,0) -> 0 | Q30: Friday assumed; PWS says weekly only.
A31: 27 | B31: A007 | C31: =IF(B31="","",IFERROR(INDEX(Deliverables!$B$5:$B$48,MATCH(B31,Deliverables!$A$5:$A$48,0)),"ID not found")) -> ACAS Scans | D31: =IF(B31="","",IFERROR(INDEX(Deliverables!$D$5:$D$48,MATCH(B31,Deliverables!$A$5:$A$48,0)),"")) -> 6.1 | E31: ="ACAS scan wk 20" -> ACAS scan wk 20 | F31: =Award+MOD(6-WEEKDAY(Award),7)+133 -> 46283 | J31: =IF(G31="","",WORKDAY(G31,ReviewDays)) | K31: =IF(AND(G31<>"",OR(H31="",H31="Pending"),Today>J31),"Past inspection window – deemed accepted","") | L31: =IF(AND(H31="Returned",I31<>""),WORKDAY(I31,ResubDays),"") | M31: =IF(OR(B31="",F31=""),"",IF(G31<>"",IF(G31<=F31,"On time","Late"),IF(Today>F31,"Overdue",IF(F31-Today<=7,"Due within 7 days","Not yet due")))) -> Overdue | N31: =IF(OR(M31="Late",M31="Overdue"),IF(G31<>"",G31-F31,Today-F31),"") -> 23 | O31: =IF(H31="Returned",1,0) -> 0 | Q31: Friday assumed; PWS says weekly only.
A32: 28 | B32: A007 | C32: =IF(B32="","",IFERROR(INDEX(Deliverables!$B$5:$B$48,MATCH(B32,Deliverables!$A$5:$A$48,0)),"ID not found")) -> ACAS Scans | D32: =IF(B32="","",IFERROR(INDEX(Deliverables!$D$5:$D$48,MATCH(B32,Deliverables!$A$5:$A$48,0)),"")) -> 6.1 | E32: ="ACAS scan wk 21" -> ACAS scan wk 21 | F32: =Award+MOD(6-WEEKDAY(Award),7)+140 -> 46290 | J32: =IF(G32="","",WORKDAY(G32,ReviewDays)) | K32: =IF(AND(G32<>"",OR(H32="",H32="Pending"),Today>J32),"Past inspection window – deemed accepted","") | L32: =IF(AND(H32="Returned",I32<>""),WORKDAY(I32,ResubDays),"") | M32: =IF(OR(B32="",F32=""),"",IF(G32<>"",IF(G32<=F32,"On time","Late"),IF(Today>F32,"Overdue",IF(F32-Today<=7,"Due within 7 days","Not yet due")))) -> Overdue | N32: =IF(OR(M32="Late",M32="Overdue"),IF(G32<>"",G32-F32,Today-F32),"") -> 16 | O32: =IF(H32="Returned",1,0) -> 0 | Q32: Friday assumed; PWS says weekly only.
A33: 29 | B33: A007 | C33: =IF(B33="","",IFERROR(INDEX(Deliverables!$B$5:$B$48,MATCH(B33,Deliverables!$A$5:$A$48,0)),"ID not found")) -> ACAS Scans | D33: =IF(B33="","",IFERROR(INDEX(Deliverables!$D$5:$D$48,MATCH(B33,Deliverables!$A$5:$A$48,0)),"")) -> 6.1 | E33: ="ACAS scan wk 22" -> ACAS scan wk 22 | F33: =Award+MOD(6-WEEKDAY(Award),7)+147 -> 46297 | J33: =IF(G33="","",WORKDAY(G33,ReviewDays)) | K33: =IF(AND(G33<>"",OR(H33="",H33="Pending"),Today>J33),"Past inspection window – deemed accepted","") | L33: =IF(AND(H33="Returned",I33<>""),WORKDAY(I33,ResubDays),"") | M33: =IF(OR(B33="",F33=""),"",IF(G33<>"",IF(G33<=F33,"On time","Late"),IF(Today>F33,"Overdue",IF(F33-Today<=7,"Due within 7 days","Not yet due")))) -> Overdue | N33: =IF(OR(M33="Late",M33="Overdue"),IF(G33<>"",G33-F33,Today-F33),"") -> 9 | O33: =IF(H33="Returned",1,0) -> 0 | Q33: Friday assumed; PWS says weekly only.
A34: 30 | B34: A007 | C34: =IF(B34="","",IFERROR(INDEX(Deliverables!$B$5:$B$48,MATCH(B34,Deliverables!$A$5:$A$48,0)),"ID not found")) -> ACAS Scans | D34: =IF(B34="","",IFERROR(INDEX(Deliverables!$D$5:$D$48,MATCH(B34,Deliverables!$A$5:$A$48,0)),"")) -> 6.1 | E34: ="ACAS scan wk 23" -> ACAS scan wk 23 | F34: =Award+MOD(6-WEEKDAY(Award),7)+154 -> 46304 | J34: =IF(G34="","",WORKDAY(G34,ReviewDays)) | K34: =IF(AND(G34<>"",OR(H34="",H34="Pending"),Today>J34),"Past inspection window – deemed accepted","") | L34: =IF(AND(H34="Returned",I34<>""),WORKDAY(I34,ResubDays),"") | M34: =IF(OR(B34="",F34=""),"",IF(G34<>"",IF(G34<=F34,"On time","Late"),IF(Today>F34,"Overdue",IF(F34-Today<=7,"Due within 7 days","Not yet due")))) -> Overdue | N34: =IF(OR(M34="Late",M34="Overdue"),IF(G34<>"",G34-F34,Today-F34),"") -> 2 | O34: =IF(H34="Returned",1,0) -> 0 | Q34: Friday assumed; PWS says weekly only.
A35: 31 | B35: A007 | C35: =IF(B35="","",IFERROR(INDEX(Deliverables!$B$5:$B$48,MATCH(B35,Deliverables!$A$5:$A$48,0)),"ID not found")) -> ACAS Scans | D35: =IF(B35="","",IFERROR(INDEX(Deliverables!$D$5:$D$48,MATCH(B35,Deliverables!$A$5:$A$48,0)),"")) -> 6.1 | E35: ="ACAS scan wk 24" -> ACAS scan wk 24 | F35: =Award+MOD(6-WEEKDAY(Award),7)+161 -> 46311 | J35: =IF(G35="","",WORKDAY(G35,ReviewDays)) | K35: =IF(AND(G35<>"",OR(H35="",H35="Pending"),Today>J35),"Past inspection window – deemed accepted","") | L35: =IF(AND(H35="Returned",I35<>""),WORKDAY(I35,ResubDays),"") | M35: =IF(OR(B35="",F35=""),"",IF(G35<>"",IF(G35<=F35,"On time","Late"),IF(Today>F35,"Overdue",IF(F35-Today<=7,"Due within 7 days","Not yet due")))) -> Due within 7 days | N35: =IF(OR(M35="Late",M35="Overdue"),IF(G35<>"",G35-F35,Today-F35),"") | O35: =IF(H35="Returned",1,0) -> 0 | Q35: Friday assumed; PWS says weekly only.
A36: 32 | B36: A007 | C36: =IF(B36="","",IFERROR(INDEX(Deliverables!$B$5:$B$48,MATCH(B36,Deliverables!$A$5:$A$48,0)),"ID not found")) -> ACAS Scans | D36: =IF(B36="","",IFERROR(INDEX(Deliverables!$D$5:$D$48,MATCH(B36,Deliverables!$A$5:$A$48,0)),"")) -> 6.1 | E36: ="ACAS scan wk 25" -> ACAS scan wk 25 | F36: =Award+MOD(6-WEEKDAY(Award),7)+168 -> 46318 | J36: =IF(G36="","",WORKDAY(G36,ReviewDays)) | K36: =IF(AND(G36<>"",OR(H36="",H36="Pending"),Today>J36),"Past inspection window – deemed accepted","") | L36: =IF(AND(H36="Returned",I36<>""),WORKDAY(I36,ResubDays),"") | M36: =IF(OR(B36="",F36=""),"",IF(G36<>"",IF(G36<=F36,"On time","Late"),IF(Today>F36,"Overdue",IF(F36-Today<=7,"Due within 7 days","Not yet due")))) -> Not yet due | N36: =IF(OR(M36="Late",M36="Overdue"),IF(G36<>"",G36-F36,Today-F36),"") | O36: =IF(H36="Returned",1,0) -> 0 | Q36: Friday assumed; PWS says weekly only.
A37: 33 | B37: A007 | C37: =IF(B37="","",IFERROR(INDEX(Deliverables!$B$5:$B$48,MATCH(B37,Deliverables!$A$5:$A$48,0)),"ID not found")) -> ACAS Scans | D37: =IF(B37="","",IFERROR(INDEX(Deliverables!$D$5:$D$48,MATCH(B37,Deliverables!$A$5:$A$48,0)),"")) -> 6.1 | E37: ="ACAS scan wk 26" -> ACAS scan wk 26 | F37: =Award+MOD(6-WEEKDAY(Award),7)+175 -> 46325 | J37: =IF(G37="","",WORKDAY(G37,ReviewDays)) | K37: =IF(AND(G37<>"",OR(H37="",H37="Pending"),Today>J37),"Past inspection window – deemed accepted","") | L37: =IF(AND(H37="Returned",I37<>""),WORKDAY(I37,ResubDays),"") | M37: =IF(OR(B37="",F37=""),"",IF(G37<>"",IF(G37<=F37,"On time","Late"),IF(Today>F37,"Overdue",IF(F37-Today<=7,"Due within 7 days","Not yet due")))) -> Not yet due | N37: =IF(OR(M37="Late",M37="Overdue"),IF(G37<>"",G37-F37,Today-F37),"") | O37: =IF(H37="Returned",1,0) -> 0 | Q37: Friday assumed; PWS says weekly only.
A38: 34 | B38: A007 | C38: =IF(B38="","",IFERROR(INDEX(Deliverables!$B$5:$B$48,MATCH(B38,Deliverables!$A$5:$A$48,0)),"ID not found")) -> ACAS Scans | D38: =IF(B38="","",IFERROR(INDEX(Deliverables!$D$5:$D$48,MATCH(B38,Deliverables!$A$5:$A$48,0)),"")) -> 6.1 | E38: ="ACAS scan wk 27" -> ACAS scan wk 27 | F38: =Award+MOD(6-WEEKDAY(Award),7)+182 -> 46332 | J38: =IF(G38="","",WORKDAY(G38,ReviewDays)) | K38: =IF(AND(G38<>"",OR(H38="",H38="Pending"),Today>J38),"Past inspection window – deemed accepted","") | L38: =IF(AND(H38="Returned",I38<>""),WORKDAY(I38,ResubDays),"") | M38: =IF(OR(B38="",F38=""),"",IF(G38<>"",IF(G38<=F38,"On time","Late"),IF(Today>F38,"Overdue",IF(F38-Today<=7,"Due within 7 days","Not yet due")))) -> Not yet due | N38: =IF(OR(M38="Late",M38="Overdue"),IF(G38<>"",G38-F38,Today-F38),"") | O38: =IF(H38="Returned",1,0) -> 0 | Q38: Friday assumed; PWS says weekly only.
A39: 35 | B39: A007 | C39: =IF(B39="","",IFERROR(INDEX(Deliverables!$B$5:$B$48,MATCH(B39,Deliverables!$A$5:$A$48,0)),"ID not found")) -> ACAS Scans | D39: =IF(B39="","",IFERROR(INDEX(Deliverables!$D$5:$D$48,MATCH(B39,Deliverables!$A$5:$A$48,0)),"")) -> 6.1 | E39: ="ACAS scan wk 28" -> ACAS scan wk 28 | F39: =Award+MOD(6-WEEKDAY(Award),7)+189 -> 46339 | J39: =IF(G39="","",WORKDAY(G39,ReviewDays)) | K39: =IF(AND(G39<>"",OR(H39="",H39="Pending"),Today>J39),"Past inspection window – deemed accepted","") | L39: =IF(AND(H39="Returned",I39<>""),WORKDAY(I39,ResubDays),"") | M39: =IF(OR(B39="",F39=""),"",IF(G39<>"",IF(G39<=F39,"On time","Late"),IF(Today>F39,"Overdue",IF(F39-Today<=7,"Due within 7 days","Not yet due")))) -> Not yet due | N39: =IF(OR(M39="Late",M39="Overdue"),IF(G39<>"",G39-F39,Today-F39),"") | O39: =IF(H39="Returned",1,0) -> 0 | Q39: Friday assumed; PWS says weekly only.
A40: 36 | B40: A007 | C40: =IF(B40="","",IFERROR(INDEX(Deliverables!$B$5:$B$48,MATCH(B40,Deliverables!$A$5:$A$48,0)),"ID not found")) -> ACAS Scans | D40: =IF(B40="","",IFERROR(INDEX(Deliverables!$D$5:$D$48,MATCH(B40,Deliverables!$A$5:$A$48,0)),"")) -> 6.1 | E40: ="ACAS scan wk 29" -> ACAS scan wk 29 | F40: =Award+MOD(6-WEEKDAY(Award),7)+196 -> 46346 | J40: =IF(G40="","",WORKDAY(G40,ReviewDays)) | K40: =IF(AND(G40<>"",OR(H40="",H40="Pending"),Today>J40),"Past inspection window – deemed accepted","") | L40: =IF(AND(H40="Returned",I40<>""),WORKDAY(I40,ResubDays),"") | M40: =IF(OR(B40="",F40=""),"",IF(G40<>"",IF(G40<=F40,"On time","Late"),IF(Today>F40,"Overdue",IF(F40-Today<=7,"Due within 7 days","Not yet due")))) -> Not yet due | N40: =IF(OR(M40="Late",M40="Overdue"),IF(G40<>"",G40-F40,Today-F40),"") | O40: =IF(H40="Returned",1,0) -> 0 | Q40: Friday assumed; PWS says weekly only.
A41: 37 | B41: A007 | C41: =IF(B41="","",IFERROR(INDEX(Deliverables!$B$5:$B$48,MATCH(B41,Deliverables!$A$5:$A$48,0)),"ID not found")) -> ACAS Scans | D41: =IF(B41="","",IFERROR(INDEX(Deliverables!$D$5:$D$48,MATCH(B41,Deliverables!$A$5:$A$48,0)),"")) -> 6.1 | E41: ="ACAS scan wk 30" -> ACAS scan wk 30 | F41: =Award+MOD(6-WEEKDAY(Award),7)+203 -> 46353 | J41: =IF(G41="","",WORKDAY(G41,ReviewDays)) | K41: =IF(AND(G41<>"",OR(H41="",H41="Pending"),Today>J41),"Past inspection window – deemed accepted","") | L41: =IF(AND(H41="Returned",I41<>""),WORKDAY(I41,ResubDays),"") | M41: =IF(OR(B41="",F41=""),"",IF(G41<>"",IF(G41<=F41,"On time","Late"),IF(Today>F41,"Overdue",IF(F41-Today<=7,"Due within 7 days","Not yet due")))) -> Not yet due | N41: =IF(OR(M41="Late",M41="Overdue"),IF(G41<>"",G41-F41,Today-F41),"") | O41: =IF(H41="Returned",1,0) -> 0 | Q41: Friday assumed; PWS says weekly only.
A42: 38 | B42: A007 | C42: =IF(B42="","",IFERROR(INDEX(Deliverables!$B$5:$B$48,MATCH(B42,Deliverables!$A$5:$A$48,0)),"ID not found")) -> ACAS Scans | D42: =IF(B42="","",IFERROR(INDEX(Deliverables!$D$5:$D$48,MATCH(B42,Deliverables!$A$5:$A$48,0)),"")) -> 6.1 | E42: ="ACAS scan wk 31" -> ACAS scan wk 31 | F42: =Award+MOD(6-WEEKDAY(Award),7)+210 -> 46360 | J42: =IF(G42="","",WORKDAY(G42,ReviewDays)) | K42: =IF(AND(G42<>"",OR(H42="",H42="Pending"),Today>J42),"Past inspection window – deemed accepted","") | L42: =IF(AND(H42="Returned",I42<>""),WORKDAY(I42,ResubDays),"") | M42: =IF(OR(B42="",F42=""),"",IF(G42<>"",IF(G42<=F42,"On time","Late"),IF(Today>F42,"Overdue",IF(F42-Today<=7,"Due within 7 days","Not yet due")))) -> Not yet due | N42: =IF(OR(M42="Late",M42="Overdue"),IF(G42<>"",G42-F42,Today-F42),"") | O42: =IF(H42="Returned",1,0) -> 0 | Q42: Friday assumed; PWS says weekly only.
A43: 39 | B43: A007 | C43: =IF(B43="","",IFERROR(INDEX(Deliverables!$B$5:$B$48,MATCH(B43,Deliverables!$A$5:$A$48,0)),"ID not found")) -> ACAS Scans | D43: =IF(B43="","",IFERROR(INDEX(Deliverables!$D$5:$D$48,MATCH(B43,Deliverables!$A$5:$A$48,0)),"")) -> 6.1 | E43: ="ACAS scan wk 32" -> ACAS scan wk 32 | F43: =Award+MOD(6-WEEKDAY(Award),7)+217 -> 46367 | J43: =IF(G43="","",WORKDAY(G43,ReviewDays)) | K43: =IF(AND(G43<>"",OR(H43="",H43="Pending"),Today>J43),"Past inspection window – deemed accepted","") | L43: =IF(AND(H43="Returned",I43<>""),WORKDAY(I43,ResubDays),"") | M43: =IF(OR(B43="",F43=""),"",IF(G43<>"",IF(G43<=F43,"On time","Late"),IF(Today>F43,"Overdue",IF(F43-Today<=7,"Due within 7 days","Not yet due")))) -> Not yet due | N43: =IF(OR(M43="Late",M43="Overdue"),IF(G43<>"",G43-F43,Today-F43),"") | O43: =IF(H43="Returned",1,0) -> 0 | Q43: Friday assumed; PWS says weekly only.
A44: 40 | B44: A007 | C44: =IF(B44="","",IFERROR(INDEX(Deliverables!$B$5:$B$48,MATCH(B44,Deliverables!$A$5:$A$48,0)),"ID not found")) -> ACAS Scans | D44: =IF(B44="","",IFERROR(INDEX(Deliverables!$D$5:$D$48,MATCH(B44,Deliverables!$A$5:$A$48,0)),"")) -> 6.1 | E44: ="ACAS scan wk 33" -> ACAS scan wk 33 | F44: =Award+MOD(6-WEEKDAY(Award),7)+224 -> 46374 | J44: =IF(G44="","",WORKDAY(G44,ReviewDays)) | K44: =IF(AND(G44<>"",OR(H44="",H44="Pending"),Today>J44),"Past inspection window – deemed accepted","") | L44: =IF(AND(H44="Returned",I44<>""),WORKDAY(I44,ResubDays),"") | M44: =IF(OR(B44="",F44=""),"",IF(G44<>"",IF(G44<=F44,"On time","Late"),IF(Today>F44,"Overdue",IF(F44-Today<=7,"Due within 7 days","Not yet due")))) -> Not yet due | N44: =IF(OR(M44="Late",M44="Overdue"),IF(G44<>"",G44-F44,Today-F44),"") | O44: =IF(H44="Returned",1,0) -> 0 | Q44: Friday assumed; PWS says weekly only.
A45: 41 | B45: A007 | C45: =IF(B45="","",IFERROR(INDEX(Deliverables!$B$5:$B$48,MATCH(B45,Deliverables!$A$5:$A$48,0)),"ID not found")) -> ACAS Scans | D45: =IF(B45="","",IFERROR(INDEX(Deliverables!$D$5:$D$48,MATCH(B45,Deliverables!$A$5:$A$48,0)),"")) -> 6.1 | E45: ="ACAS scan wk 34" -> ACAS scan wk 34 | F45: =Award+MOD(6-WEEKDAY(Award),7)+231 -> 46381 | J45: =IF(G45="","",WORKDAY(G45,ReviewDays)) | K45: =IF(AND(G45<>"",OR(H45="",H45="Pending"),Today>J45),"Past inspection window – deemed accepted","") | L45: =IF(AND(H45="Returned",I45<>""),WORKDAY(I45,ResubDays),"") | M45: =IF(OR(B45="",F45=""),"",IF(G45<>"",IF(G45<=F45,"On time","Late"),IF(Today>F45,"Overdue",IF(F45-Today<=7,"Due within 7 days","Not yet due")))) -> Not yet due | N45: =IF(OR(M45="Late",M45="Overdue"),IF(G45<>"",G45-F45,Today-F45),"") | O45: =IF(H45="Returned",1,0) -> 0 | Q45: Friday assumed; PWS says weekly only.
A46: 42 | B46: A007 | C46: =IF(B46="","",IFERROR(INDEX(Deliverables!$B$5:$B$48,MATCH(B46,Deliverables!$A$5:$A$48,0)),"ID not found")) -> ACAS Scans | D46: =IF(B46="","",IFERROR(INDEX(Deliverables!$D$5:$D$48,MATCH(B46,Deliverables!$A$5:$A$48,0)),"")) -> 6.1 | E46: ="ACAS scan wk 35" -> ACAS scan wk 35 | F46: =Award+MOD(6-WEEKDAY(Award),7)+238 -> 46388 | J46: =IF(G46="","",WORKDAY(G46,ReviewDays)) | K46: =IF(AND(G46<>"",OR(H46="",H46="Pending"),Today>J46),"Past inspection window – deemed accepted","") | L46: =IF(AND(H46="Returned",I46<>""),WORKDAY(I46,ResubDays),"") | M46: =IF(OR(B46="",F46=""),"",IF(G46<>"",IF(G46<=F46,"On time","Late"),IF(Today>F46,"Overdue",IF(F46-Today<=7,"Due within 7 days","Not yet due")))) -> Not yet due | N46: =IF(OR(M46="Late",M46="Overdue"),IF(G46<>"",G46-F46,Today-F46),"") | O46: =IF(H46="Returned",1,0) -> 0 | Q46: Friday assumed; PWS says weekly only.
A47: 43 | B47: A007 | C47: =IF(B47="","",IFERROR(INDEX(Deliverables!$B$5:$B$48,MATCH(B47,Deliverables!$A$5:$A$48,0)),"ID not found")) -> ACAS Scans | D47: =IF(B47="","",IFERROR(INDEX(Deliverables!$D$5:$D$48,MATCH(B47,Deliverables!$A$5:$A$48,0)),"")) -> 6.1 | E47: ="ACAS scan wk 36" -> ACAS scan wk 36 | F47: =Award+MOD(6-WEEKDAY(Award),7)+245 -> 46395 | J47: =IF(G47="","",WORKDAY(G47,ReviewDays)) | K47: =IF(AND(G47<>"",OR(H47="",H47="Pending"),Today>J47),"Past inspection window – deemed accepted","") | L47: =IF(AND(H47="Returned",I47<>""),WORKDAY(I47,ResubDays),"") | M47: =IF(OR(B47="",F47=""),"",IF(G47<>"",IF(G47<=F47,"On time","Late"),IF(Today>F47,"Overdue",IF(F47-Today<=7,"Due within 7 days","Not yet due")))) -> Not yet due | N47: =IF(OR(M47="Late",M47="Overdue"),IF(G47<>"",G47-F47,Today-F47),"") | O47: =IF(H47="Returned",1,0) -> 0 | Q47: Friday assumed; PWS says weekly only.
A48: 44 | B48: A007 | C48: =IF(B48="","",IFERROR(INDEX(Deliverables!$B$5:$B$48,MATCH(B48,Deliverables!$A$5:$A$48,0)),"ID not found")) -> ACAS Scans | D48: =IF(B48="","",IFERROR(INDEX(Deliverables!$D$5:$D$48,MATCH(B48,Deliverables!$A$5:$A$48,0)),"")) -> 6.1 | E48: ="ACAS scan wk 37" -> ACAS scan wk 37 | F48: =Award+MOD(6-WEEKDAY(Award),7)+252 -> 46402 | J48: =IF(G48="","",WORKDAY(G48,ReviewDays)) | K48: =IF(AND(G48<>"",OR(H48="",H48="Pending"),Today>J48),"Past inspection window – deemed accepted","") | L48: =IF(AND(H48="Returned",I48<>""),WORKDAY(I48,ResubDays),"") | M48: =IF(OR(B48="",F48=""),"",IF(G48<>"",IF(G48<=F48,"On time","Late"),IF(Today>F48,"Overdue",IF(F48-Today<=7,"Due within 7 days","Not yet due")))) -> Not yet due | N48: =IF(OR(M48="Late",M48="Overdue"),IF(G48<>"",G48-F48,Today-F48),"") | O48: =IF(H48="Returned",1,0) -> 0 | Q48: Friday assumed; PWS says weekly only.
A49: 45 | B49: A007 | C49: =IF(B49="","",IFERROR(INDEX(Deliverables!$B$5:$B$48,MATCH(B49,Deliverables!$A$5:$A$48,0)),"ID not found")) -> ACAS Scans | D49: =IF(B49="","",IFERROR(INDEX(Deliverables!$D$5:$D$48,MATCH(B49,Deliverables!$A$5:$A$48,0)),"")) -> 6.1 | E49: ="ACAS scan wk 38" -> ACAS scan wk 38 | F49: =Award+MOD(6-WEEKDAY(Award),7)+259 -> 46409 | J49: =IF(G49="","",WORKDAY(G49,ReviewDays)) | K49: =IF(AND(G49<>"",OR(H49="",H49="Pending"),Today>J49),"Past inspection window – deemed accepted","") | L49: =IF(AND(H49="Returned",I49<>""),WORKDAY(I49,ResubDays),"") | M49: =IF(OR(B49="",F49=""),"",IF(G49<>"",IF(G49<=F49,"On time","Late"),IF(Today>F49,"Overdue",IF(F49-Today<=7,"Due within 7 days","Not yet due")))) -> Not yet due | N49: =IF(OR(M49="Late",M49="Overdue"),IF(G49<>"",G49-F49,Today-F49),"") | O49: =IF(H49="Returned",1,0) -> 0 | Q49: Friday assumed; PWS says weekly only.
A50: 46 | B50: A007 | C50: =IF(B50="","",IFERROR(INDEX(Deliverables!$B$5:$B$48,MATCH(B50,Deliverables!$A$5:$A$48,0)),"ID not found")) -> ACAS Scans | D50: =IF(B50="","",IFERROR(INDEX(Deliverables!$D$5:$D$48,MATCH(B50,Deliverables!$A$5:$A$48,0)),"")) -> 6.1 | E50: ="ACAS scan wk 39" -> ACAS scan wk 39 | F50: =Award+MOD(6-WEEKDAY(Award),7)+266 -> 46416 | J50: =IF(G50="","",WORKDAY(G50,ReviewDays)) | K50: =IF(AND(G50<>"",OR(H50="",H50="Pending"),Today>J50),"Past inspection window – deemed accepted","") | L50: =IF(AND(H50="Returned",I50<>""),WORKDAY(I50,ResubDays),"") | M50: =IF(OR(B50="",F50=""),"",IF(G50<>"",IF(G50<=F50,"On time","Late"),IF(Today>F50,"Overdue",IF(F50-Today<=7,"Due within 7 days","Not yet due")))) -> Not yet due | N50: =IF(OR(M50="Late",M50="Overdue"),IF(G50<>"",G50-F50,Today-F50),"") | O50: =IF(H50="Returned",1,0) -> 0 | Q50: Friday assumed; PWS says weekly only.
A51: 47 | B51: A007 | C51: =IF(B51="","",IFERROR(INDEX(Deliverables!$B$5:$B$48,MATCH(B51,Deliverables!$A$5:$A$48,0)),"ID not found")) -> ACAS Scans | D51: =IF(B51="","",IFERROR(INDEX(Deliverables!$D$5:$D$48,MATCH(B51,Deliverables!$A$5:$A$48,0)),"")) -> 6.1 | E51: ="ACAS scan wk 40" -> ACAS scan wk 40 | F51: =Award+MOD(6-WEEKDAY(Award),7)+273 -> 46423 | J51: =IF(G51="","",WORKDAY(G51,ReviewDays)) | K51: =IF(AND(G51<>"",OR(H51="",H51="Pending"),Today>J51),"Past inspection window – deemed accepted","") | L51: =IF(AND(H51="Returned",I51<>""),WORKDAY(I51,ResubDays),"") | M51: =IF(OR(B51="",F51=""),"",IF(G51<>"",IF(G51<=F51,"On time","Late"),IF(Today>F51,"Overdue",IF(F51-Today<=7,"Due within 7 days","Not yet due")))) -> Not yet due | N51: =IF(OR(M51="Late",M51="Overdue"),IF(G51<>"",G51-F51,Today-F51),"") | O51: =IF(H51="Returned",1,0) -> 0 | Q51: Friday assumed; PWS says weekly only.
A52: 48 | B52: A007 | C52: =IF(B52="","",IFERROR(INDEX(Deliverables!$B$5:$B$48,MATCH(B52,Deliverables!$A$5:$A$48,0)),"ID not found")) -> ACAS Scans | D52: =IF(B52="","",IFERROR(INDEX(Deliverables!$D$5:$D$48,MATCH(B52,Deliverables!$A$5:$A$48,0)),"")) -> 6.1 | E52: ="ACAS scan wk 41" -> ACAS scan wk 41 | F52: =Award+MOD(6-WEEKDAY(Award),7)+280 -> 46430 | J52: =IF(G52="","",WORKDAY(G52,ReviewDays)) | K52: =IF(AND(G52<>"",OR(H52="",H52="Pending"),Today>J52),"Past inspection window – deemed accepted","") | L52: =IF(AND(H52="Returned",I52<>""),WORKDAY(I52,ResubDays),"") | M52: =IF(OR(B52="",F52=""),"",IF(G52<>"",IF(G52<=F52,"On time","Late"),IF(Today>F52,"Overdue",IF(F52-Today<=7,"Due within 7 days","Not yet due")))) -> Not yet due | N52: =IF(OR(M52="Late",M52="Overdue"),IF(G52<>"",G52-F52,Today-F52),"") | O52: =IF(H52="Returned",1,0) -> 0 | Q52: Friday assumed; PWS says weekly only.
A53: 49 | B53: A007 | C53: =IF(B53="","",IFERROR(INDEX(Deliverables!$B$5:$B$48,MATCH(B53,Deliverables!$A$5:$A$48,0)),"ID not found")) -> ACAS Scans | D53: =IF(B53="","",IFERROR(INDEX(Deliverables!$D$5:$D$48,MATCH(B53,Deliverables!$A$5:$A$48,0)),"")) -> 6.1 | E53: ="ACAS scan wk 42" -> ACAS scan wk 42 | F53: =Award+MOD(6-WEEKDAY(Award),7)+287 -> 46437 | J53: =IF(G53="","",WORKDAY(G53,ReviewDays)) | K53: =IF(AND(G53<>"",OR(H53="",H53="Pending"),Today>J53),"Past inspection window – deemed accepted","") | L53: =IF(AND(H53="Returned",I53<>""),WORKDAY(I53,ResubDays),"") | M53: =IF(OR(B53="",F53=""),"",IF(G53<>"",IF(G53<=F53,"On time","Late"),IF(Today>F53,"Overdue",IF(F53-Today<=7,"Due within 7 days","Not yet due")))) -> Not yet due | N53: =IF(OR(M53="Late",M53="Overdue"),IF(G53<>"",G53-F53,Today-F53),"") | O53: =IF(H53="Returned",1,0) -> 0 | Q53: Friday assumed; PWS says weekly only.
A54: 50 | B54: A007 | C54: =IF(B54="","",IFERROR(INDEX(Deliverables!$B$5:$B$48,MATCH(B54,Deliverables!$A$5:$A$48,0)),"ID not found")) -> ACAS Scans | D54: =IF(B54="","",IFERROR(INDEX(Deliverables!$D$5:$D$48,MATCH(B54,Deliverables!$A$5:$A$48,0)),"")) -> 6.1 | E54: ="ACAS scan wk 43" -> ACAS scan wk 43 | F54: =Award+MOD(6-WEEKDAY(Award),7)+294 -> 46444 | J54: =IF(G54="","",WORKDAY(G54,ReviewDays)) | K54: =IF(AND(G54<>"",OR(H54="",H54="Pending"),Today>J54),"Past inspection window – deemed accepted","") | L54: =IF(AND(H54="Returned",I54<>""),WORKDAY(I54,ResubDays),"") | M54: =IF(OR(B54="",F54=""),"",IF(G54<>"",IF(G54<=F54,"On time","Late"),IF(Today>F54,"Overdue",IF(F54-Today<=7,"Due within 7 days","Not yet due")))) -> Not yet due | N54: =IF(OR(M54="Late",M54="Overdue"),IF(G54<>"",G54-F54,Today-F54),"") | O54: =IF(H54="Returned",1,0) -> 0 | Q54: Friday assumed; PWS says weekly only.
A55: 51 | B55: A007 | C55: =IF(B55="","",IFERROR(INDEX(Deliverables!$B$5:$B$48,MATCH(B55,Deliverables!$A$5:$A$48,0)),"ID not found")) -> ACAS Scans | D55: =IF(B55="","",IFERROR(INDEX(Deliverables!$D$5:$D$48,MATCH(B55,Deliverables!$A$5:$A$48,0)),"")) -> 6.1 | E55: ="ACAS scan wk 44" -> ACAS scan wk 44 | F55: =Award+MOD(6-WEEKDAY(Award),7)+301 -> 46451 | J55: =IF(G55="","",WORKDAY(G55,ReviewDays)) | K55: =IF(AND(G55<>"",OR(H55="",H55="Pending"),Today>J55),"Past inspection window – deemed accepted","") | L55: =IF(AND(H55="Returned",I55<>""),WORKDAY(I55,ResubDays),"") | M55: =IF(OR(B55="",F55=""),"",IF(G55<>"",IF(G55<=F55,"On time","Late"),IF(Today>F55,"Overdue",IF(F55-Today<=7,"Due within 7 days","Not yet due")))) -> Not yet due | N55: =IF(OR(M55="Late",M55="Overdue"),IF(G55<>"",G55-F55,Today-F55),"") | O55: =IF(H55="Returned",1,0) -> 0 | Q55: Friday assumed; PWS says weekly only.
A56: 52 | B56: A007 | C56: =IF(B56="","",IFERROR(INDEX(Deliverables!$B$5:$B$48,MATCH(B56,Deliverables!$A$5:$A$48,0)),"ID not found")) -> ACAS Scans | D56: =IF(B56="","",IFERROR(INDEX(Deliverables!$D$5:$D$48,MATCH(B56,Deliverables!$A$5:$A$48,0)),"")) -> 6.1 | E56: ="ACAS scan wk 45" -> ACAS scan wk 45 | F56: =Award+MOD(6-WEEKDAY(Award),7)+308 -> 46458 | J56: =IF(G56="","",WORKDAY(G56,ReviewDays)) | K56: =IF(AND(G56<>"",OR(H56="",H56="Pending"),Today>J56),"Past inspection window – deemed accepted","") | L56: =IF(AND(H56="Returned",I56<>""),WORKDAY(I56,ResubDays),"") | M56: =IF(OR(B56="",F56=""),"",IF(G56<>"",IF(G56<=F56,"On time","Late"),IF(Today>F56,"Overdue",IF(F56-Today<=7,"Due within 7 days","Not yet due")))) -> Not yet due | N56: =IF(OR(M56="Late",M56="Overdue"),IF(G56<>"",G56-F56,Today-F56),"") | O56: =IF(H56="Returned",1,0) -> 0 | Q56: Friday assumed; PWS says weekly only.
A57: 53 | B57: A007 | C57: =IF(B57="","",IFERROR(INDEX(Deliverables!$B$5:$B$48,MATCH(B57,Deliverables!$A$5:$A$48,0)),"ID not found")) -> ACAS Scans | D57: =IF(B57="","",IFERROR(INDEX(Deliverables!$D$5:$D$48,MATCH(B57,Deliverables!$A$5:$A$48,0)),"")) -> 6.1 | E57: ="ACAS scan wk 46" -> ACAS scan wk 46 | F57: =Award+MOD(6-WEEKDAY(Award),7)+315 -> 46465 | J57: =IF(G57="","",WORKDAY(G57,ReviewDays)) | K57: =IF(AND(G57<>"",OR(H57="",H57="Pending"),Today>J57),"Past inspection window – deemed accepted","") | L57: =IF(AND(H57="Returned",I57<>""),WORKDAY(I57,ResubDays),"") | M57: =IF(OR(B57="",F57=""),"",IF(G57<>"",IF(G57<=F57,"On time","Late"),IF(Today>F57,"Overdue",IF(F57-Today<=7,"Due within 7 days","Not yet due")))) -> Not yet due | N57: =IF(OR(M57="Late",M57="Overdue"),IF(G57<>"",G57-F57,Today-F57),"") | O57: =IF(H57="Returned",1,0) -> 0 | Q57: Friday assumed; PWS says weekly only.
A58: 54 | B58: A007 | C58: =IF(B58="","",IFERROR(INDEX(Deliverables!$B$5:$B$48,MATCH(B58,Deliverables!$A$5:$A$48,0)),"ID not found")) -> ACAS Scans | D58: =IF(B58="","",IFERROR(INDEX(Deliverables!$D$5:$D$48,MATCH(B58,Deliverables!$A$5:$A$48,0)),"")) -> 6.1 | E58: ="ACAS scan wk 47" -> ACAS scan wk 47 | F58: =Award+MOD(6-WEEKDAY(Award),7)+322 -> 46472 | J58: =IF(G58="","",WORKDAY(G58,ReviewDays)) | K58: =IF(AND(G58<>"",OR(H58="",H58="Pending"),Today>J58),"Past inspection window – deemed accepted","") | L58: =IF(AND(H58="Returned",I58<>""),WORKDAY(I58,ResubDays),"") | M58: =IF(OR(B58="",F58=""),"",IF(G58<>"",IF(G58<=F58,"On time","Late"),IF(Today>F58,"Overdue",IF(F58-Today<=7,"Due within 7 days","Not yet due")))) -> Not yet due | N58: =IF(OR(M58="Late",M58="Overdue"),IF(G58<>"",G58-F58,Today-F58),"") | O58: =IF(H58="Returned",1,0) -> 0 | Q58: Friday assumed; PWS says weekly only.
A59: 55 | B59: A007 | C59: =IF(B59="","",IFERROR(INDEX(Deliverables!$B$5:$B$48,MATCH(B59,Deliverables!$A$5:$A$48,0)),"ID not found")) -> ACAS Scans | D59: =IF(B59="","",IFERROR(INDEX(Deliverables!$D$5:$D$48,MATCH(B59,Deliverables!$A$5:$A$48,0)),"")) -> 6.1 | E59: ="ACAS scan wk 48" -> ACAS scan wk 48 | F59: =Award+MOD(6-WEEKDAY(Award),7)+329 -> 46479 | J59: =IF(G59="","",WORKDAY(G59,ReviewDays)) | K59: =IF(AND(G59<>"",OR(H59="",H59="Pending"),Today>J59),"Past inspection window – deemed accepted","") | L59: =IF(AND(H59="Returned",I59<>""),WORKDAY(I59,ResubDays),"") | M59: =IF(OR(B59="",F59=""),"",IF(G59<>"",IF(G59<=F59,"On time","Late"),IF(Today>F59,"Overdue",IF(F59-Today<=7,"Due within 7 days","Not yet due")))) -> Not yet due | N59: =IF(OR(M59="Late",M59="Overdue"),IF(G59<>"",G59-F59,Today-F59),"") | O59: =IF(H59="Returned",1,0) -> 0 | Q59: Friday assumed; PWS says weekly only.
A60: 56 | B60: A007 | C60: =IF(B60="","",IFERROR(INDEX(Deliverables!$B$5:$B$48,MATCH(B60,Deliverables!$A$5:$A$48,0)),"ID not found")) -> ACAS Scans | D60: =IF(B60="","",IFERROR(INDEX(Deliverables!$D$5:$D$48,MATCH(B60,Deliverables!$A$5:$A$48,0)),"")) -> 6.1 | E60: ="ACAS scan wk 49" -> ACAS scan wk 49 | F60: =Award+MOD(6-WEEKDAY(Award),7)+336 -> 46486 | J60: =IF(G60="","",WORKDAY(G60,ReviewDays)) | K60: =IF(AND(G60<>"",OR(H60="",H60="Pending"),Today>J60),"Past inspection window – deemed accepted","") | L60: =IF(AND(H60="Returned",I60<>""),WORKDAY(I60,ResubDays),"") | M60: =IF(OR(B60="",F60=""),"",IF(G60<>"",IF(G60<=F60,"On time","Late"),IF(Today>F60,"Overdue",IF(F60-Today<=7,"Due within 7 days","Not yet due")))) -> Not yet due | N60: =IF(OR(M60="Late",M60="Overdue"),IF(G60<>"",G60-F60,Today-F60),"") | O60: =IF(H60="Returned",1,0) -> 0 | Q60: Friday assumed; PWS says weekly only.
A61: 57 | B61: A007 | C61: =IF(B61="","",IFERROR(INDEX(Deliverables!$B$5:$B$48,MATCH(B61,Deliverables!$A$5:$A$48,0)),"ID not found")) -> ACAS Scans | D61: =IF(B61="","",IFERROR(INDEX(Deliverables!$D$5:$D$48,MATCH(B61,Deliverables!$A$5:$A$48,0)),"")) -> 6.1 | E61: ="ACAS scan wk 50" -> ACAS scan wk 50 | F61: =Award+MOD(6-WEEKDAY(Award),7)+343 -> 46493 | J61: =IF(G61="","",WORKDAY(G61,ReviewDays)) | K61: =IF(AND(G61<>"",OR(H61="",H61="Pending"),Today>J61),"Past inspection window – deemed accepted","") | L61: =IF(AND(H61="Returned",I61<>""),WORKDAY(I61,ResubDays),"") | M61: =IF(OR(B61="",F61=""),"",IF(G61<>"",IF(G61<=F61,"On time","Late"),IF(Today>F61,"Overdue",IF(F61-Today<=7,"Due within 7 days","Not yet due")))) -> Not yet due | N61: =IF(OR(M61="Late",M61="Overdue"),IF(G61<>"",G61-F61,Today-F61),"") | O61: =IF(H61="Returned",1,0) -> 0 | Q61: Friday assumed; PWS says weekly only.
A62: 58 | B62: A007 | C62: =IF(B62="","",IFERROR(INDEX(Deliverables!$B$5:$B$48,MATCH(B62,Deliverables!$A$5:$A$48,0)),"ID not found")) -> ACAS Scans | D62: =IF(B62="","",IFERROR(INDEX(Deliverables!$D$5:$D$48,MATCH(B62,Deliverables!$A$5:$A$48,0)),"")) -> 6.1 | E62: ="ACAS scan wk 51" -> ACAS scan wk 51 | F62: =Award+MOD(6-WEEKDAY(Award),7)+350 -> 46500 | J62: =IF(G62="","",WORKDAY(G62,ReviewDays)) | K62: =IF(AND(G62<>"",OR(H62="",H62="Pending"),Today>J62),"Past inspection window – deemed accepted","") | L62: =IF(AND(H62="Returned",I62<>""),WORKDAY(I62,ResubDays),"") | M62: =IF(OR(B62="",F62=""),"",IF(G62<>"",IF(G62<=F62,"On time","Late"),IF(Today>F62,"Overdue",IF(F62-Today<=7,"Due within 7 days","Not yet due")))) -> Not yet due | N62: =IF(OR(M62="Late",M62="Overdue"),IF(G62<>"",G62-F62,Today-F62),"") | O62: =IF(H62="Returned",1,0) -> 0 | Q62: Friday assumed; PWS says weekly only.
A63: 59 | B63: A007 | C63: =IF(B63="","",IFERROR(INDEX(Deliverables!$B$5:$B$48,MATCH(B63,Deliverables!$A$5:$A$48,0)),"ID not found")) -> ACAS Scans | D63: =IF(B63="","",IFERROR(INDEX(Deliverables!$D$5:$D$48,MATCH(B63,Deliverables!$A$5:$A$48,0)),"")) -> 6.1 | E63: ="ACAS scan wk 52" -> ACAS scan wk 52 | F63: =Award+MOD(6-WEEKDAY(Award),7)+357 -> 46507 | J63: =IF(G63="","",WORKDAY(G63,ReviewDays)) | K63: =IF(AND(G63<>"",OR(H63="",H63="Pending"),Today>J63),"Past inspection window – deemed accepted","") | L63: =IF(AND(H63="Returned",I63<>""),WORKDAY(I63,ResubDays),"") | M63: =IF(OR(B63="",F63=""),"",IF(G63<>"",IF(G63<=F63,"On time","Late"),IF(Today>F63,"Overdue",IF(F63-Today<=7,"Due within 7 days","Not yet due")))) -> Not yet due | N63: =IF(OR(M63="Late",M63="Overdue"),IF(G63<>"",G63-F63,Today-F63),"") | O63: =IF(H63="Returned",1,0) -> 0 | Q63: Friday assumed; PWS says weekly only.
A64: 60 | B64: A011 | C64: =IF(B64="","",IFERROR(INDEX(Deliverables!$B$5:$B$48,MATCH(B64,Deliverables!$A$5:$A$48,0)),"ID not found")) -> Incident Response Plan | D64: =IF(B64="","",IFERROR(INDEX(Deliverables!$D$5:$D$48,MATCH(B64,Deliverables!$A$5:$A$48,0)),"")) -> 6.2 | E64: Initial delivery | J64: =IF(G64="","",WORKDAY(G64,ReviewDays)) | K64: =IF(AND(G64<>"",OR(H64="",H64="Pending"),Today>J64),"Past inspection window – deemed accepted","") | L64: =IF(AND(H64="Returned",I64<>""),WORKDAY(I64,ResubDays),"") | M64: =IF(OR(B64="",F64=""),"",IF(G64<>"",IF(G64<=F64,"On time","Late"),IF(Today>F64,"Overdue",IF(F64-Today<=7,"Due within 7 days","Not yet due")))) | N64: =IF(OR(M64="Late",M64="Overdue"),IF(G64<>"",G64-F64,Today-F64),"") | O64: =IF(H64="Returned",1,0) -> 0 | Q64: Due per the IMS (A017): enter the date.
A65: 61 | B65: A012 | C65: =IF(B65="","",IFERROR(INDEX(Deliverables!$B$5:$B$48,MATCH(B65,Deliverables!$A$5:$A$48,0)),"ID not found")) -> Security Monitoring Reports | D65: =IF(B65="","",IFERROR(INDEX(Deliverables!$D$5:$D$48,MATCH(B65,Deliverables!$A$5:$A$48,0)),"")) -> 6.2 | E65: ="Quarter 1 (months 1-3)" -> Quarter 1 (months 1-3) | F65: =WORKDAY(EOMONTH(Award,2),DueOffset) -> 46241 | J65: =IF(G65="","",WORKDAY(G65,ReviewDays)) | K65: =IF(AND(G65<>"",OR(H65="",H65="Pending"),Today>J65),"Past inspection window – deemed accepted","") | L65: =IF(AND(H65="Returned",I65<>""),WORKDAY(I65,ResubDays),"") | M65: =IF(OR(B65="",F65=""),"",IF(G65<>"",IF(G65<=F65,"On time","Late"),IF(Today>F65,"Overdue",IF(F65-Today<=7,"Due within 7 days","Not yet due")))) -> Overdue | N65: =IF(OR(M65="Late",M65="Overdue"),IF(G65<>"",G65-F65,Today-F65),"") -> 65 | O65: =IF(H65="Returned",1,0) -> 0 | Q65: Due date uses the DueOffset assumption.
A66: 62 | B66: A012 | C66: =IF(B66="","",IFERROR(INDEX(Deliverables!$B$5:$B$48,MATCH(B66,Deliverables!$A$5:$A$48,0)),"ID not found")) -> Security Monitoring Reports | D66: =IF(B66="","",IFERROR(INDEX(Deliverables!$D$5:$D$48,MATCH(B66,Deliverables!$A$5:$A$48,0)),"")) -> 6.2 | E66: ="Quarter 2 (months 4-6)" -> Quarter 2 (months 4-6) | F66: =WORKDAY(EOMONTH(Award,5),DueOffset) -> 46332 | J66: =IF(G66="","",WORKDAY(G66,ReviewDays)) | K66: =IF(AND(G66<>"",OR(H66="",H66="Pending"),Today>J66),"Past inspection window – deemed accepted","") | L66: =IF(AND(H66="Returned",I66<>""),WORKDAY(I66,ResubDays),"") | M66: =IF(OR(B66="",F66=""),"",IF(G66<>"",IF(G66<=F66,"On time","Late"),IF(Today>F66,"Overdue",IF(F66-Today<=7,"Due within 7 days","Not yet due")))) -> Not yet due | N66: =IF(OR(M66="Late",M66="Overdue"),IF(G66<>"",G66-F66,Today-F66),"") | O66: =IF(H66="Returned",1,0) -> 0 | Q66: Due date uses the DueOffset assumption.
A67: 63 | B67: A012 | C67: =IF(B67="","",IFERROR(INDEX(Deliverables!$B$5:$B$48,MATCH(B67,Deliverables!$A$5:$A$48,0)),"ID not found")) -> Security Monitoring Reports | D67: =IF(B67="","",IFERROR(INDEX(Deliverables!$D$5:$D$48,MATCH(B67,Deliverables!$A$5:$A$48,0)),"")) -> 6.2 | E67: ="Quarter 3 (months 7-9)" -> Quarter 3 (months 7-9) | F67: =WORKDAY(EOMONTH(Award,8),DueOffset) -> 46423 | J67: =IF(G67="","",WORKDAY(G67,ReviewDays)) | K67: =IF(AND(G67<>"",OR(H67="",H67="Pending"),Today>J67),"Past inspection window – deemed accepted","") | L67: =IF(AND(H67="Returned",I67<>""),WORKDAY(I67,ResubDays),"") | M67: =IF(OR(B67="",F67=""),"",IF(G67<>"",IF(G67<=F67,"On time","Late"),IF(Today>F67,"Overdue",IF(F67-Today<=7,"Due within 7 days","Not yet due")))) -> Not yet due | N67: =IF(OR(M67="Late",M67="Overdue"),IF(G67<>"",G67-F67,Today-F67),"") | O67: =IF(H67="Returned",1,0) -> 0 | Q67: Due date uses the DueOffset assumption.
A68: 64 | B68: A012 | C68: =IF(B68="","",IFERROR(INDEX(Deliverables!$B$5:$B$48,MATCH(B68,Deliverables!$A$5:$A$48,0)),"ID not found")) -> Security Monitoring Reports | D68: =IF(B68="","",IFERROR(INDEX(Deliverables!$D$5:$D$48,MATCH(B68,Deliverables!$A$5:$A$48,0)),"")) -> 6.2 | E68: ="Quarter 4 (months 10-12)" -> Quarter 4 (months 10-12) | F68: =WORKDAY(EOMONTH(Award,11),DueOffset) -> 46514 | J68: =IF(G68="","",WORKDAY(G68,ReviewDays)) | K68: =IF(AND(G68<>"",OR(H68="",H68="Pending"),Today>J68),"Past inspection window – deemed accepted","") | L68: =IF(AND(H68="Returned",I68<>""),WORKDAY(I68,ResubDays),"") | M68: =IF(OR(B68="",F68=""),"",IF(G68<>"",IF(G68<=F68,"On time","Late"),IF(Today>F68,"Overdue",IF(F68-Today<=7,"Due within 7 days","Not yet due")))) -> Not yet due | N68: =IF(OR(M68="Late",M68="Overdue"),IF(G68<>"",G68-F68,Today-F68),"") | O68: =IF(H68="Returned",1,0) -> 0 | Q68: Due date uses the DueOffset assumption.
A69: 65 | B69: A013 | C69: =IF(B69="","",IFERROR(INDEX(Deliverables!$B$5:$B$48,MATCH(B69,Deliverables!$A$5:$A$48,0)),"ID not found")) -> Vulnerability Scan Reports | D69: =IF(B69="","",IFERROR(INDEX(Deliverables!$D$5:$D$48,MATCH(B69,Deliverables!$A$5:$A$48,0)),"")) -> 6.2 | E69: ="Quarter 1 (months 1-3)" -> Quarter 1 (months 1-3) | F69: =WORKDAY(EOMONTH(Award,2),DueOffset) -> 46241 | J69: =IF(G69="","",WORKDAY(G69,ReviewDays)) | K69: =IF(AND(G69<>"",OR(H69="",H69="Pending"),Today>J69),"Past inspection window – deemed accepted","") | L69: =IF(AND(H69="Returned",I69<>""),WORKDAY(I69,ResubDays),"") | M69: =IF(OR(B69="",F69=""),"",IF(G69<>"",IF(G69<=F69,"On time","Late"),IF(Today>F69,"Overdue",IF(F69-Today<=7,"Due within 7 days","Not yet due")))) -> Overdue | N69: =IF(OR(M69="Late",M69="Overdue"),IF(G69<>"",G69-F69,Today-F69),"") -> 65 | O69: =IF(H69="Returned",1,0) -> 0 | Q69: Due date uses the DueOffset assumption.
A70: 66 | B70: A013 | C70: =IF(B70="","",IFERROR(INDEX(Deliverables!$B$5:$B$48,MATCH(B70,Deliverables!$A$5:$A$48,0)),"ID not found")) -> Vulnerability Scan Reports | D70: =IF(B70="","",IFERROR(INDEX(Deliverables!$D$5:$D$48,MATCH(B70,Deliverables!$A$5:$A$48,0)),"")) -> 6.2 | E70: ="Quarter 2 (months 4-6)" -> Quarter 2 (months 4-6) | F70: =WORKDAY(EOMONTH(Award,5),DueOffset) -> 46332 | J70: =IF(G70="","",WORKDAY(G70,ReviewDays)) | K70: =IF(AND(G70<>"",OR(H70="",H70="Pending"),Today>J70),"Past inspection window – deemed accepted","") | L70: =IF(AND(H70="Returned",I70<>""),WORKDAY(I70,ResubDays),"") | M70: =IF(OR(B70="",F70=""),"",IF(G70<>"",IF(G70<=F70,"On time","Late"),IF(Today>F70,"Overdue",IF(F70-Today<=7,"Due within 7 days","Not yet due")))) -> Not yet due | N70: =IF(OR(M70="Late",M70="Overdue"),IF(G70<>"",G70-F70,Today-F70),"") | O70: =IF(H70="Returned",1,0) -> 0 | Q70: Due date uses the DueOffset assumption.
A71: 67 | B71: A013 | C71: =IF(B71="","",IFERROR(INDEX(Deliverables!$B$5:$B$48,MATCH(B71,Deliverables!$A$5:$A$48,0)),"ID not found")) -> Vulnerability Scan Reports | D71: =IF(B71="","",IFERROR(INDEX(Deliverables!$D$5:$D$48,MATCH(B71,Deliverables!$A$5:$A$48,0)),"")) -> 6.2 | E71: ="Quarter 3 (months 7-9)" -> Quarter 3 (months 7-9) | F71: =WORKDAY(EOMONTH(Award,8),DueOffset) -> 46423 | J71: =IF(G71="","",WORKDAY(G71,ReviewDays)) | K71: =IF(AND(G71<>"",OR(H71="",H71="Pending"),Today>J71),"Past inspection window – deemed accepted","") | L71: =IF(AND(H71="Returned",I71<>""),WORKDAY(I71,ResubDays),"") | M71: =IF(OR(B71="",F71=""),"",IF(G71<>"",IF(G71<=F71,"On time","Late"),IF(Today>F71,"Overdue",IF(F71-Today<=7,"Due within 7 days","Not yet due")))) -> Not yet due | N71: =IF(OR(M71="Late",M71="Overdue"),IF(G71<>"",G71-F71,Today-F71),"") | O71: =IF(H71="Returned",1,0) -> 0 | Q71: Due date uses the DueOffset assumption.
A72: 68 | B72: A013 | C72: =IF(B72="","",IFERROR(INDEX(Deliverables!$B$5:$B$48,MATCH(B72,Deliverables!$A$5:$A$48,0)),"ID not found")) -> Vulnerability Scan Reports | D72: =IF(B72="","",IFERROR(INDEX(Deliverables!$D$5:$D$48,MATCH(B72,Deliverables!$A$5:$A$48,0)),"")) -> 6.2 | E72: ="Quarter 4 (months 10-12)" -> Quarter 4 (months 10-12) | F72: =WORKDAY(EOMONTH(Award,11),DueOffset) -> 46514 | J72: =IF(G72="","",WORKDAY(G72,ReviewDays)) | K72: =IF(AND(G72<>"",OR(H72="",H72="Pending"),Today>J72),"Past inspection window – deemed accepted","") | L72: =IF(AND(H72="Returned",I72<>""),WORKDAY(I72,ResubDays),"") | M72: =IF(OR(B72="",F72=""),"",IF(G72<>"",IF(G72<=F72,"On time","Late"),IF(Today>F72,"Overdue",IF(F72-Today<=7,"Due within 7 days","Not yet due")))) -> Not yet due | N72: =IF(OR(M72="Late",M72="Overdue"),IF(G72<>"",G72-F72,Today-F72),"") | O72: =IF(H72="Returned",1,0) -> 0 | Q72: Due date uses the DueOffset assumption.
A73: 69 | B73: A014 | C73: =IF(B73="","",IFERROR(INDEX(Deliverables!$B$5:$B$48,MATCH(B73,Deliverables!$A$5:$A$48,0)),"ID not found")) -> Compliance Documentation | D73: =IF(B73="","",IFERROR(INDEX(Deliverables!$D$5:$D$48,MATCH(B73,Deliverables!$A$5:$A$48,0)),"")) -> 6.2 | E73: 90 days after award | F73: =Award+90 -> 46236 | J73: =IF(G73="","",WORKDAY(G73,ReviewDays)) | K73: =IF(AND(G73<>"",OR(H73="",H73="Pending"),Today>J73),"Past inspection window – deemed accepted","") | L73: =IF(AND(H73="Returned",I73<>""),WORKDAY(I73,ResubDays),"") | M73: =IF(OR(B73="",F73=""),"",IF(G73<>"",IF(G73<=F73,"On time","Late"),IF(Today>F73,"Overdue",IF(F73-Today<=7,"Due within 7 days","Not yet due")))) -> Overdue | N73: =IF(OR(M73="Late",M73="Overdue"),IF(G73<>"",G73-F73,Today-F73),"") -> 70 | O73: =IF(H73="Returned",1,0) -> 0
A74: 70 | B74: A015 | C74: =IF(B74="","",IFERROR(INDEX(Deliverables!$B$5:$B$48,MATCH(B74,Deliverables!$A$5:$A$48,0)),"ID not found")) -> Security Assessment Report | D74: =IF(B74="","",IFERROR(INDEX(Deliverables!$D$5:$D$48,MATCH(B74,Deliverables!$A$5:$A$48,0)),"")) -> 6.2 | E74: Initial delivery | J74: =IF(G74="","",WORKDAY(G74,ReviewDays)) | K74: =IF(AND(G74<>"",OR(H74="",H74="Pending"),Today>J74),"Past inspection window – deemed accepted","") | L74: =IF(AND(H74="Returned",I74<>""),WORKDAY(I74,ResubDays),"") | M74: =IF(OR(B74="",F74=""),"",IF(G74<>"",IF(G74<=F74,"On time","Late"),IF(Today>F74,"Overdue",IF(F74-Today<=7,"Due within 7 days","Not yet due")))) | N74: =IF(OR(M74="Late",M74="Overdue"),IF(G74<>"",G74-F74,Today-F74),"") | O74: =IF(H74="Returned",1,0) -> 0 | Q74: In concert with accreditation.
A75: 71 | B75: A017 | C75: =IF(B75="","",IFERROR(INDEX(Deliverables!$B$5:$B$48,MATCH(B75,Deliverables!$A$5:$A$48,0)),"ID not found")) -> Integrated Master Schedule | D75: =IF(B75="","",IFERROR(INDEX(Deliverables!$D$5:$D$48,MATCH(B75,Deliverables!$A$5:$A$48,0)),"")) -> 6.3 | E75: ="Month 1: "&TEXT(EDATE(Award,0),"mmm yyyy") -> Month 1: May 2026 | F75: =WORKDAY(EOMONTH(Award,0),DueOffset) -> 46178 | J75: =IF(G75="","",WORKDAY(G75,ReviewDays)) | K75: =IF(AND(G75<>"",OR(H75="",H75="Pending"),Today>J75),"Past inspection window – deemed accepted","") | L75: =IF(AND(H75="Returned",I75<>""),WORKDAY(I75,ResubDays),"") | M75: =IF(OR(B75="",F75=""),"",IF(G75<>"",IF(G75<=F75,"On time","Late"),IF(Today>F75,"Overdue",IF(F75-Today<=7,"Due within 7 days","Not yet due")))) -> Overdue | N75: =IF(OR(M75="Late",M75="Overdue"),IF(G75<>"",G75-F75,Today-F75),"") -> 128 | O75: =IF(H75="Returned",1,0) -> 0 | Q75: Due date uses the DueOffset assumption.
A76: 72 | B76: A017 | C76: =IF(B76="","",IFERROR(INDEX(Deliverables!$B$5:$B$48,MATCH(B76,Deliverables!$A$5:$A$48,0)),"ID not found")) -> Integrated Master Schedule | D76: =IF(B76="","",IFERROR(INDEX(Deliverables!$D$5:$D$48,MATCH(B76,Deliverables!$A$5:$A$48,0)),"")) -> 6.3 | E76: ="Month 2: "&TEXT(EDATE(Award,1),"mmm yyyy") -> Month 2: Jun 2026 | F76: =WORKDAY(EOMONTH(Award,1),DueOffset) -> 46210 | J76: =IF(G76="","",WORKDAY(G76,ReviewDays)) | K76: =IF(AND(G76<>"",OR(H76="",H76="Pending"),Today>J76),"Past inspection window – deemed accepted","") | L76: =IF(AND(H76="Returned",I76<>""),WORKDAY(I76,ResubDays),"") | M76: =IF(OR(B76="",F76=""),"",IF(G76<>"",IF(G76<=F76,"On time","Late"),IF(Today>F76,"Overdue",IF(F76-Today<=7,"Due within 7 days","Not yet due")))) -> Overdue | N76: =IF(OR(M76="Late",M76="Overdue"),IF(G76<>"",G76-F76,Today-F76),"") -> 96 | O76: =IF(H76="Returned",1,0) -> 0 | Q76: Due date uses the DueOffset assumption.
A77: 73 | B77: A017 | C77: =IF(B77="","",IFERROR(INDEX(Deliverables!$B$5:$B$48,MATCH(B77,Deliverables!$A$5:$A$48,0)),"ID not found")) -> Integrated Master Schedule | D77: =IF(B77="","",IFERROR(INDEX(Deliverables!$D$5:$D$48,MATCH(B77,Deliverables!$A$5:$A$48,0)),"")) -> 6.3 | E77: ="Month 3: "&TEXT(EDATE(Award,2),"mmm yyyy") -> Month 3: Jul 2026 | F77: =WORKDAY(EOMONTH(Award,2),DueOffset) -> 46241 | J77: =IF(G77="","",WORKDAY(G77,ReviewDays)) | K77: =IF(AND(G77<>"",OR(H77="",H77="Pending"),Today>J77),"Past inspection window – deemed accepted","") | L77: =IF(AND(H77="Returned",I77<>""),WORKDAY(I77,ResubDays),"") | M77: =IF(OR(B77="",F77=""),"",IF(G77<>"",IF(G77<=F77,"On time","Late"),IF(Today>F77,"Overdue",IF(F77-Today<=7,"Due within 7 days","Not yet due")))) -> Overdue | N77: =IF(OR(M77="Late",M77="Overdue"),IF(G77<>"",G77-F77,Today-F77),"") -> 65 | O77: =IF(H77="Returned",1,0) -> 0 | Q77: Due date uses the DueOffset assumption.
A78: 74 | B78: A017 | C78: =IF(B78="","",IFERROR(INDEX(Deliverables!$B$5:$B$48,MATCH(B78,Deliverables!$A$5:$A$48,0)),"ID not found")) -> Integrated Master Schedule | D78: =IF(B78="","",IFERROR(INDEX(Deliverables!$D$5:$D$48,MATCH(B78,Deliverables!$A$5:$A$48,0)),"")) -> 6.3 | E78: ="Month 4: "&TEXT(EDATE(Award,3),"mmm yyyy") -> Month 4: Aug 2026 | F78: =WORKDAY(EOMONTH(Award,3),DueOffset) -> 46272 | J78: =IF(G78="","",WORKDAY(G78,ReviewDays)) | K78: =IF(AND(G78<>"",OR(H78="",H78="Pending"),Today>J78),"Past inspection window – deemed accepted","") | L78: =IF(AND(H78="Returned",I78<>""),WORKDAY(I78,ResubDays),"") | M78: =IF(OR(B78="",F78=""),"",IF(G78<>"",IF(G78<=F78,"On time","Late"),IF(Today>F78,"Overdue",IF(F78-Today<=7,"Due within 7 days","Not yet due")))) -> Overdue | N78: =IF(OR(M78="Late",M78="Overdue"),IF(G78<>"",G78-F78,Today-F78),"") -> 34 | O78: =IF(H78="Returned",1,0) -> 0 | Q78: Due date uses the DueOffset assumption.
A79: 75 | B79: A017 | C79: =IF(B79="","",IFERROR(INDEX(Deliverables!$B$5:$B$48,MATCH(B79,Deliverables!$A$5:$A$48,0)),"ID not found")) -> Integrated Master Schedule | D79: =IF(B79="","",IFERROR(INDEX(Deliverables!$D$5:$D$48,MATCH(B79,Deliverables!$A$5:$A$48,0)),"")) -> 6.3 | E79: ="Month 5: "&TEXT(EDATE(Award,4),"mmm yyyy") -> Month 5: Sep 2026 | F79: =WORKDAY(EOMONTH(Award,4),DueOffset) -> 46302 | J79: =IF(G79="","",WORKDAY(G79,ReviewDays)) | K79: =IF(AND(G79<>"",OR(H79="",H79="Pending"),Today>J79),"Past inspection window – deemed accepted","") | L79: =IF(AND(H79="Returned",I79<>""),WORKDAY(I79,ResubDays),"") | M79: =IF(OR(B79="",F79=""),"",IF(G79<>"",IF(G79<=F79,"On time","Late"),IF(Today>F79,"Overdue",IF(F79-Today<=7,"Due within 7 days","Not yet due")))) -> Overdue | N79: =IF(OR(M79="Late",M79="Overdue"),IF(G79<>"",G79-F79,Today-F79),"") -> 4 | O79: =IF(H79="Returned",1,0) -> 0 | Q79: Due date uses the DueOffset assumption.
A80: 76 | B80: A017 | C80: =IF(B80="","",IFERROR(INDEX(Deliverables!$B$5:$B$48,MATCH(B80,Deliverables!$A$5:$A$48,0)),"ID not found")) -> Integrated Master Schedule | D80: =IF(B80="","",IFERROR(INDEX(Deliverables!$D$5:$D$48,MATCH(B80,Deliverables!$A$5:$A$48,0)),"")) -> 6.3 | E80: ="Month 6: "&TEXT(EDATE(Award,5),"mmm yyyy") -> Month 6: Oct 2026 | F80: =WORKDAY(EOMONTH(Award,5),DueOffset) -> 46332 | J80: =IF(G80="","",WORKDAY(G80,ReviewDays)) | K80: =IF(AND(G80<>"",OR(H80="",H80="Pending"),Today>J80),"Past inspection window – deemed accepted","") | L80: =IF(AND(H80="Returned",I80<>""),WORKDAY(I80,ResubDays),"") | M80: =IF(OR(B80="",F80=""),"",IF(G80<>"",IF(G80<=F80,"On time","Late"),IF(Today>F80,"Overdue",IF(F80-Today<=7,"Due within 7 days","Not yet due")))) -> Not yet due | N80: =IF(OR(M80="Late",M80="Overdue"),IF(G80<>"",G80-F80,Today-F80),"") | O80: =IF(H80="Returned",1,0) -> 0 | Q80: Due date uses the DueOffset assumption.
A81: 77 | B81: A017 | C81: =IF(B81="","",IFERROR(INDEX(Deliverables!$B$5:$B$48,MATCH(B81,Deliverables!$A$5:$A$48,0)),"ID not found")) -> Integrated Master Schedule | D81: =IF(B81="","",IFERROR(INDEX(Deliverables!$D$5:$D$48,MATCH(B81,Deliverables!$A$5:$A$48,0)),"")) -> 6.3 | E81: ="Month 7: "&TEXT(EDATE(Award,6),"mmm yyyy") -> Month 7: Nov 2026 | F81: =WORKDAY(EOMONTH(Award,6),DueOffset) -> 46363 | J81: =IF(G81="","",WORKDAY(G81,ReviewDays)) | K81: =IF(AND(G81<>"",OR(H81="",H81="Pending"),Today>J81),"Past inspection window – deemed accepted","") | L81: =IF(AND(H81="Returned",I81<>""),WORKDAY(I81,ResubDays),"") | M81: =IF(OR(B81="",F81=""),"",IF(G81<>"",IF(G81<=F81,"On time","Late"),IF(Today>F81,"Overdue",IF(F81-Today<=7,"Due within 7 days","Not yet due")))) -> Not yet due | N81: =IF(OR(M81="Late",M81="Overdue"),IF(G81<>"",G81-F81,Today-F81),"") | O81: =IF(H81="Returned",1,0) -> 0 | Q81: Due date uses the DueOffset assumption.
A82: 78 | B82: A017 | C82: =IF(B82="","",IFERROR(INDEX(Deliverables!$B$5:$B$48,MATCH(B82,Deliverables!$A$5:$A$48,0)),"ID not found")) -> Integrated Master Schedule | D82: =IF(B82="","",IFERROR(INDEX(Deliverables!$D$5:$D$48,MATCH(B82,Deliverables!$A$5:$A$48,0)),"")) -> 6.3 | E82: ="Month 8: "&TEXT(EDATE(Award,7),"mmm yyyy") -> Month 8: Dec 2026 | F82: =WORKDAY(EOMONTH(Award,7),DueOffset) -> 46394 | J82: =IF(G82="","",WORKDAY(G82,ReviewDays)) | K82: =IF(AND(G82<>"",OR(H82="",H82="Pending"),Today>J82),"Past inspection window – deemed accepted","") | L82: =IF(AND(H82="Returned",I82<>""),WORKDAY(I82,ResubDays),"") | M82: =IF(OR(B82="",F82=""),"",IF(G82<>"",IF(G82<=F82,"On time","Late"),IF(Today>F82,"Overdue",IF(F82-Today<=7,"Due within 7 days","Not yet due")))) -> Not yet due | N82: =IF(OR(M82="Late",M82="Overdue"),IF(G82<>"",G82-F82,Today-F82),"") | O82: =IF(H82="Returned",1,0) -> 0 | Q82: Due date uses the DueOffset assumption.
A83: 79 | B83: A017 | C83: =IF(B83="","",IFERROR(INDEX(Deliverables!$B$5:$B$48,MATCH(B83,Deliverables!$A$5:$A$48,0)),"ID not found")) -> Integrated Master Schedule | D83: =IF(B83="","",IFERROR(INDEX(Deliverables!$D$5:$D$48,MATCH(B83,Deliverables!$A$5:$A$48,0)),"")) -> 6.3 | E83: ="Month 9: "&TEXT(EDATE(Award,8),"mmm yyyy") -> Month 9: Jan 2027 | F83: =WORKDAY(EOMONTH(Award,8),DueOffset) -> 46423 | J83: =IF(G83="","",WORKDAY(G83,ReviewDays)) | K83: =IF(AND(G83<>"",OR(H83="",H83="Pending"),Today>J83),"Past inspection window – deemed accepted","") | L83: =IF(AND(H83="Returned",I83<>""),WORKDAY(I83,ResubDays),"") | M83: =IF(OR(B83="",F83=""),"",IF(G83<>"",IF(G83<=F83,"On time","Late"),IF(Today>F83,"Overdue",IF(F83-Today<=7,"Due within 7 days","Not yet due")))) -> Not yet due | N83: =IF(OR(M83="Late",M83="Overdue"),IF(G83<>"",G83-F83,Today-F83),"") | O83: =IF(H83="Returned",1,0) -> 0 | Q83: Due date uses the DueOffset assumption.
A84: 80 | B84: A017 | C84: =IF(B84="","",IFERROR(INDEX(Deliverables!$B$5:$B$48,MATCH(B84,Deliverables!$A$5:$A$48,0)),"ID not found")) -> Integrated Master Schedule | D84: =IF(B84="","",IFERROR(INDEX(Deliverables!$D$5:$D$48,MATCH(B84,Deliverables!$A$5:$A$48,0)),"")) -> 6.3 | E84: ="Month 10: "&TEXT(EDATE(Award,9),"mmm yyyy") -> Month 10: Feb 2027 | F84: =WORKDAY(EOMONTH(Award,9),DueOffset) -> 46451 | J84: =IF(G84="","",WORKDAY(G84,ReviewDays)) | K84: =IF(AND(G84<>"",OR(H84="",H84="Pending"),Today>J84),"Past inspection window – deemed accepted","") | L84: =IF(AND(H84="Returned",I84<>""),WORKDAY(I84,ResubDays),"") | M84: =IF(OR(B84="",F84=""),"",IF(G84<>"",IF(G84<=F84,"On time","Late"),IF(Today>F84,"Overdue",IF(F84-Today<=7,"Due within 7 days","Not yet due")))) -> Not yet due | N84: =IF(OR(M84="Late",M84="Overdue"),IF(G84<>"",G84-F84,Today-F84),"") | O84: =IF(H84="Returned",1,0) -> 0 | Q84: Due date uses the DueOffset assumption.
A85: 81 | B85: A017 | C85: =IF(B85="","",IFERROR(INDEX(Deliverables!$B$5:$B$48,MATCH(B85,Deliverables!$A$5:$A$48,0)),"ID not found")) -> Integrated Master Schedule | D85: =IF(B85="","",IFERROR(INDEX(Deliverables!$D$5:$D$48,MATCH(B85,Deliverables!$A$5:$A$48,0)),"")) -> 6.3 | E85: ="Month 11: "&TEXT(EDATE(Award,10),"mmm yyyy") -> Month 11: Mar 2027 | F85: =WORKDAY(EOMONTH(Award,10),DueOffset) -> 46484 | J85: =IF(G85="","",WORKDAY(G85,ReviewDays)) | K85: =IF(AND(G85<>"",OR(H85="",H85="Pending"),Today>J85),"Past inspection window – deemed accepted","") | L85: =IF(AND(H85="Returned",I85<>""),WORKDAY(I85,ResubDays),"") | M85: =IF(OR(B85="",F85=""),"",IF(G85<>"",IF(G85<=F85,"On time","Late"),IF(Today>F85,"Overdue",IF(F85-Today<=7,"Due within 7 days","Not yet due")))) -> Not yet due | N85: =IF(OR(M85="Late",M85="Overdue"),IF(G85<>"",G85-F85,Today-F85),"") | O85: =IF(H85="Returned",1,0) -> 0 | Q85: Due date uses the DueOffset assumption.
A86: 82 | B86: A017 | C86: =IF(B86="","",IFERROR(INDEX(Deliverables!$B$5:$B$48,MATCH(B86,Deliverables!$A$5:$A$48,0)),"ID not found")) -> Integrated Master Schedule | D86: =IF(B86="","",IFERROR(INDEX(Deliverables!$D$5:$D$48,MATCH(B86,Deliverables!$A$5:$A$48,0)),"")) -> 6.3 | E86: ="Month 12: "&TEXT(EDATE(Award,11),"mmm yyyy") -> Month 12: Apr 2027 | F86: =WORKDAY(EOMONTH(Award,11),DueOffset) -> 46514 | J86: =IF(G86="","",WORKDAY(G86,ReviewDays)) | K86: =IF(AND(G86<>"",OR(H86="",H86="Pending"),Today>J86),"Past inspection window – deemed accepted","") | L86: =IF(AND(H86="Returned",I86<>""),WORKDAY(I86,ResubDays),"") | M86: =IF(OR(B86="",F86=""),"",IF(G86<>"",IF(G86<=F86,"On time","Late"),IF(Today>F86,"Overdue",IF(F86-Today<=7,"Due within 7 days","Not yet due")))) -> Not yet due | N86: =IF(OR(M86="Late",M86="Overdue"),IF(G86<>"",G86-F86,Today-F86),"") | O86: =IF(H86="Returned",1,0) -> 0 | Q86: Due date uses the DueOffset assumption.
A87: 83 | B87: A018 | C87: =IF(B87="","",IFERROR(INDEX(Deliverables!$B$5:$B$48,MATCH(B87,Deliverables!$A$5:$A$48,0)),"ID not found")) -> Monthly Progress Report (MPR) (including Invoice Data, ODC Data, Travel Data) | D87: =IF(B87="","",IFERROR(INDEX(Deliverables!$D$5:$D$48,MATCH(B87,Deliverables!$A$5:$A$48,0)),"")) -> 6.3 | E87: ="Month 1: "&TEXT(EDATE(Award,0),"mmm yyyy") -> Month 1: May 2026 | F87: =WORKDAY(EOMONTH(Award,0),DueOffset) -> 46178 | J87: =IF(G87="","",WORKDAY(G87,ReviewDays)) | K87: =IF(AND(G87<>"",OR(H87="",H87="Pending"),Today>J87),"Past inspection window – deemed accepted","") | L87: =IF(AND(H87="Returned",I87<>""),WORKDAY(I87,ResubDays),"") | M87: =IF(OR(B87="",F87=""),"",IF(G87<>"",IF(G87<=F87,"On time","Late"),IF(Today>F87,"Overdue",IF(F87-Today<=7,"Due within 7 days","Not yet due")))) -> Overdue | N87: =IF(OR(M87="Late",M87="Overdue"),IF(G87<>"",G87-F87,Today-F87),"") -> 128 | O87: =IF(H87="Returned",1,0) -> 0 | Q87: Due date uses the DueOffset assumption.
A88: 84 | B88: A018 | C88: =IF(B88="","",IFERROR(INDEX(Deliverables!$B$5:$B$48,MATCH(B88,Deliverables!$A$5:$A$48,0)),"ID not found")) -> Monthly Progress Report (MPR) (including Invoice Data, ODC Data, Travel Data) | D88: =IF(B88="","",IFERROR(INDEX(Deliverables!$D$5:$D$48,MATCH(B88,Deliverables!$A$5:$A$48,0)),"")) -> 6.3 | E88: ="Month 2: "&TEXT(EDATE(Award,1),"mmm yyyy") -> Month 2: Jun 2026 | F88: =WORKDAY(EOMONTH(Award,1),DueOffset) -> 46210 | J88: =IF(G88="","",WORKDAY(G88,ReviewDays)) | K88: =IF(AND(G88<>"",OR(H88="",H88="Pending"),Today>J88),"Past inspection window – deemed accepted","") | L88: =IF(AND(H88="Returned",I88<>""),WORKDAY(I88,ResubDays),"") | M88: =IF(OR(B88="",F88=""),"",IF(G88<>"",IF(G88<=F88,"On time","Late"),IF(Today>F88,"Overdue",IF(F88-Today<=7,"Due within 7 days","Not yet due")))) -> Overdue | N88: =IF(OR(M88="Late",M88="Overdue"),IF(G88<>"",G88-F88,Today-F88),"") -> 96 | O88: =IF(H88="Returned",1,0) -> 0 | Q88: Due date uses the DueOffset assumption.
A89: 85 | B89: A018 | C89: =IF(B89="","",IFERROR(INDEX(Deliverables!$B$5:$B$48,MATCH(B89,Deliverables!$A$5:$A$48,0)),"ID not found")) -> Monthly Progress Report (MPR) (including Invoice Data, ODC Data, Travel Data) | D89: =IF(B89="","",IFERROR(INDEX(Deliverables!$D$5:$D$48,MATCH(B89,Deliverables!$A$5:$A$48,0)),"")) -> 6.3 | E89: ="Month 3: "&TEXT(EDATE(Award,2),"mmm yyyy") -> Month 3: Jul 2026 | F89: =WORKDAY(EOMONTH(Award,2),DueOffset) -> 46241 | J89: =IF(G89="","",WORKDAY(G89,ReviewDays)) | K89: =IF(AND(G89<>"",OR(H89="",H89="Pending"),Today>J89),"Past inspection window – deemed accepted","") | L89: =IF(AND(H89="Returned",I89<>""),WORKDAY(I89,ResubDays),"") | M89: =IF(OR(B89="",F89=""),"",IF(G89<>"",IF(G89<=F89,"On time","Late"),IF(Today>F89,"Overdue",IF(F89-Today<=7,"Due within 7 days","Not yet due")))) -> Overdue | N89: =IF(OR(M89="Late",M89="Overdue"),IF(G89<>"",G89-F89,Today-F89),"") -> 65 | O89: =IF(H89="Returned",1,0) -> 0 | Q89: Due date uses the DueOffset assumption.
A90: 86 | B90: A018 | C90: =IF(B90="","",IFERROR(INDEX(Deliverables!$B$5:$B$48,MATCH(B90,Deliverables!$A$5:$A$48,0)),"ID not found")) -> Monthly Progress Report (MPR) (including Invoice Data, ODC Data, Travel Data) | D90: =IF(B90="","",IFERROR(INDEX(Deliverables!$D$5:$D$48,MATCH(B90,Deliverables!$A$5:$A$48,0)),"")) -> 6.3 | E90: ="Month 4: "&TEXT(EDATE(Award,3),"mmm yyyy") -> Month 4: Aug 2026 | F90: =WORKDAY(EOMONTH(Award,3),DueOffset) -> 46272 | J90: =IF(G90="","",WORKDAY(G90,ReviewDays)) | K90: =IF(AND(G90<>"",OR(H90="",H90="Pending"),Today>J90),"Past inspection window – deemed accepted","") | L90: =IF(AND(H90="Returned",I90<>""),WORKDAY(I90,ResubDays),"") | M90: =IF(OR(B90="",F90=""),"",IF(G90<>"",IF(G90<=F90,"On time","Late"),IF(Today>F90,"Overdue",IF(F90-Today<=7,"Due within 7 days","Not yet due")))) -> Overdue | N90: =IF(OR(M90="Late",M90="Overdue"),IF(G90<>"",G90-F90,Today-F90),"") -> 34 | O90: =IF(H90="Returned",1,0) -> 0 | Q90: Due date uses the DueOffset assumption.
A91: 87 | B91: A018 | C91: =IF(B91="","",IFERROR(INDEX(Deliverables!$B$5:$B$48,MATCH(B91,Deliverables!$A$5:$A$48,0)),"ID not found")) -> Monthly Progress Report (MPR) (including Invoice Data, ODC Data, Travel Data) | D91: =IF(B91="","",IFERROR(INDEX(Deliverables!$D$5:$D$48,MATCH(B91,Deliverables!$A$5:$A$48,0)),"")) -> 6.3 | E91: ="Month 5: "&TEXT(EDATE(Award,4),"mmm yyyy") -> Month 5: Sep 2026 | F91: =WORKDAY(EOMONTH(Award,4),DueOffset) -> 46302 | J91: =IF(G91="","",WORKDAY(G91,ReviewDays)) | K91: =IF(AND(G91<>"",OR(H91="",H91="Pending"),Today>J91),"Past inspection window – deemed accepted","") | L91: =IF(AND(H91="Returned",I91<>""),WORKDAY(I91,ResubDays),"") | M91: =IF(OR(B91="",F91=""),"",IF(G91<>"",IF(G91<=F91,"On time","Late"),IF(Today>F91,"Overdue",IF(F91-Today<=7,"Due within 7 days","Not yet due")))) -> Overdue | N91: =IF(OR(M91="Late",M91="Overdue"),IF(G91<>"",G91-F91,Today-F91),"") -> 4 | O91: =IF(H91="Returned",1,0) -> 0 | Q91: Due date uses the DueOffset assumption.
A92: 88 | B92: A018 | C92: =IF(B92="","",IFERROR(INDEX(Deliverables!$B$5:$B$48,MATCH(B92,Deliverables!$A$5:$A$48,0)),"ID not found")) -> Monthly Progress Report (MPR) (including Invoice Data, ODC Data, Travel Data) | D92: =IF(B92="","",IFERROR(INDEX(Deliverables!$D$5:$D$48,MATCH(B92,Deliverables!$A$5:$A$48,0)),"")) -> 6.3 | E92: ="Month 6: "&TEXT(EDATE(Award,5),"mmm yyyy") -> Month 6: Oct 2026 | F92: =WORKDAY(EOMONTH(Award,5),DueOffset) -> 46332 | J92: =IF(G92="","",WORKDAY(G92,ReviewDays)) | K92: =IF(AND(G92<>"",OR(H92="",H92="Pending"),Today>J92),"Past inspection window – deemed accepted","") | L92: =IF(AND(H92="Returned",I92<>""),WORKDAY(I92,ResubDays),"") | M92: =IF(OR(B92="",F92=""),"",IF(G92<>"",IF(G92<=F92,"On time","Late"),IF(Today>F92,"Overdue",IF(F92-Today<=7,"Due within 7 days","Not yet due")))) -> Not yet due | N92: =IF(OR(M92="Late",M92="Overdue"),IF(G92<>"",G92-F92,Today-F92),"") | O92: =IF(H92="Returned",1,0) -> 0 | Q92: Due date uses the DueOffset assumption.
A93: 89 | B93: A018 | C93: =IF(B93="","",IFERROR(INDEX(Deliverables!$B$5:$B$48,MATCH(B93,Deliverables!$A$5:$A$48,0)),"ID not found")) -> Monthly Progress Report (MPR) (including Invoice Data, ODC Data, Travel Data) | D93: =IF(B93="","",IFERROR(INDEX(Deliverables!$D$5:$D$48,MATCH(B93,Deliverables!$A$5:$A$48,0)),"")) -> 6.3 | E93: ="Month 7: "&TEXT(EDATE(Award,6),"mmm yyyy") -> Month 7: Nov 2026 | F93: =WORKDAY(EOMONTH(Award,6),DueOffset) -> 46363 | J93: =IF(G93="","",WORKDAY(G93,ReviewDays)) | K93: =IF(AND(G93<>"",OR(H93="",H93="Pending"),Today>J93),"Past inspection window – deemed accepted","") | L93: =IF(AND(H93="Returned",I93<>""),WORKDAY(I93,ResubDays),"") | M93: =IF(OR(B93="",F93=""),"",IF(G93<>"",IF(G93<=F93,"On time","Late"),IF(Today>F93,"Overdue",IF(F93-Today<=7,"Due within 7 days","Not yet due")))) -> Not yet due | N93: =IF(OR(M93="Late",M93="Overdue"),IF(G93<>"",G93-F93,Today-F93),"") | O93: =IF(H93="Returned",1,0) -> 0 | Q93: Due date uses the DueOffset assumption.
A94: 90 | B94: A018 | C94: =IF(B94="","",IFERROR(INDEX(Deliverables!$B$5:$B$48,MATCH(B94,Deliverables!$A$5:$A$48,0)),"ID not found")) -> Monthly Progress Report (MPR) (including Invoice Data, ODC Data, Travel Data) | D94: =IF(B94="","",IFERROR(INDEX(Deliverables!$D$5:$D$48,MATCH(B94,Deliverables!$A$5:$A$48,0)),"")) -> 6.3 | E94: ="Month 8: "&TEXT(EDATE(Award,7),"mmm yyyy") -> Month 8: Dec 2026 | F94: =WORKDAY(EOMONTH(Award,7),DueOffset) -> 46394 | J94: =IF(G94="","",WORKDAY(G94,ReviewDays)) | K94: =IF(AND(G94<>"",OR(H94="",H94="Pending"),Today>J94),"Past inspection window – deemed accepted","") | L94: =IF(AND(H94="Returned",I94<>""),WORKDAY(I94,ResubDays),"") | M94: =IF(OR(B94="",F94=""),"",IF(G94<>"",IF(G94<=F94,"On time","Late"),IF(Today>F94,"Overdue",IF(F94-Today<=7,"Due within 7 days","Not yet due")))) -> Not yet due | N94: =IF(OR(M94="Late",M94="Overdue"),IF(G94<>"",G94-F94,Today-F94),"") | O94: =IF(H94="Returned",1,0) -> 0 | Q94: Due date uses the DueOffset assumption.
A95: 91 | B95: A018 | C95: =IF(B95="","",IFERROR(INDEX(Deliverables!$B$5:$B$48,MATCH(B95,Deliverables!$A$5:$A$48,0)),"ID not found")) -> Monthly Progress Report (MPR) (including Invoice Data, ODC Data, Travel Data) | D95: =IF(B95="","",IFERROR(INDEX(Deliverables!$D$5:$D$48,MATCH(B95,Deliverables!$A$5:$A$48,0)),"")) -> 6.3 | E95: ="Month 9: "&TEXT(EDATE(Award,8),"mmm yyyy") -> Month 9: Jan 2027 | F95: =WORKDAY(EOMONTH(Award,8),DueOffset) -> 46423 | J95: =IF(G95="","",WORKDAY(G95,ReviewDays)) | K95: =IF(AND(G95<>"",OR(H95="",H95="Pending"),Today>J95),"Past inspection window – deemed accepted","") | L95: =IF(AND(H95="Returned",I95<>""),WORKDAY(I95,ResubDays),"") | M95: =IF(OR(B95="",F95=""),"",IF(G95<>"",IF(G95<=F95,"On time","Late"),IF(Today>F95,"Overdue",IF(F95-Today<=7,"Due within 7 days","Not yet due")))) -> Not yet due | N95: =IF(OR(M95="Late",M95="Overdue"),IF(G95<>"",G95-F95,Today-F95),"") | O95: =IF(H95="Returned",1,0) -> 0 | Q95: Due date uses the DueOffset assumption.
A96: 92 | B96: A018 | C96: =IF(B96="","",IFERROR(INDEX(Deliverables!$B$5:$B$48,MATCH(B96,Deliverables!$A$5:$A$48,0)),"ID not found")) -> Monthly Progress Report (MPR) (including Invoice Data, ODC Data, Travel Data) | D96: =IF(B96="","",IFERROR(INDEX(Deliverables!$D$5:$D$48,MATCH(B96,Deliverables!$A$5:$A$48,0)),"")) -> 6.3 | E96: ="Month 10: "&TEXT(EDATE(Award,9),"mmm yyyy") -> Month 10: Feb 2027 | F96: =WORKDAY(EOMONTH(Award,9),DueOffset) -> 46451 | J96: =IF(G96="","",WORKDAY(G96,ReviewDays)) | K96: =IF(AND(G96<>"",OR(H96="",H96="Pending"),Today>J96),"Past inspection window – deemed accepted","") | L96: =IF(AND(H96="Returned",I96<>""),WORKDAY(I96,ResubDays),"") | M96: =IF(OR(B96="",F96=""),"",IF(G96<>"",IF(G96<=F96,"On time","Late"),IF(Today>F96,"Overdue",IF(F96-Today<=7,"Due within 7 days","Not yet due")))) -> Not yet due | N96: =IF(OR(M96="Late",M96="Overdue"),IF(G96<>"",G96-F96,Today-F96),"") | O96: =IF(H96="Returned",1,0) -> 0 | Q96: Due date uses the DueOffset assumption.
A97: 93 | B97: A018 | C97: =IF(B97="","",IFERROR(INDEX(Deliverables!$B$5:$B$48,MATCH(B97,Deliverables!$A$5:$A$48,0)),"ID not found")) -> Monthly Progress Report (MPR) (including Invoice Data, ODC Data, Travel Data) | D97: =IF(B97="","",IFERROR(INDEX(Deliverables!$D$5:$D$48,MATCH(B97,Deliverables!$A$5:$A$48,0)),"")) -> 6.3 | E97: ="Month 11: "&TEXT(EDATE(Award,10),"mmm yyyy") -> Month 11: Mar 2027 | F97: =WORKDAY(EOMONTH(Award,10),DueOffset) -> 46484 | J97: =IF(G97="","",WORKDAY(G97,ReviewDays)) | K97: =IF(AND(G97<>"",OR(H97="",H97="Pending"),Today>J97),"Past inspection window – deemed accepted","") | L97: =IF(AND(H97="Returned",I97<>""),WORKDAY(I97,ResubDays),"") | M97: =IF(OR(B97="",F97=""),"",IF(G97<>"",IF(G97<=F97,"On time","Late"),IF(Today>F97,"Overdue",IF(F97-Today<=7,"Due within 7 days","Not yet due")))) -> Not yet due | N97: =IF(OR(M97="Late",M97="Overdue"),IF(G97<>"",G97-F97,Today-F97),"") | O97: =IF(H97="Returned",1,0) -> 0 | Q97: Due date uses the DueOffset assumption.
A98: 94 | B98: A018 | C98: =IF(B98="","",IFERROR(INDEX(Deliverables!$B$5:$B$48,MATCH(B98,Deliverables!$A$5:$A$48,0)),"ID not found")) -> Monthly Progress Report (MPR) (including Invoice Data, ODC Data, Travel Data) | D98: =IF(B98="","",IFERROR(INDEX(Deliverables!$D$5:$D$48,MATCH(B98,Deliverables!$A$5:$A$48,0)),"")) -> 6.3 | E98: ="Month 12: "&TEXT(EDATE(Award,11),"mmm yyyy") -> Month 12: Apr 2027 | F98: =WORKDAY(EOMONTH(Award,11),DueOffset) -> 46514 | J98: =IF(G98="","",WORKDAY(G98,ReviewDays)) | K98: =IF(AND(G98<>"",OR(H98="",H98="Pending"),Today>J98),"Past inspection window – deemed accepted","") | L98: =IF(AND(H98="Returned",I98<>""),WORKDAY(I98,ResubDays),"") | M98: =IF(OR(B98="",F98=""),"",IF(G98<>"",IF(G98<=F98,"On time","Late"),IF(Today>F98,"Overdue",IF(F98-Today<=7,"Due within 7 days","Not yet due")))) -> Not yet due | N98: =IF(OR(M98="Late",M98="Overdue"),IF(G98<>"",G98-F98,Today-F98),"") | O98: =IF(H98="Returned",1,0) -> 0 | Q98: Due date uses the DueOffset assumption.
A99: 95 | B99: A019 | C99: =IF(B99="","",IFERROR(INDEX(Deliverables!$B$5:$B$48,MATCH(B99,Deliverables!$A$5:$A$48,0)),"ID not found")) -> Weekly Activity Report (WAR) | D99: =IF(B99="","",IFERROR(INDEX(Deliverables!$D$5:$D$48,MATCH(B99,Deliverables!$A$5:$A$48,0)),"")) -> 6.3 | E99: ="WAR wk 1" -> WAR wk 1 | F99: =Award+MOD(6-WEEKDAY(Award),7)+0 -> 46150 | J99: =IF(G99="","",WORKDAY(G99,ReviewDays)) | K99: =IF(AND(G99<>"",OR(H99="",H99="Pending"),Today>J99),"Past inspection window – deemed accepted","") | L99: =IF(AND(H99="Returned",I99<>""),WORKDAY(I99,ResubDays),"") | M99: =IF(OR(B99="",F99=""),"",IF(G99<>"",IF(G99<=F99,"On time","Late"),IF(Today>F99,"Overdue",IF(F99-Today<=7,"Due within 7 days","Not yet due")))) -> Overdue | N99: =IF(OR(M99="Late",M99="Overdue"),IF(G99<>"",G99-F99,Today-F99),"") -> 156 | O99: =IF(H99="Returned",1,0) -> 0
A100: 96 | B100: A019 | C100: =IF(B100="","",IFERROR(INDEX(Deliverables!$B$5:$B$48,MATCH(B100,Deliverables!$A$5:$A$48,0)),"ID not found")) -> Weekly Activity Report (WAR) | D100: =IF(B100="","",IFERROR(INDEX(Deliverables!$D$5:$D$48,MATCH(B100,Deliverables!$A$5:$A$48,0)),"")) -> 6.3 | E100: ="WAR wk 2" -> WAR wk 2 | F100: =Award+MOD(6-WEEKDAY(Award),7)+7 -> 46157 | J100: =IF(G100="","",WORKDAY(G100,ReviewDays)) | K100: =IF(AND(G100<>"",OR(H100="",H100="Pending"),Today>J100),"Past inspection window – deemed accepted","") | L100: =IF(AND(H100="Returned",I100<>""),WORKDAY(I100,ResubDays),"") | M100: =IF(OR(B100="",F100=""),"",IF(G100<>"",IF(G100<=F100,"On time","Late"),IF(Today>F100,"Overdue",IF(F100-Today<=7,"Due within 7 days","Not yet due")))) -> Overdue | N100: =IF(OR(M100="Late",M100="Overdue"),IF(G100<>"",G100-F100,Today-F100),"") -> 149 | O100: =IF(H100="Returned",1,0) -> 0
A101: 97 | B101: A019 | C101: =IF(B101="","",IFERROR(INDEX(Deliverables!$B$5:$B$48,MATCH(B101,Deliverables!$A$5:$A$48,0)),"ID not found")) -> Weekly Activity Report (WAR) | D101: =IF(B101="","",IFERROR(INDEX(Deliverables!$D$5:$D$48,MATCH(B101,Deliverables!$A$5:$A$48,0)),"")) -> 6.3 | E101: ="WAR wk 3" -> WAR wk 3 | F101: =Award+MOD(6-WEEKDAY(Award),7)+14 -> 46164 | J101: =IF(G101="","",WORKDAY(G101,ReviewDays)) | K101: =IF(AND(G101<>"",OR(H101="",H101="Pending"),Today>J101),"Past inspection window – deemed accepted","") | L101: =IF(AND(H101="Returned",I101<>""),WORKDAY(I101,ResubDays),"") | M101: =IF(OR(B101="",F101=""),"",IF(G101<>"",IF(G101<=F101,"On time","Late"),IF(Today>F101,"Overdue",IF(F101-Today<=7,"Due within 7 days","Not yet due")))) -> Overdue | N101: =IF(OR(M101="Late",M101="Overdue"),IF(G101<>"",G101-F101,Today-F101),"") -> 142 | O101: =IF(H101="Returned",1,0) -> 0
...

Sheet PWS Requirements
A1: PWS Requirements Register
A2: One row per PWS paragraph. "Deliverables named" is generated from the deliverable lists inside the PWS body. Paragraph numbers marked "Derived" are not printed in the PWS.
A4: Req ID | B4: PWS ¶ | C4: Ref basis | D4: Task group | E4: Requirement title | F4: Type | G4: What the Vendor shall do (summary of the PWS text) | H4: Deliverables named in PWS body | I4: # named | J4: Gap flag | K4: Owner | L4: Status | M4: Evidence / notes
A5: R000 | B5: Scope (unnumbered) | C5: PWS body | D5: All | E5: Project Management Plan; alignment to J6 Lines of Effort | F5: Base | G5: Maintain a Project Management Plan describing how PWS tasks are executed. Align all efforts to USPACOM J6 LOEs. Ensure deliverables meet quality, timeliness and compliance standards. Contribute to hardening the DoW enterprise on ZT principles. | I5: =IF(H5="",0,(LEN(H5)-LEN(SUBSTITUTE(H5,"A0","")))/2) -> 0 | J5: =IF(AND(I5=0,F5<>"Parent"),"No deliverable named","") -> No deliverable named | L5: Not Started
A6: R001 | B6: 6.1 | C6: PWS table | D6: 6.1 | E6: Zero Trust AI Implementation | F6: Base | G6: Develop architecture and install/implementation approach for a ZT AI platform; install and configure it in the PACOM environment; implement 2 use cases (Asset Management, Business Process Reengineering) to improve ZT governance; support ATO per RMF/NIST 800-53 (hosting, RBAC/ABAC); evaluate AS-IS PMN and recommend COAs; produce post-deployment design materials (architecture diagrams, ICDs, CONOPS); provide resources to operate and sustain the platform. | H6: A001 A002 A004 A005 A006 A007 A016 A024 A025 A026 | I6: =IF(H6="",0,(LEN(H6)-LEN(SUBSTITUTE(H6,"A0","")))/2) -> 10 | J6: =IF(AND(I6=0,F6<>"Parent"),"No deliverable named","") | L6: Not Started
A7: R002 | B7: 6.2.1 | C7: PWS table | D7: 6.2 | E7: Cybersecurity Engineering / A&A | F7: Base | G7: Test, evaluate, correct, mitigate and document system accreditation for USPACOM projects; coordinate vendors and the Risk Management Executive; manage PPSM records and whitelist entries; deliver weekly scan results with COAs to the ISSM; evaluate new IAVM, STIGs and SRGs; submit CAT I POA&Ms if a fix is not achieved within one week; track CAT I–III POA&Ms and Residual Risk Statements to closure. | H7: A003 A004 A005 A006 A007 A008 A009 A010 A011 A012 A013 A014 A015 | I7: =IF(H7="",0,(LEN(H7)-LEN(SUBSTITUTE(H7,"A0","")))/2) -> 13 | J7: =IF(AND(I7=0,F7<>"Parent"),"No deliverable named","") | L7: Not Started
A8: R003 | B8: 6.2.2 | C8: PWS table | D8: 6.2 | E8: Partner Nation Coordination / Country Desk Officer Support | F8: Base | G8: Provide Country Desk Officers: strengthen allied and partner defense relationships, assist with policy implementation guidance, and help develop common TTPs and SOPs for interoperability. | H8: A016 | I8: =IF(H8="",0,(LEN(H8)-LEN(SUBSTITUTE(H8,"A0","")))/2) -> 1 | J8: =IF(AND(I8=0,F8<>"Parent"),"No deliverable named","") | L8: Not Started
A9: R004 | B9: 6.3.1 | C9: PWS table | D9: 6.3 | E9: Task Order Management / PMO Support for PMN | F9: Base | G9: Plan, run and track the kickoff meeting plus a weekly team meeting and monthly reviews; maintain knowledge management; use DoD365 for document control; provide task order management, reporting and oversight; submit MPR and WAR; deliver transition-in/out plans and closeout. | H9: A017 | I9: =IF(H9="",0,(LEN(H9)-LEN(SUBSTITUTE(H9,"A0","")))/2) -> 1 | J9: =IF(AND(I9=0,F9<>"Parent"),"No deliverable named","") | L9: Not Started
A10: R005 | B10: 6.3.1.1 | C10: PWS table | D10: 6.3 | E10: Monthly Progress Report (MPR) | F10: Base | G10: Submit an MPR (format agreed with the Government) covering tasks, progress, quality, risks, customer feedback, problems, accomplishments, trips, personnel changes, funds depletion and invoicing, ODCs and GFE status. | H10: A018 | I10: =IF(H10="",0,(LEN(H10)-LEN(SUBSTITUTE(H10,"A0","")))/2) -> 1 | J10: =IF(AND(I10=0,F10<>"Parent"),"No deliverable named","") | L10: Not Started
A11: R006 | B11: 6.3.1.2 | C11: PWS table | D11: 6.3 | E11: Weekly Activity Report (WAR) | F11: Base | G11: Take part in weekly project meetings; collect and present weekly status charts and reports to the on-site Government POC. | H11: A019 | I11: =IF(H11="",0,(LEN(H11)-LEN(SUBSTITUTE(H11,"A0","")))/2) -> 1 | J11: =IF(AND(I11=0,F11<>"Parent"),"No deliverable named","") | L11: Not Started
A12: R007 | B12: 6.3.1.3 | C12: PWS table | D12: 6.3 | E12: Transition Planning | F12: Base | G12: Deliver a Transition-In Plan (30 days after kickoff per body) and a Transition-Out Plan (120 calendar days before end per body); run a formal closeout; capture and deliver lessons learned. | H12: A041 A042 A043 | I12: =IF(H12="",0,(LEN(H12)-LEN(SUBSTITUTE(H12,"A0","")))/2) -> 3 | J12: =IF(AND(I12=0,F12<>"Parent"),"No deliverable named","") | L12: Not Started
A13: R008 | B13: 6.3.1.4 | C13: PWS table | D13: 6.3 | E13: Hardware and Software Maintenance Support (Logistics) | F13: Base | G13: Order, deliver and account for HW/SW; define and track GFE; sustain and track maintenance agreements; coordinate equipment movement between lab and production; pass tracking data to Configuration Management. | H13: A019 A044 | I13: =IF(H13="",0,(LEN(H13)-LEN(SUBSTITUTE(H13,"A0","")))/2) -> 2 | J13: =IF(AND(I13=0,F13<>"Parent"),"No deliverable named","") | L13: Not Started
A14: R009 | B14: 6.3.1.5 | C14: PWS body | D14: 6.3 | E14: Communications | F14: Base | G14: Engage DoW and USPACOM stakeholders; attend meetings, conferences and events; develop marketing material (SharePoint sites, brochures, presentations); run an engagement strategy to promote adoption of modernization initiatives. | I14: =IF(H14="",0,(LEN(H14)-LEN(SUBSTITUTE(H14,"A0","")))/2) -> 0 | J14: =IF(AND(I14=0,F14<>"Parent"),"No deliverable named","") -> No deliverable named | L14: Not Started
A15: R010 | B15: 6.3.1.6 | C15: PWS body | D15: 6.3 | E15: Cyber Capacity | F15: Base | G15: Support partner-nation cyber and mission assurance: set capacity-building objectives, plan and run engagements (exercises, training), track deliverables and coordinate stakeholders. | I15: =IF(H15="",0,(LEN(H15)-LEN(SUBSTITUTE(H15,"A0","")))/2) -> 0 | J15: =IF(AND(I15=0,F15<>"Parent"),"No deliverable named","") -> No deliverable named | L15: Not Started
A16: R011 | B16: 6.3.1.7 | C16: PWS table | D16: 6.3 | E16: Knowledge Management, Technical Documentation, Meeting Support | F16: Base | G16: Maintain knowledge management and a technical library on DoD365; support project management, integration, engineering reviews and meetings; prepare technical briefs and presentations. | H16: A020 A021 A022 | I16: =IF(H16="",0,(LEN(H16)-LEN(SUBSTITUTE(H16,"A0","")))/2) -> 3 | J16: =IF(AND(I16=0,F16<>"Parent"),"No deliverable named","") | L16: Not Started
A17: R012 | B17: 6.3.2 | C17: Derived | D17: 6.3 | E17: Subtask 2 – ZT Modernization Design and Architecture (parent) | F17: Parent | G17: Support continual modernization of the DoW/USPACOM ZTA: expand, scale and make Thunderdome resilient; integrate non-Thunderdome ZT capabilities across all seven DoW ZT pillars. | I17: =IF(H17="",0,(LEN(H17)-LEN(SUBSTITUTE(H17,"A0","")))/2) -> 0 | J17: =IF(AND(I17=0,F17<>"Parent"),"No deliverable named","") | L17: Not Started
A18: R013 | B18: 6.3.2.1 | C18: PWS table | D18: 6.3 | E18: Analysis of Alternatives | F18: Base | G18: Research new ZT technologies across the pillars; assess capabilities for tech insertion and refresh; run AoAs that separate vendors offering similar capabilities. | H18: A016 A023 | I18: =IF(H18="",0,(LEN(H18)-LEN(SUBSTITUTE(H18,"A0","")))/2) -> 2 | J18: =IF(AND(I18=0,F18<>"Parent"),"No deliverable named","") | L18: Not Started
A19: R014 | B19: 6.3.2.2 | C19: PWS table | D19: 6.3 | E19: Network Transformation and Modernization Support | F19: Base | G19: Recommend and support progress toward operational C2; refine architectures to ZT; scale for CJADC2; lead migration off legacy infrastructure (SD-WAN, NFV, STIG adherence); lead migration/integration of MNIS and CENTRIX into PMN. | H19: A027 | I19: =IF(H19="",0,(LEN(H19)-LEN(SUBSTITUTE(H19,"A0","")))/2) -> 1 | J19: =IF(AND(I19=0,F19<>"Parent"),"No deliverable named","") | L19: Not Started
A20: R015 | B20: 6.3.2.3 | C20: PWS table | D20: 6.3 | E20: Zero Trust Policy Assessment | F20: Base | G20: Compare USPACOM cyber capabilities with the DoW Reference Architecture and DoW CIO requirements; identify and recommend ways to close gaps; comment on proposed policy impacts. | H20: A023 A028 A029 A030 | I20: =IF(H20="",0,(LEN(H20)-LEN(SUBSTITUTE(H20,"A0","")))/2) -> 4 | J20: =IF(AND(I20=0,F20<>"Parent"),"No deliverable named","") | L20: Not Started
A21: R016 | B21: 6.3.2.4 | C21: PWS table | D21: 6.3 | E21: Architecture, Design, and Engineering | F21: Base + Optional | G21: Develop architecture and design documentation for continual ZTA modernization across API security, tactical ZTNA, SASE, Cyber SA/CDAP, SOAR, AppSS, data protection, RBI/VDI, secure collaboration, CSfC and gateway/national boundary. Optional priced: Tactical/Fly-Away Kit, PNSOC design. | H21: A016 A023 A024 A025 | I21: =IF(H21="",0,(LEN(H21)-LEN(SUBSTITUTE(H21,"A0","")))/2) -> 4 | J21: =IF(AND(I21=0,F21<>"Parent"),"No deliverable named","") | L21: Not Started
A22: R017 | B22: 6.3.2.5 | C22: PWS table | D22: 6.3 | E22: AppSS Integration, Implementation, and Cutover | F22: Base | G22: Design, integrate and implement the Thunderdome AppSS template for USPACOM hosted applications; collect application architecture, flows and PPS requirements from application owners. | H22: A031 A032 A033 | I22: =IF(H22="",0,(LEN(H22)-LEN(SUBSTITUTE(H22,"A0","")))/2) -> 3 | J22: =IF(AND(I22=0,F22<>"Parent"),"No deliverable named","") | L22: Not Started
A23: R018 | B23: 6.3.2.6 | C23: PWS table | D23: 6.3 | E23: MPE Enterprise Management Services | F23: Base | G23: Provide technical SME services for USPACOM MPE governance: advice on MPE principles and standards, scaled governance frameworks, support to the CISO for RMF oversight and configuration control. | I23: =IF(H23="",0,(LEN(H23)-LEN(SUBSTITUTE(H23,"A0","")))/2) -> 0 | J23: =IF(AND(I23=0,F23<>"Parent"),"No deliverable named","") -> No deliverable named | L23: Not Started
A24: R019 | B24: 6.3.3 | C24: Derived | D24: 6.3 | E24: Subtask 3 – ZT Integration and Implementation for PMN (parent) | F24: Parent | G24: Parent heading for 6.3.3.1 through 6.3.3.7. | I24: =IF(H24="",0,(LEN(H24)-LEN(SUBSTITUTE(H24,"A0","")))/2) -> 0 | J24: =IF(AND(I24=0,F24<>"Parent"),"No deliverable named","") | L24: Not Started
A25: R020 | B25: 6.3.3.1 | C25: PWS table | D25: 6.3 | E25: Site Specific Advanced Engineering Services | F25: Base | G25: Provide engineering for J6 innovation projects as directed by J68; produce site-specific architecture and design documentation; conduct site surveys for new fielding or upgrades; scale integration testing; improve documentation and training. | H25: A016 A023 A024 A032 A034 | I25: =IF(H25="",0,(LEN(H25)-LEN(SUBSTITUTE(H25,"A0","")))/2) -> 5 | J25: =IF(AND(I25=0,F25<>"Parent"),"No deliverable named","") | L25: Not Started
A26: R021 | B26: 6.3.3.2 | C26: PWS table | D26: 6.3 | E26: Integration, Implementation, and Cutover of Existing Solutions | F26: Base + Optional | G26: Integrate and implement Thunderdome for USPACOM (configurations, lab testing, integration, user migration); lead MNIS/CENTRIX migration; implement API security, tactical ZTNA, SASE, Cyber SA (CDAP, feeds, dashboards), SOAR, AppSS, data protection, RBI/VDI, secure collaboration, CSfC and gateway. Optional priced: Fly-Away Kits, PNSOC deployment. | H26: A031 A032 A033 | I26: =IF(H26="",0,(LEN(H26)-LEN(SUBSTITUTE(H26,"A0","")))/2) -> 3 | J26: =IF(AND(I26=0,F26<>"Parent"),"No deliverable named","") | L26: Not Started
A27: R022 | B27: 6.3.3.3 | C27: PWS table | D27: 6.3 | E27: Integration, Implementation, and Cutover of New ZT Solutions | F27: Base | G27: Integrate and implement new ZT solutions designed under this PWS (API security with AppSS, COOP, tactical ZTNA, Cyber SA, SOAR, AppSS, data protection, system administration, cloud security). | H27: A031 A032 A033 | I27: =IF(H27="",0,(LEN(H27)-LEN(SUBSTITUTE(H27,"A0","")))/2) -> 3 | J27: =IF(AND(I27=0,F27<>"Parent"),"No deliverable named","") | L27: Not Started
A28: R023 | B28: 6.3.3.4 | C28: Derived | D28: 6.3 | E28: Operational VDI Deployment and Integration | F28: Base | G28: Design and build a rapidly deployable, data-aware VDI baseline for hosting third-party applications; sustain existing VDI while expanding users/applications; improve logging and monitoring; refine templates. | I28: =IF(H28="",0,(LEN(H28)-LEN(SUBSTITUTE(H28,"A0","")))/2) -> 0 | J28: =IF(AND(I28=0,F28<>"Parent"),"No deliverable named","") -> No deliverable named | L28: Not Started
A29: R024 | B29: 6.3.3.4.1 | C29: Derived | D29: 6.3 | E29: Data Centric Security (DCS) Enabled Mission Applications | F29: Base | G29: Provide a data-aware environment with third-party DCS toolsets to support MPE development; scale DCS-enabled applications; improve compliance with secure data-sharing and ZT. | I29: =IF(H29="",0,(LEN(H29)-LEN(SUBSTITUTE(H29,"A0","")))/2) -> 0 | J29: =IF(AND(I29=0,F29<>"Parent"),"No deliverable named","") -> No deliverable named | L29: Not Started
A30: R025 | B30: 6.3.3.5 | C30: Derived | D30: 6.3 | E30: Identity and Access Management (IAM) | F30: Base | G30: Manage identities, credentials and access rights; implement and maintain MFA, RBAC and IAM best practice; integrate with Active Directory and CAC. | I30: =IF(H30="",0,(LEN(H30)-LEN(SUBSTITUTE(H30,"A0","")))/2) -> 0 | J30: =IF(AND(I30=0,F30<>"Parent"),"No deliverable named","") -> No deliverable named | L30: Not Started
A31: R026 | B31: 6.3.3.6 | C31: Derived | D31: 6.3 | E31: Secure Enclave Migration | F31: Base | G31: Plan and execute migration of legacy systems into the modernized secure network; build a comprehensive migration plan with milestones, procedures and rollback plans. | I31: =IF(H31="",0,(LEN(H31)-LEN(SUBSTITUTE(H31,"A0","")))/2) -> 0 | J31: =IF(AND(I31=0,F31<>"Parent"),"No deliverable named","") -> No deliverable named | L31: Not Started
A32: R027 | B32: 6.3.3.7 | C32: Derived | D32: 6.3 | E32: Exercise Support | F32: Base | G32: Engage stakeholders and produce architecture/design documentation for exercises; run pre-exercise lead-in 30–60 days before execution; operate the exercise network, provision accounts, build integrations and implement changes under change management. | I32: =IF(H32="",0,(LEN(H32)-LEN(SUBSTITUTE(H32,"A0","")))/2) -> 0 | J32: =IF(AND(I32=0,F32<>"Parent"),"No deliverable named","") -> No deliverable named | L32: Not Started
A33: R028 | B33: 6.3.4 | C33: Derived | D33: 6.3 | E33: Subtask 4 – Tier III Engineering, Help Desk, Lab and Testing (parent) | F33: Parent | G33: Provide Tier III engineering for USPACOM ZT solutions and develop and maintain multiple lab environments. | I33: =IF(H33="",0,(LEN(H33)-LEN(SUBSTITUTE(H33,"A0","")))/2) -> 0 | J33: =IF(AND(I33=0,F33<>"Parent"),"No deliverable named","") | L33: Not Started
A34: R029 | B34: 6.3.4.1.1 | C34: PWS table | D34: 6.3 | E34: 8x5 Tier III Engineering | F34: Base | G34: Provide Tier III SMEs for current and future PMN architecture; resolve escalated incidents and problems; receive Tier II tickets in the existing incident management systems. | H34: A035 | I34: =IF(H34="",0,(LEN(H34)-LEN(SUBSTITUTE(H34,"A0","")))/2) -> 1 | J34: =IF(AND(I34=0,F34<>"Parent"),"No deliverable named","") | L34: Not Started
A35: R030 | B35: 6.3.4.1.2 | C35: PWS table | D35: 6.3 | E35: Change Management and Help Desk Support | F35: Optional Priced | G35: Provide Tier III help desk and change management; open, track and close changes; support transition to ServiceNow ITSM; provide dedicated help desk engineering. | H35: A035 A036 A037 | I35: =IF(H35="",0,(LEN(H35)-LEN(SUBSTITUTE(H35,"A0","")))/2) -> 3 | J35: =IF(AND(I35=0,F35<>"Parent"),"No deliverable named","") | L35: Not Started
A36: R031 | B36: Unnumbered (24x7) | C36: Derived | D36: 6.3 | E36: 24x7 Dedicated Tier III Engineering and Help Desk Support | F36: Optional | G36: Tier III team for all supported capabilities with 24x7 coverage and a 2-hour maximum response; up to 90 calendar days per labor position, up to two personnel. | H36: A035 A036 A037 | I36: =IF(H36="",0,(LEN(H36)-LEN(SUBSTITUTE(H36,"A0","")))/2) -> 3 | J36: =IF(AND(I36=0,F36<>"Parent"),"No deliverable named","") | L36: Not Started
A37: R032 | B37: 6.3.4.1.3 | C37: PWS table | D37: 6.3 | E37: Vendor Lab Testing | F37: Base | G37: Maintain a Vendor-hosted lab; test new SW/HW before fielding; provide test plans and reports for major upgrades; test and remediate IAVAs, tech refresh and Tier III fixes. | H37: A025 A038 A039 | I37: =IF(H37="",0,(LEN(H37)-LEN(SUBSTITUTE(H37,"A0","")))/2) -> 3 | J37: =IF(AND(I37=0,F37<>"Parent"),"No deliverable named","") | L37: Not Started
A38: R033 | B38: 6.3.4.1.4 | C38: PWS table | D38: 6.3 | E38: Government Lab Support | F38: Base | G38: Provide architecture, design and engineering support to Government-owned cloud and on-premises labs that integrate and evaluate ZT technologies. | H38: A025 A038 A039 | I38: =IF(H38="",0,(LEN(H38)-LEN(SUBSTITUTE(H38,"A0","")))/2) -> 3 | J38: =IF(AND(I38=0,F38<>"Parent"),"No deliverable named","") | L38: Not Started
A39: R034 | B39: 6.3.4.1.5 | C39: PWS table | D39: 6.3 | E39: DevSecOps | F39: Optional Priced | G39: Architect and integrate a DevSecOps environment for MPE; evaluate the existing development environment, propose COAs, stand up and transition, then operate it. | H39: A025 | I39: =IF(H39="",0,(LEN(H39)-LEN(SUBSTITUTE(H39,"A0","")))/2) -> 1 | J39: =IF(AND(I39=0,F39<>"Parent"),"No deliverable named","") | L39: Not Started
A40: R035 | B40: 6.3.4.2 | C40: PWS table | D40: 6.3 | E40: PACOM Network Security Operation Center (PNSOC) Support | F40: Optional Priced | G40: Provide ongoing security monitoring and incident response with automated tools, threat intelligence and trained staff; detect, analyze, contain and eradicate incidents quickly. | H40: A040 | I40: =IF(H40="",0,(LEN(H40)-LEN(SUBSTITUTE(H40,"A0","")))/2) -> 1 | J40: =IF(AND(I40=0,F40<>"Parent"),"No deliverable named","") | L40: Not Started
A42: Derived paragraph numbers: the PWS prints numbers only for 6.3.1.3–6.3.1.7. All other numbers come from the deliverables table or heading order. Confirm against the Government's numbered copy.

Sheet Timed Obligations
A1: Timed Obligations
A2: Every time limit the PWS sets. "Tracked in" tells you where the clock lives in this workbook.
A4: ID | B4: PWS ¶ / source | C4: Obligation | D4: Trigger | E4: Limit | F4: Unit | G4: Related deliverable | H4: Tracked in | I4: Conflict / note
A5: T01 | B5: 6.2.1 body | C5: Submit a CAT I POA&M to the ISSM when a fix cannot be achieved | D5: Finding or newly released IAVM/STIG/SRG | E5: 1 | F5: week (7 calendar days) | G5: A005 | H5: Log (add row per finding) | I5: Conflicts with A005 table: 30 days after identification.
A6: T02 | B6: A005 table | C6: Submit risk-acceptance POA&M; review every 30 days | D6: Vulnerability that cannot be mitigated | E6: 30 | F6: calendar days | G6: A005 | H6: Log (add row per finding) | I6: See above.
A7: T03 | B7: 6.2.1 body | C7: Deliver scan results with recommended COAs to the ISSM | D7: Weekly | E7: 7 | F7: calendar days | G7: A007 | H7: Log (pre-filled weekly) | I7: Table due date says "As Needed"; frequency says Weekly.
A8: T04 | B8: 6.3.1.3 body | C8: Deliver Transition-In Plan | D8: Contract kickoff | E8: 30 | F8: calendar days | G8: A041 | H8: Log (pre-filled) | I8: Table: draft at kickoff, final 5 business days after award.
A9: T05 | B9: 6.3.1.3 body | C9: Deliver Transition-Out Plan | D9: End of task order | E9: 120 | F9: calendar days before end | G9: A042 | H9: Log (pre-filled) | I9: Table: T-30. Workbook uses 120.
A10: T06 | B10: Deliverables | C10: Government inspects and accepts/rejects; silence = deemed acceptance | D10: Deliverable received | E10: 5 | F10: business days | G10: All | H10: Log col J–K
A11: T07 | B11: Deliverables | C11: Vendor resubmits after written rejection | D11: Rejection notice | E11: 10 | F11: business days | G11: All | H11: Log col L
A12: T08 | B12: Incentives | C12: Written reply to a Corrective Action Report with prevention plan | D12: CAR received | E12: 5 | F12: business days | G12: n/a | H12: Not logged (add to Log with a custom ID if used) | I12: Government may withhold payment until corrective action is accepted.
A13: T09 | B13: 6.3.3.7 body | C13: Pre-exercise lead-in: requirements, design, procurement, pre-staging | D13: Exercise execution date | E13: 60 | F13: to 30 days before | G13: n/a | H13: Not logged | I13: Window is 30–60 days before the exercise.
A14: T10 | B14: 6.3.4.1.x body | C14: Maximum response time for 24x7 Tier III support | D14: Issue reported | E14: 2 | F14: hours | G14: A035–A037 | H14: Not logged | I14: Optional task. Up to 90 calendar days per labor position, up to 2 personnel.
A15: T11 | B15: A037 table | C15: Help Desk Report on request | D15: Government request | E15: 24 | F15: hours | G15: A037 | H15: Not logged
A16: T12 | B16: A033 table | C16: ASI submitted before an expected outage | D16: Planned outage | E16: 10 | F16: days before | G16: A033 | H16: Not logged | I16: Needs Government approval.
A17: T13 | B17: A035 table | C17: ITSM / change ticket before the change | D17: Planned change | E17: 10 | F17: days before | G17: A035 | H17: Not logged
A18: T14 | B18: A031 table | C18: Implementation Plan before implementation | D18: Planned implementation | E18: 30 | F18: days before | G18: A031 | H18: Not logged
A19: T15 | B19: A025/A032 table | C19: Engineering artifacts after assignment | D19: Tasking | E19: 10 | F19: business days | G19: A025, A032 | H19: Not logged
A20: T16 | B20: A036 table | C20: Metrics Report after implementation | D20: Implementation | E20: 30 | F20: days after | G20: A036 | H20: Not logged
A21: T17 | B21: A026 table | C21: CONOPS after deployment | D21: Deployment | E21: 60 | F21: days after | G21: A026 | H21: Log (blank due date) | I21: Enter the deployment date + 60.
A22: T18 | B22: Place of Performance | C22: Written AOR approval for long-distance travel | D22: Before incurring cost | E22: 0 | F22: before travel | G22: n/a | H22: Not logged | I22: Approval must precede the cost.
A23: T19 | B23: Dependencies | C23: Written notice to PM and AO of a Government-caused delay | D23: Delay event | E23: 0 | F23: as soon as possible | G23: n/a | H23: Not logged | I23: Notice is a condition for relief under the Dependencies clause.

Sheet Traceability Check
A1: Traceability Check
A2: Compares the PWS refs in the deliverables table with where each deliverable is actually listed in the PWS body.
A4: ID | B4: Deliverable | C4: Refs in PWS table | D4: Refs in PWS body (generated) | E4: Result | F4: Difference
A5: A001 | B5: Implementation Approach and Architecture | C5: 6.1 | D5: 6.1 | E5: =IF(C5=D5,"Match","Differs") -> Match
A6: A002 | B6: ZT Governance Plan | C6: 6.1 | D6: 6.1 | E6: =IF(C6=D6,"Match","Differs") -> Match
A7: A003 | B7: eMASS Data Entry | C7: 6.2.1 | D7: 6.2.1 | E7: =IF(C7=D7,"Match","Differs") -> Match
A8: A004 | B8: ATO Documentation/ Artifacts | C8: 6.1, 6.2.1 | D8: 6.1, 6.2.1 | E8: =IF(C8=D8,"Match","Differs") -> Match
A9: A005 | B9: POA&Ms including risk acceptance POA&Ms for vulnerabilities that cannot be mitigated and STIGs that cannot be applied. | C9: 6.1, 6.2.1 | D9: 6.1, 6.2.1 | E9: =IF(C9=D9,"Match","Differs") -> Match
A10: A006 | B10: STIG/SRG Checklists | C10: 6.1, 6.2.1 | D10: 6.1, 6.2.1 | E10: =IF(C10=D10,"Match","Differs") -> Match
A11: A007 | B11: ACAS Scans | C11: 6.1, 6.2.1 | D11: 6.1, 6.2.1 | E11: =IF(C11=D11,"Match","Differs") -> Match
A12: A008 | B12: System Change Requests Form/ Configuration Change Request | C12: 6.2.1 | D12: 6.2.1 | E12: =IF(C12=D12,"Match","Differs") -> Match
A13: A009 | B13: eMASS Package | C13: 6.2.1 | D13: 6.2.1 | E13: =IF(C13=D13,"Match","Differs") -> Match
A14: A010 | B14: Status updates on Security patches/hot fixes, OPORD, TASK ORDER, FISMA, PPSM, IAVM and STIGs | C14: 6.2.1 | D14: 6.2.1 | E14: =IF(C14=D14,"Match","Differs") -> Match
A15: A011 | B15: Incident Response Plan | C15: 6.2.1 | D15: 6.2.1 | E15: =IF(C15=D15,"Match","Differs") -> Match
A16: A012 | B16: Security Monitoring Reports | C16: 6.2.1 | D16: 6.2.1 | E16: =IF(C16=D16,"Match","Differs") -> Match
... A26: A022 | B26: Knowledge Management Site | C26: 6.3.1.7 | D26: 6.3.1.7 | E26: =IF(C26=D26,"Match","Differs") -> Match
A27: A023 | B27: Whitepapers | C27: 6.3.2.1, 6.3.2.3, 6.3.3.1 | D27: 6.3.2.1, 6.3.2.3, 6.3.2.4, 6.3.3.1 | E27: =IF(C27=D27,"Match","Differs") -> Differs | F27: In body, not in table: 6.3.2.4
A28: A024 | B28: DoDAF Artifacts/Diagrams (e.g., OV, SV) | C28: 6.1, 6.3.2.4, 6.3.3.1 | D28: 6.1, 6.3.2.4, 6.3.3.1 | E28: =IF(C28=D28,"Match","Differs") -> Match
A29: A025 | B29: Engineering Artifacts (e.g., Network/System Diagrams) | C29: 6.1, 6.3.2.4, 6.3.4.1.3, 6.3.4.1.4, 6.3.4.1.5 | D29: 6.1, 6.3.2.4, 6.3.4.1.3, 6.3.4.1.4, 6.3.4.1.5 | E29: =IF(C29=D29,"Match","Differs") -> Match
A30: A026 | B30: Concept of Operations (CONOPS) | C30: 6.1 | D30: 6.1 | E30: =IF(C30=D30,"Match","Differs") -> Match
A31: A027 | B31: Network Modernization Plan | C31: 6.3.2.2 | D31: 6.3.2.2 | E31: =IF(C31=D31,"Match","Differs") -> Match
A32: A028 | B32: ZT Traceability Matrix | C32: 6.3.2.3 | D32: 6.3.2.3 | E32: =IF(C32=D32,"Match","Differs") -> Match
A33: A029 | B33: ZT Gap Analysis | C33: 6.3.2.3 | D33: 6.3.2.3 | E33: =IF(C33=D33,"Match","Differs") -> Match
A34: A030 | B34: Zero Trust Architecture Design Document | C34: 6.3.2.3 | D34: 6.3.2.3 | E34: =IF(C34=D34,"Match","Differs") -> Match
A35: A031 | B35: Implementation Plan | C35: 6.3.2.5, 6.3.3.2, 6.3.3.3 | D35: 6.3.2.5, 6.3.3.2, 6.3.3.3 | E35: =IF(C35=D35,"Match","Differs") -> Match
A36: A032 | B36: Engineering Artifacts (e.g., Network/System Diagrams) | C36: 6.3.2.5, 6.3.3.1, 6.3.3.2, 6.3.3.3 | D36: 6.3.2.5, 6.3.3.1, 6.3.3.2, 6.3.3.3 | E36: =IF(C36=D36,"Match","Differs") -> Match
A37: A033 | B37: ASIs | C37: 6.3.2.5, 6.3.3.2, 6.3.3.3 | D37: 6.3.2.5, 6.3.3.2, 6.3.3.3 | E37: =IF(C37=D37,"Match","Differs") -> Match
A38: A034 | B38: Site Survey Reports | C38: 6.3.2.6, 6.3.3.1 | D38: 6.3.3.1 | E38: =IF(C38=D38,"Match","Differs") -> Differs | F38: In table, not in body: 6.3.2.6
A39: A035 | B39: ITSM/ Change Tickets | C39: 6.3.4.1.1, 6.3.4.1.2 | D39: 6.3.4.1.1, 6.3.4.1.2, 6.3.4.1.x | E39: =IF(C39=D39,"Match","Differs") -> Differs | F39: In body, not in table: 6.3.4.1.x
A40: A036 | B40: Metrics Report | C40: 6.3.4.1.2 | D40: 6.3.4.1.2, 6.3.4.1.x | E40: =IF(C40=D40,"Match","Differs") -> Differs | F40: In body, not in table: 6.3.4.1.x
A41: A037 | B41: Help Desk Report | C41: 6.3.4.1.2 | D41: 6.3.4.1.2, 6.3.4.1.x | E41: =IF(C41=D41,"Match","Differs") -> Differs | F41: In body, not in table: 6.3.4.1.x
A42: A038 | B42: Test Plans | C42: 6.3.4.1.3, 6.3.4.1.4 | D42: 6.3.4.1.3, 6.3.4.1.4 | E42: =IF(C42=D42,"Match","Differs") -> Match
A43: A039 | B43: Test Reports | C43: 6.3.4.1.3, 6.3.4.1.4 | D43: 6.3.4.1.3, 6.3.4.1.4 | E43: =IF(C43=D43,"Match","Differs") -> Match
A44: A040 | B44: Security Monitoring Reports | C44: 6.3.4.2 | D44: 6.3.4.2 | E44: =IF(C44=D44,"Match","Differs") -> Match
A45: A041 | B45: Transition-In Plan | C45: 6.3.1.3 | D45: 6.3.1.3 | E45: =IF(C45=D45,"Match","Differs") -> Match
A46: A042 | B46: Transition-Out Plan | C46: 6.3.1.3 | D46: 6.3.1.3 | E46: =IF(C46=D46,"Match","Differs") -> Match
A47: A043 | B47: Task Order Closeout | C47: 6.3.1.3 | D47: 6.3.1.3 | E47: =IF(C47=D47,"Match","Differs") -> Match
A48: A044 | B48: Logistics Deliverables | C48: 6.3.1.4 | D48: 6.3.1.4 | E48: =IF(C48=D48,"Match","Differs") -> Match
A50: Deliverables that differ | C50: =COUNTIF(E5:E48,"Differs") -> 5

Sheet PWS Issues
A1: PWS Issues for Government Ruling
A2: Items the Vendor should get clarified (ideally in writing from the AOR) before relying on a date or scope boundary.
A4: # | B4: Type | C4: Where | D4: Issue | E4: Why it matters | F4: Suggested resolution | G4: Raised with / date | H4: Resolution
A5: 1 | B5: Conflict | C5: 6.3.1.3 vs A041 | D5: Body: Transition-In Plan 30 days after kickoff. Table: initial draft at kickoff, final 5 business days after award. | E5: Two due dates for one deliverable. Either could be called late. | F5: Ask the AOR which governs; record the answer in the Log note.
A6: 2 | B6: Conflict | C6: 6.3.1.3 vs A042 | D6: Body: Transition-Out Plan 120 calendar days before end. Table: T-30 days. | E6: Roughly 1 Jun 2029 vs 30 Aug 2029 for the final option year (end 29 Sep 2029). | F6: Plan to the earlier date until ruled otherwise (workbook does this).
A7: 3 | B7: Conflict | C7: 6.2.1 vs A005 | D7: Body: submit CAT I POA&M if no fix within one week. Table: 30 days after identification, reviewed every 30 days. | E7: A 7-day vs 30-day clock on a security deliverable. | F7: Confirm the one-week trigger is the escalation point and 30 days the POA&M due date.
A8: 4 | B8: Reference gap | C8: A034 / 6.3.2.6 | D8: Table cites 6.3.2.6 (MPE Enterprise Management) for Site Survey Reports. The body lists A034 only under 6.3.3.1. | E8: 6.3.2.6 has no deliverable in the body; either the table is wrong or the paragraph needs one. | F8: Correct the table or add the deliverable to 6.3.2.6.
A9: 5 | B9: Reference gap | C9: A023 / 6.3.2.4 | D9: Body lists Whitepapers under Architecture, Design and Engineering; table omits 6.3.2.4. | E9: Acceptance criteria could skip a whitepaper owed under 6.3.2.4. | F9: Add 6.3.2.4 to the table row.
A10: 6 | B10: Reference gap | C10: A035–A037 / 24x7 | D10: The 24x7 optional task lists A035, A036, A037 in the body; the table cites only 6.3.4.1.1 and 6.3.4.1.2. The 24x7 paragraph also has no number that fits the table sequence. | E10: Optional-task deliverables untraceable if the option is exercised. | F10: Number the paragraph and add it to the table.
A11: 7 | B11: Undefined term | C11: A020–A023, A028, A044 | D11: Due date "ICW MSR". The PWS never defines MSR (it uses MPR). | E11: Six deliverables have no defined due date. | F11: Ask whether MSR = Monthly Status Review, or the MPR. Set the DueOffset on Start Here.
A12: 8 | B12: Undefined term | C12: A001, A002, A004, A011, A015, A031, A034 and others | D12: Due "IAW IMS" (Integrated Master Schedule, A017). "Standard Distribution" is also undefined. | E12: The IMS itself is a monthly deliverable, so dates for others depend on it being approved first. | F12: Get the baseline IMS accepted first; record the distribution list.
A13: 9 | B13: Timing | C13: A038, A039, A040 | D13: Test Plans and Test Reports due 30 days after award; Security Monitoring Reports (PNSOC) due 90 days after award as a one-time item. | E13: Test reports cannot precede testing; PNSOC monitoring is ongoing and optional. | F13: Ask whether these are per-upgrade and per-period items.
A14: 10 | B14: Gap | C14: 6.3.1.5, 6.3.1.6, 6.3.2.6, 6.3.3.4–6.3.3.7 | D14: No deliverable is named for Communications, Cyber Capacity, MPE Enterprise Management, VDI, DCS, IAM, Secure Enclave Migration or Exercise Support. | E14: Work with no acceptance event is hard to invoice and defend. Enclave migration requires a "comprehensive migration plan" and Exercise Support requires architecture and design documentation, yet neither has a deliverable number. | F14: Propose deliverable numbers or confirm they roll into A016, A025 and A032.
A15: 11 | B15: Gap | C15: Scope, Task 1, 6.2.1, 6.3.1.3 | D15: Named but not in the deliverables table: Project Management Plan, ICDs (Task 1), lessons-learned report, Residual Risk Statements, weekly scan COAs. | E15: Obligations without deliverable IDs get missed. | F15: Map each to an existing ID or request new IDs.
A16: 12 | B16: Gap | C16: 6.2.2 | D16: Partner Nation Coordination lists only A016 Briefings Slides. | E16: Country Desk Officer work has no measurable output beyond slides. | F16: Ask for the reporting expected (for example a monthly desk-officer summary).
... A24: 20 | B24: Duplicate | C24: A025 / A032, A012 / A040 | D24: A025 and A032 share a title and description; A012 and A040 share a title (Security Monitoring Reports). | E24: Reports could be filed under the wrong ID. | F24: Rename for clarity: A032 "Implementation Engineering Artifacts", A040 "PNSOC Security Monitoring Reports".

Sheet Performance
A1: Performance Against PWS Standards
A2: Calculated from the Submission Log. "Due to date" = on time + late + overdue. Rates are meaningless until past submissions are back-filled.
A4: Measure | B4: Value | C4: Target | D4: Status
A5: Submitted on time | B5: =COUNTIF('Submission Log'!$M$5:$M$400,"On time") -> 0
A6: Submitted late | B6: =COUNTIF('Submission Log'!$M$5:$M$400,"Late") -> 0
A7: Overdue, not submitted | B7: =COUNTIF('Submission Log'!$M$5:$M$400,"Overdue") -> 76
A8: Due to date | B8: =B5+B6+B7 -> 76
A9: On-time rate | B9: =IF(B8=0,"n/a",B5/B8) -> 0 | C9: =TargetOnTime -> 0.95 | D9: =IF(B9="n/a","n/a",IF(B9>=C9,"Meets","Below target")) -> Below target
A10: Decisions recorded (accepted + returned + deemed) | B10: =COUNTIF('Submission Log'!$H$5:$H$400,"Accepted")+COUNTIF('Submission Log'!$H$5:$H$400,"Returned")+COUNTIF('Submission Log'!$H$5:$H$400,"Deemed Accepted") -> 0
A11: Returned for rework | B11: =COUNTIF('Submission Log'!$H$5:$H$400,"Returned") -> 0
A12: Rework rate | B12: =IF(B10=0,"n/a",B11/B10) -> n/a | C12: =MaxRework -> 0.05 | D12: =IF(B12="n/a","n/a",IF(B12<C12,"Meets","Above limit")) -> n/a
A14: Task group (first PWS ref) | B14: On time | C14: Due to date | D14: On-time % | E14: Accepted % | F14: AQL | G14: Status
A15: PWS 6.1 | B15: =COUNTIFS('Submission Log'!$D$5:$D$400,"6.1",'Submission Log'!$M$5:$M$400,"On time") -> 0 | C15: =B15+COUNTIFS('Submission Log'!$D$5:$D$400,"6.1",'Submission Log'!$M$5:$M$400,"Late")+COUNTIFS('Submission Log'!$D$5:$D$400,"6.1",'Submission Log'!$M$5:$M$400,"Overdue") -> 24 | D15: =IF(C15=0,"n/a",B15/C15) -> 0 | E15: =IF(COUNTIFS('Submission Log'!$D$5:$D$400,"6.1",'Submission Log'!$H$5:$H$400,"Accepted")+COUNTIFS('Submission Log'!$D$5:$D$400,"6.1",'Submission Log'!$H$5:$H$400,"Returned")+COUNTIFS('Submission Log'!$D$5:$D$400,"6.1",'Submission Log'!$H$5:$H$400,"Deemed Accepted")=0,"n/a",(COUNTIFS('Submission Log'!$D$5:$D$400,"6.1",'Submission Log'!$H$5:$H$400,"Accepted")+COUNTIFS('Submission Log'!$D$5:$D$400,"6.1",'Submission Log'!$H$5:$H$400,"Deemed Accepted"))/(COUNTIFS('Submission Log'!$D$5:$D$400,"6.1",'Submission Log'!$H$5:$H$400,"Accepted")+COUNTIFS('Submission Log'!$D$5:$D$400,"6.1",'Submission Log'!$H$5:$H$400,"Returned")+COUNTIFS('Submission Log'!$D$5:$D$400,"6.1",'Submission Log'!$H$5:$H$400,"Deemed Accepted"))) -> n/a | F15: =AQL -> 0.9 | G15: =IF(AND(D15="n/a",E15="n/a"),"n/a",IF(AND(OR(D15="n/a",D15>=F15),OR(E15="n/a",E15>=F15)),"Meets","Below AQL")) -> Below AQL
A16: PWS 6.2 | B16: =COUNTIFS('Submission Log'!$D$5:$D$400,"6.2",'Submission Log'!$M$5:$M$400,"On time") -> 0 | C16: =B16+COUNTIFS('Submission Log'!$D$5:$D$400,"6.2",'Submission Log'!$M$5:$M$400,"Late")+COUNTIFS('Submission Log'!$D$5:$D$400,"6.2",'Submission Log'!$M$5:$M$400,"Overdue") -> 3 | D16: =IF(C16=0,"n/a",B16/C16) -> 0 | E16: =IF(COUNTIFS('Submission Log'!$D$5:$D$400,"6.2",'Submission Log'!$H$5:$H$400,"Accepted")+COUNTIFS('Submission Log'!$D$5:$D$400,"6.2",'Submission Log'!$H$5:$H$400,"Returned")+COUNTIFS('Submission Log'!$D$5:$D$400,"6.2",'Submission Log'!$H$5:$H$400,"Deemed Accepted")=0,"n/a",(COUNTIFS('Submission Log'!$D$5:$D$400,"6.2",'Submission Log'!$H$5:$H$400,"Accepted")+COUNTIFS('Submission Log'!$D$5:$D$400,"6.2",'Submission Log'!$H$5:$H$400,"Deemed Accepted"))/(COUNTIFS('Submission Log'!$D$5:$D$400,"6.2",'Submission Log'!$H$5:$H$400,"Accepted")+COUNTIFS('Submission Log'!$D$5:$D$400,"6.2",'Submission Log'!$H$5:$H$400,"Returned")+COUNTIFS('Submission Log'!$D$5:$D$400,"6.2",'Submission Log'!$H$5:$H$400,"Deemed Accepted"))) -> n/a | F16: =AQL -> 0.9 | G16: =IF(AND(D16="n/a",E16="n/a"),"n/a",IF(AND(OR(D16="n/a",D16>=F16),OR(E16="n/a",E16>=F16)),"Meets","Below AQL")) -> Below AQL
A17: PWS 6.3 | B17: =COUNTIFS('Submission Log'!$D$5:$D$400,"6.3",'Submission Log'!$M$5:$M$400,"On time") -> 0 | C17: =B17+COUNTIFS('Submission Log'!$D$5:$D$400,"6.3",'Submission Log'!$M$5:$M$400,"Late")+COUNTIFS('Submission Log'!$D$5:$D$400,"6.3",'Submission Log'!$M$5:$M$400,"Overdue") -> 49 | D17: =IF(C17=0,"n/a",B17/C17) -> 0 | E17: =IF(COUNTIFS('Submission Log'!$D$5:$D$400,"6.3",'Submission Log'!$H$5:$H$400,"Accepted")+COUNTIFS('Submission Log'!$D$5:$D$400,"6.3",'Submission Log'!$H$5:$H$400,"Returned")+COUNTIFS('Submission Log'!$D$5:$D$400,"6.3",'Submission Log'!$H$5:$H$400,"Deemed Accepted")=0,"n/a",(COUNTIFS('Submission Log'!$D$5:$D$400,"6.3",'Submission Log'!$H$5:$H$400,"Accepted")+COUNTIFS('Submission Log'!$D$5:$D$400,"6.3",'Submission Log'!$H$5:$H$400,"Deemed Accepted"))/(COUNTIFS('Submission Log'!$D$5:$D$400,"6.3",'Submission Log'!$H$5:$H$400,"Accepted")+COUNTIFS('Submission Log'!$D$5:$D$400,"6.3",'Submission Log'!$H$5:$H$400,"Returned")+COUNTIFS('Submission Log'!$D$5:$D$400,"6.3",'Submission Log'!$H$5:$H$400,"Deemed Accepted"))) -> n/a | F17: =AQL -> 0.9 | G17: =IF(AND(D17="n/a",E17="n/a"),"n/a",IF(AND(OR(D17="n/a",D17>=F17),OR(E17="n/a",E17>=F17)),"Meets","Below AQL")) -> Below AQL
A19: Open items
A20: Overdue (not submitted) | B20: =COUNTIF('Submission Log'!$M$5:$M$400,"Overdue") -> 76
A21: Due within 7 days | B21: =COUNTIF('Submission Log'!$M$5:$M$400,"Due within 7 days") -> 2
A22: Submitted, no Government decision | B22: =COUNTIFS('Submission Log'!$G$5:$G$400,"<>",'Submission Log'!$H$5:$H$400,"")+COUNTIFS('Submission Log'!$G$5:$G$400,"<>",'Submission Log'!$H$5:$H$400,"Pending") -> 0
A23: Past 5-business-day window (deemed accepted) | B23: =COUNTIF('Submission Log'!$K$5:$K$400,"Past*") -> 0
A24: Returned, awaiting resubmission | B24: =COUNTIFS('Submission Log'!$H$5:$H$400,"Returned",'Submission Log'!$L$5:$L$400,"<>") -> 0
A26: PWS AQL table (verbatim intent)
A27: PWS ¶ | B27: Standard | C27: AQL
A28: 6.1 | B28: Develop ZT AI integration design documentation per Government requirements. | C28: 90% detailed and submitted per schedule
A29: 6.2 | B29: Update and maintain the Thunderdome accreditation package. | C29: 90% accuracy; 90% timeliness; 90% current
A30: 6.3 | B30: Manage, maintain and update documentation; finalize presentations to Government templates. | C30: 90% of design and architecture plans accurate and accepted

Sheet Lists
A1: Lists
A2: Dropdown sources. Edit here, not on the other tabs.
A4: Gov decision | B4: Deliverable status | C4: Requirement status | D4: Cadence | E4: Task group
A5: Pending | B5: Not Started | C5: Not Started | D5: Weekly | E5: 6.1
A6: Accepted | B6: In Progress | C6: In Progress | D6: Monthly | E6: 6.2
A7: Returned | B7: Active - recurring | C7: Compliant | D7: Quarterly | E7: 6.3
A8: Deemed Accepted | B8: Complete | C8: At Risk | D8: One-time
B9: Not exercised (optional) | C9: Not exercised (optional) | D9: One-time + updates
B10: N/A | D10: Per package
D11: As needed
